Workbook
Name tt_Type: LISTS!$B$7:$B$14
Name tt_Dir: LISTS!$C$7:$C$14
Name tt_Src: LISTS!$D$7:$D$14
Name tt_Tax: LISTS!$E$7:$E$14
Name tt_Other: LISTS!$G$7:$G$14
Name lstTypes: LISTS!$B$7:$B$14
Name acctAR: LISTS!$K$7
Name acctAP: LISTS!$K$8
Name acctTax: LISTS!$K$9
Name acctCapital: LISTS!$K$10
Name acctDrawings: LISTS!$K$11
Name acctOBE: LISTS!$K$12
Name sys_Role: LISTS!$I$7:$I$12
Name sys_Acct: LISTS!$K$7:$K$12
Name sys_Check: LISTS!$L$7:$L$12
Name at_Type: LISTS!$N$7:$N$16
Name at_Stmt: LISTS!$O$7:$O$16
Name at_Sign: LISTS!$P$7:$P$16
Name at_Normal: LISTS!$Q$7:$Q$16
Name at_Section: LISTS!$R$7:$R$16
Name lstPayMethods: LISTS!$B$21:$B$35
Name lstBizTypes: LISTS!$C$21:$C$32
Name lstMonths: LISTS!$D$21:$D$32
Name lstYesNo: LISTS!$E$21:$E$22
Name lstCF: LISTS!$F$21:$F$24
Name lstNormal: LISTS!$G$21:$G$22
Name lstBuckets: LISTS!$H$21:$H$25
Name lstPayAccts: LISTS!$J$21:$J$50
Name lstAccounts: LISTS!$K$21:$K$170
Name BizName: SETUP!$C$6
Name BizType: SETUP!$C$7
Name OwnerName: SETUP!$C$8
Name BizAddress: SETUP!$C$9
Name BizEmail: SETUP!$C$10
Name BizPhone: SETUP!$C$11
Name StartDate: SETUP!$C$14
Name FYStartMonthName: SETUP!$C$15
Name Currency: SETUP!$C$16
Name OpenCash: SETUP!$C$17
Name OpenBank: SETUP!$C$18
Name DefaultTerms: SETUP!$C$19
Name TaxOn: SETUP!$C$22
Name TaxLabel: SETUP!$C$23
Name RptYear: SETUP!$C$26
Name RptMonth: SETUP!$C$27
Name RptStart: SETUP!$C$28
Name AsOf: SETUP!$C$29
Name FYStartMonth: SETUP!$C$30
Name FYStart: SETUP!$C$31
Name FYEnd: SETUP!$C$32
Name FYYM: SETUP!$C$33
Name RptIdx: SETUP!$C$34
Name PrevStart: SETUP!$C$35
Name PrevEnd: SETUP!$C$36
Name TermsDays: SETUP!$C$37
Name coa_Code: COA!$B$7:$B$156
Name coa_Name: COA!$C$7:$C$156
Name coa_Type: COA!$D$7:$D$156
Name coa_Normal: COA!$E$7:$E$156
Name coa_CF: COA!$F$7:$F$156

Sheet START_HERE
B2: SimpleLedger
B3: Small Business Accounting Workbook
B4: Know where your money goes, know how much you earn, and understand your business finances from one simple Excel workbook.
B5: ="Workbook for: "&BizName
B8: QUICK START
B9: =HYPERLINK("#SETUP!A1","1 · Setup") | C9: =HYPERLINK("#TRANSACTIONS!A1","2 · Record") | D9: =HYPERLINK("#DASHBOARD!A1","3 · Dashboard") | E9: =HYPERLINK("#PNL!A1","Profit & Loss") | F9: =HYPERLINK("#BALANCE_SHEET!A1","Balance Sheet") | G9: =HYPERLINK("#CASH_FLOW!A1","Cash Flow") | H9: =HYPERLINK("#HELP!A1","Help")
B10: =HYPERLINK("#AR!A1","Invoices (AR)") | C10: =HYPERLINK("#AP!A1","Bills (AP)") | D10: =HYPERLINK("#CUSTOMERS!A1","Customers") | E10: =HYPERLINK("#VENDORS!A1","Vendors") | F10: =HYPERLINK("#COA!A1","Accounts") | G10: =HYPERLINK("#MONTHLY_SUMMARY!A1","Monthly") | H10: =HYPERLINK("#LEDGER!A1","Ledger")
B12: YOUR WORKFLOW
B13: 1. Read this page | D13: Two minutes. It tells you where everything is.
B14: 2. Complete SETUP | D14: Business name, start date, currency, beginning cash and bank balances.
B15: 3. Add customers and vendors | D15: Optional but recommended: CUSTOMERS and VENDORS sheets.
B16: 4. Record transactions | D16: Every sale, expense, payment and transfer — one row each on TRANSACTIONS.
B17: 5. Record credit sales and unpaid bills | D17: Invoices you will be paid for later → AR. Bills you will pay later → AP.
B18: 6. Review the DASHBOARD | D18: Pick the month at the top. Revenue, expenses, profit and cash update automatically.
B19: 7. Review monthly reports | D19: Profit & Loss, Balance Sheet, Cash Flow, Monthly Summary.
B20: 8. Fix warnings | D20: The Dashboard's Data Health box lists anything that needs attention (⛔ / ⚠).
B21: 9. Export / share | D21: File → Print or Save as PDF on any report sheet. Reports are print-ready.
B23: COLOUR GUIDE
B24: Yellow cell | C24: A setting you fill in (SETUP, LISTS, report filters).
B25: White table column | C25: Where you type your data (dark-blue header).
B26: Grey cell / column | C26: Automatic. Calculated for you — do not type here.
B27: ⛔ Error | C27: The row is NOT included in reports until you fix it.
B28: ⚠ Warning | C28: Included in reports, but please double-check.
B29: ✓ OK | C29: All good.
B31: GOOD TO KNOW
B32: • Everything is calculated from three input sheets: TRANSACTIONS, AR and AP. Reports never need typing.
B33: • No accounting knowledge needed: choose a Type (Money In / Money Out …) and a Category. Debits and credits are automatic.
B34: • Don't delete or rename sheets. Don't type over grey cells. Most report sheets are protected (no password) to prevent accidents.
B35: • Capacity: 2,000 transactions, 500 invoices and 500 bills per workbook — plenty for a typical small business year. Start a fresh copy each fiscal year.
B36: • Keep a backup: save a dated copy at the end of every month (e.g. Books-2026-09.xlsx).
B37: • Requires Microsoft Excel 2010 or later (Windows or Mac) or Microsoft 365. No macros.
B39: SimpleLedger v1.0.0

Sheet SETUP
B1: Setup
B2: Fill in the yellow cells once. Everything else in the workbook reads from here.
B5: BUSINESS DETAILS
B6: Business name | C6: Sunrise Bakery & Café | D6: Shown on every report header.
B7: Business type | C7: Food & Beverage | D7: Pick the closest match.
B8: Owner name | C8: Maria Santos
B9: Business address | C9: 123 Mabini St., Quezon City
B10: Email | C10: hello@sunrisebakery.example
B11: Phone | C11: 0917 555 0100
B13: ACCOUNTING SETTINGS
B14: Accounting start date | C14: 46023 | D14: The day you start recording in this workbook. Opening balances are as of this date.
B15: Fiscal year starts in | C15: January | D15: Most small businesses use January (calendar year).
B16: Currency (code or symbol) | C16: PHP | D16: Used in report headings, e.g. PHP, USD, ₱, $.
B17: Beginning cash on hand | C17: 15000 | D17: Cash you physically had on the start date. Posts to 'Cash on Hand'.
B18: Beginning bank balance | C18: 285000 | D18: Bank balance on the start date. Posts to 'Bank Account'. Other opening balances: COA sheet.
B19: Default payment terms (days) | C19: 30 | D19: Used for invoice/bill due dates when you leave Due Date blank.
B21: TAX SETTINGS
B22: Track VAT / sales tax separately? | C22: Yes | D22: Yes = the Tax column is posted to the Tax Payable account. No = tax columns are ignored.
B23: Tax name | C23: VAT | D23: e.g. VAT, GST, Sales Tax. Used in labels only.
B25: REPORT PERIOD (automatic — choose the month on the Dashboard) | D25: =HYPERLINK("#DASHBOARD!C5","→ Change report month on the Dashboard")
B26: Report year | C26: =IF(ISNUMBER(RptYearIn),RptYearIn,YEAR(TODAY()))
B27: Report month (1-12) | C27: =IFERROR(MATCH(RptMonthIn,lstMonths,0),MONTH(TODAY()))
B28: Report period start | C28: =DATE(RptYear,RptMonth,1)
B29: Report period end (as-of date) | C29: =EOMONTH(RptStart,0)
B30: Fiscal year start month (1-12) | C30: =IFERROR(MATCH(FYStartMonthName,lstMonths,0),1)
B31: Fiscal year start | C31: =DATE(RptYear-IF(RptMonth<FYStartMonth,1,0),FYStartMonth,1)
B32: Fiscal year end | C32: =EDATE(FYStart,12)-1
B33: Fiscal year start (year*12+month) | C33: =YEAR(FYStart)*12+MONTH(FYStart)
B34: Report month number within fiscal year | C34: =YEAR(RptStart)*12+MONTH(RptStart)-FYYM+1
B35: Previous month start | C35: =EDATE(RptStart,-1)
B36: Previous month end | C36: =RptStart-1
B37: Default terms used | C37: =IF(ISNUMBER(DefaultTerms),DefaultTerms,30)

Sheet DASHBOARD
B1: Financial Dashboard | P1: Chart data (automatic)
B2: =BizName
P3: Month | Q3: Revenue | R3: Expenses | S3: Net Profit
P4: =MONTHLY_SUMMARY!B7 | Q4: =MONTHLY_SUMMARY!C7 | R4: =MONTHLY_SUMMARY!C7-MONTHLY_SUMMARY!H7 | S4: =MONTHLY_SUMMARY!H7
B5: Report month | C5: September | E5: Year | F5: 2026 | H5: ="Period: "&TEXT(RptStart,"mmmm yyyy")&" · Year to date from "&TEXT(FYStart,"dd mmm yyyy")&" · "&Currency | P5: =MONTHLY_SUMMARY!B8 | Q5: =MONTHLY_SUMMARY!C8 | R5: =MONTHLY_SUMMARY!C8-MONTHLY_SUMMARY!H8 | S5: =MONTHLY_SUMMARY!H8
P6: =MONTHLY_SUMMARY!B9 | Q6: =MONTHLY_SUMMARY!C9 | R6: =MONTHLY_SUMMARY!C9-MONTHLY_SUMMARY!H9 | S6: =MONTHLY_SUMMARY!H9
B7: REVENUE · THIS MONTH | E7: EXPENSES · THIS MONTH | H7: NET PROFIT · THIS MONTH | K7: CASH BALANCE · MONTH END | P7: =MONTHLY_SUMMARY!B10 | Q7: =MONTHLY_SUMMARY!C10 | R7: =MONTHLY_SUMMARY!C10-MONTHLY_SUMMARY!H10 | S7: =MONTHLY_SUMMARY!H10
B8: =PL_Rev_Cur | E8: =PL_COS_Cur+PL_Opex_Cur+PL_OthExp_Cur | H8: =PL_Net_Cur | K8: =CF_End_Cur | P8: =MONTHLY_SUMMARY!B11 | Q8: =MONTHLY_SUMMARY!C11 | R8: =MONTHLY_SUMMARY!C11-MONTHLY_SUMMARY!H11 | S8: =MONTHLY_SUMMARY!H11
B9: ="Year to date: "&TEXT(PL_Rev_YTD,"#,##0") | E9: ="Year to date: "&TEXT(PL_COS_YTD+PL_Opex_YTD+PL_OthExp_YTD,"#,##0") | H9: ="Year to date: "&TEXT(PL_Net_YTD,"#,##0;(#,##0)") | K9: ="Change this month: "&TEXT(CF_Net_Cur,"+#,##0;-#,##0;0") | P9: =MONTHLY_SUMMARY!B12 | Q9: =MONTHLY_SUMMARY!C12 | R9: =MONTHLY_SUMMARY!C12-MONTHLY_SUMMARY!H12 | S9: =MONTHLY_SUMMARY!H12
P10: =MONTHLY_SUMMARY!B13 | Q10: =MONTHLY_SUMMARY!C13 | R10: =MONTHLY_SUMMARY!C13-MONTHLY_SUMMARY!H13 | S10: =MONTHLY_SUMMARY!H13
B11: RECEIVABLES · CUSTOMERS OWE YOU | E11: PAYABLES · YOU OWE SUPPLIERS | H11: GROSS MARGIN · YEAR TO DATE | K11: NET MARGIN · YEAR TO DATE | P11: =MONTHLY_SUMMARY!B14 | Q11: =MONTHLY_SUMMARY!C14 | R11: =MONTHLY_SUMMARY!C14-MONTHLY_SUMMARY!H14 | S11: =MONTHLY_SUMMARY!H14
B12: =SUMIFS(calc_Bal,calc_Name,acctAR) | E12: =-SUMIFS(calc_Bal,calc_Name,acctAP) | H12: =IF(PL_GM_YTD="","",PL_GM_YTD) | K12: =IF(PL_NM_YTD="","",PL_NM_YTD) | P12: =MONTHLY_SUMMARY!B15 | Q12: =MONTHLY_SUMMARY!C15 | R12: =MONTHLY_SUMMARY!C15-MONTHLY_SUMMARY!H15 | S12: =MONTHLY_SUMMARY!H15
B13: ="Overdue: "&TEXT(SUMIFS(ar_Balance,ar_Status,"Overdue"),"#,##0") | E13: ="Overdue: "&TEXT(SUMIFS(ap_Balance,ap_Status,"Overdue"),"#,##0") | H13: ="This month: "&IF(PL_GM_Cur="","-",TEXT(PL_GM_Cur,"0.0%")) | K13: ="This month: "&IF(PL_NM_Cur="","-",TEXT(PL_NM_Cur,"0.0%")) | P13: =MONTHLY_SUMMARY!B16 | Q13: =MONTHLY_SUMMARY!C16 | R13: =MONTHLY_SUMMARY!C16-MONTHLY_SUMMARY!H16 | S13: =MONTHLY_SUMMARY!H16
P14: =MONTHLY_SUMMARY!B17 | Q14: =MONTHLY_SUMMARY!C17 | R14: =MONTHLY_SUMMARY!C17-MONTHLY_SUMMARY!H17 | S14: =MONTHLY_SUMMARY!H17
B15: DATA HEALTH | P15: =MONTHLY_SUMMARY!B18 | Q15: =MONTHLY_SUMMARY!C18 | R15: =MONTHLY_SUMMARY!C18-MONTHLY_SUMMARY!H18 | S15: =MONTHLY_SUMMARY!H18
B16: Trial balance | D16: =TB_Status | H16: Entries with warnings | J16: =IF(COUNTIF(tx_Warn,"?*")+COUNTIF(ar_Warn,"?*")+COUNTIF(ap_Warn,"?*")=0,"✓ None","⚠ "&COUNTIF(tx_Warn,"?*")+COUNTIF(ar_Warn,"?*")+COUNTIF(ap_Warn,"?*")&" to review")
B17: Balance sheet | D17: =IF(BS_Diff=0,"✓ Balanced","⚠ Out of balance by "&TEXT(BS_Diff,"#,##0.00")) | H17: Receivables register | J17: =IF(ROUND(SUM(ar_Balance)-SUMIFS(calc_Bal,calc_Name,acctAR),2)=0,"✓ Matches the ledger","⚠ Differs from ledger by "&TEXT(SUM(ar_Balance)-SUMIFS(calc_Bal,calc_Name,acctAR),"#,##0.00")) | P17: Top expenses (YTD) | Q17: Amount
B18: Cash flow | D18: =IF(LEFT(CF_Status,1)="✓","✓ Reconciles","⚠ Does not reconcile") | H18: Payables register | J18: =IF(ROUND(SUM(ap_Balance)-(-SUMIFS(calc_Bal,calc_Name,acctAP)),2)=0,"✓ Matches the ledger","⚠ Differs from ledger by "&TEXT(SUM(ap_Balance)-(-SUMIFS(calc_Bal,calc_Name,acctAP)),"#,##0.00")) | P18: =IFERROR(INDEX(calc_Name,MATCH(LARGE(calc_TopKey,1),calc_TopKey,0)),"") | Q18: =IF(P18="",0,INDEX(calc_YTD,MATCH(P18,calc_Name,0)))
B19: Entries with errors | D19: =IF(COUNTIF(tx_Err,"?*")+COUNTIF(ar_Err,"?*")+COUNTIF(ap_Err,"?*")=0,"✓ None","⛔ "&COUNTIF(tx_Err,"?*")+COUNTIF(ar_Err,"?*")+COUNTIF(ap_Err,"?*")&" not posted — see the Check column") | H19: Setup | J19: =IF(COUNTIF(sys_Check,"⛔*")+COUNTIF(coa_Check,"⛔*")>0,"⛔ Fix the Chart of Accounts / Lists",IF(COUNT(tx_Date)>1800,"⚠ Transactions sheet is nearly full","✓ OK")) | P19: =IFERROR(INDEX(calc_Name,MATCH(LARGE(calc_TopKey,2),calc_TopKey,0)),"") | Q19: =IF(P19="",0,INDEX(calc_YTD,MATCH(P19,calc_Name,0)))
P20: =IFERROR(INDEX(calc_Name,MATCH(LARGE(calc_TopKey,3),calc_TopKey,0)),"") | Q20: =IF(P20="",0,INDEX(calc_YTD,MATCH(P20,calc_Name,0)))
P21: =IFERROR(INDEX(calc_Name,MATCH(LARGE(calc_TopKey,4),calc_TopKey,0)),"") | Q21: =IF(P21="",0,INDEX(calc_YTD,MATCH(P21,calc_Name,0)))
P22: =IFERROR(INDEX(calc_Name,MATCH(LARGE(calc_TopKey,5),calc_TopKey,0)),"") | Q22: =IF(P22="",0,INDEX(calc_YTD,MATCH(P22,calc_Name,0)))
P24: Aging (days overdue) | Q24: Receivables | R24: Payables
P25: Current | Q25: =SUMIFS(ar_Balance,ar_Bucket,P25) | R25: =SUMIFS(ap_Balance,ap_Bucket,P25)
P26: 1-30 | Q26: =SUMIFS(ar_Balance,ar_Bucket,P26) | R26: =SUMIFS(ap_Balance,ap_Bucket,P26)
P27: 31-60 | Q27: =SUMIFS(ar_Balance,ar_Bucket,P27) | R27: =SUMIFS(ap_Balance,ap_Bucket,P27)
P28: 61-90 | Q28: =SUMIFS(ar_Balance,ar_Bucket,P28) | R28: =SUMIFS(ap_Balance,ap_Bucket,P28)
P29: 90+ | Q29: =SUMIFS(ar_Balance,ar_Bucket,P29) | R29: =SUMIFS(ap_Balance,ap_Bucket,P29)
B54: CASH FLOW · THIS MONTH | H54: WHO OWES WHOM
B55: Cash at start of month | E55: =CF_Begin_Cur | H55: Receivables due in the next 14 days | L55: =SUMIFS(ar_Balance,ar_EffDue,">="&AsOf,ar_EffDue,"<="&(AsOf+14))
B56: + Operating activities | E56: =CF_Op_Cur | H56: Payables due in the next 14 days | L56: =SUMIFS(ap_Balance,ap_EffDue,">="&AsOf,ap_EffDue,"<="&(AsOf+14))
B57: + Investing activities | E57: =CF_Inv_Cur
B58: + Financing activities | E58: =CF_Fin_Cur | H58: Top customers owing you | K58: Top vendors you owe
B59: Cash at end of month | E59: =CF_End_Cur | H59: =IFERROR(INDEX(cust_Name,MATCH(LARGE(cust_TopKey,1),cust_TopKey,0)),"") | J59: =IF(H59="","",INDEX(cust_Outstanding,MATCH(H59,cust_Name,0))) | K59: =IFERROR(INDEX(vend_Name,MATCH(LARGE(vend_TopKey,1),vend_TopKey,0)),"") | M59: =IF(K59="","",INDEX(vend_Outstanding,MATCH(K59,vend_Name,0)))
H60: =IFERROR(INDEX(cust_Name,MATCH(LARGE(cust_TopKey,2),cust_TopKey,0)),"") | J60: =IF(H60="","",INDEX(cust_Outstanding,MATCH(H60,cust_Name,0))) | K60: =IFERROR(INDEX(vend_Name,MATCH(LARGE(vend_TopKey,2),vend_TopKey,0)),"") | M60: =IF(K60="","",INDEX(vend_Outstanding,MATCH(K60,vend_Name,0)))
H61: =IFERROR(INDEX(cust_Name,MATCH(LARGE(cust_TopKey,3),cust_TopKey,0)),"") | J61: =IF(H61="","",INDEX(cust_Outstanding,MATCH(H61,cust_Name,0))) | K61: =IFERROR(INDEX(vend_Name,MATCH(LARGE(vend_TopKey,3),vend_TopKey,0)),"") | M61: =IF(K61="","",INDEX(vend_Outstanding,MATCH(K61,vend_Name,0)))

Sheet TRANSACTIONS
B1: Transactions
B2: Record every money movement here: sales, expenses, payments, transfers. One row = one transaction. | H2: Example: 15-Jan-2026 | Money Out | Rent | Shop rent January | … | Bank Account | 15,000.00
B4: Tip: work top-to-bottom, one row per entry. Rows with ⛔ are NOT included in reports until fixed; ⚠ rows are included but worth a look.
B5: ▼ YOUR ENTRIES (white columns — type or pick from the dropdown) | O5: ▼ AUTOMATIC (grey columns — calculated, do not type)
B6: Transaction ID | C6: Date | D6: Type | E6: Category (Account) | F6: Description | G6: Customer | H6: Vendor | I6: Payment Method | J6: Reference No. / Invoice # / Bill # | K6: Paid From / Deposited To | L6: Amount (incl. tax) | M6: Tax | N6: Notes | O6: Net Amount | P6: Account Type | Q6: Debit Account | R6: Credit Account | S6: Check | T6: Blank? | U6: Direction | V6: Other side | W6: Tax used | X6: Error | Y6: Warning | Z6: Posted | AA6: Debit Amt | AB6: Credit Amt | AC6: Tax Debit | AD6: Tax Credit
B7: TX-0001 | C7: 46023 | D7: Money Out | E7: Rent | F7: Shop rent | I7: Bank Transfer | J7: RENT-01 | K7: Bank Account | L7: 28000 | M7: 3000 | O7: =IF(Z7=1,L7-W7,"") | P7: =IF(V7="","",IFERROR(INDEX(coa_Type,MATCH(V7,coa_Name,0)),"")) | Q7: =IF(Z7=1,IF(U7="In",K7&"",V7),"") | R7: =IF(Z7=1,IF(U7="In",V7,K7&""),"") | S7: =IF(X7<>"","⛔ "&X7&" — not posted",IF(Y7<>"","⚠ "&Y7,IF(Z7=1,"✓ OK",""))) | T7: =IF(AND(C7="",D7="",E7="",L7="",K7=""),1,0) | U7: =IFERROR(INDEX(tt_Dir,MATCH(D7,tt_Type,0)),"") | V7: =IF(D7="","",IFERROR(IF(INDEX(tt_Other,MATCH(D7,tt_Type,0))="",E7&"",INDEX(tt_Other,MATCH(D7,tt_Type,0))),"")) | W7: =IF(OR(TaxOn<>"Yes",NOT(ISNUMBER(M7))),0,IF(IFERROR(INDEX(tt_Tax,MATCH(D7,tt_Type,0)),"No")="Yes",M7,0)) | X7: =IF(T7=1,"",IF(C7="","Missing transaction date",IF(NOT(ISNUMBER(C7)),"Invalid date",IF(OR(C7<DATE(2000,1,1),C7>DATE(2099,12,31)),"Invalid date",IF(D7="","Select a type",IF(U7="","Unknown type: "&D7,IF(V7="","Select an account (Category)",IF(ISNA(MATCH(V7,coa_Name,0)),"Unknown account: "&V7,IF(K7="","Select Paid From / Deposited To",IF(ISNA(MATCH(K7,coa_Name,0)),"Unknown account: "&K7,IF(NOT(ISNUMBER(L7)),"Enter an amount",IF(L7=0,"Enter an amount",IF(ABS(W7)>ABS(L7),"Tax is larger than the amount",""))))))))))))) | Y7: =IF(OR(T7=1,X7<>""),"",IF(AND(B7<>"",COUNTIF(tx_ID,B7)>1),"Duplicate transaction ID",IF(AND(L7<0,D7<>"Adjustment"),"Negative amount — check this entry",IF(AND(D7="Customer Payment",G7=""),"Add the customer",IF(AND(D7="Customer Payment",OR(J7="",COUNTIF(ar_No,J7&"")=0)),"Invoice # in Reference not found on AR sheet",IF(AND(D7="Bill Payment",H7=""),"Add the vendor",IF(AND(D7="Bill Payment",OR(J7="",COUNTIFS(ap_No,J7&"",ap_Party,H7&"")=0)),"Bill # + vendor not found on AP sheet",IF(AND(ISNUMBER(M7),N(M7)<>0,W7=0),"Tax ignored (tax tracking off, or not allowed for this type)",IF(V7=K7&"","Same account on both sides",IF(AND(ISNUMBER(StartDate),C7<StartDate),"Date is before the accounting start date",IF(AND(D7<>"Adjustment",IFERROR(INDEX(coa_Pay,MATCH(K7&"",coa_Name,0)),"")<>"Yes"),"Paid From / Deposited To is not a payment account",""))))))))))) | Z7: =IF(AND(T7=0,X7=""),1,0) | AA7: =IF(Z7=1,IF(U7="In",L7,L7-W7),0) | AB7: =IF(Z7=1,IF(U7="In",L7-W7,L7),0) | AC7: =IF(AND(Z7=1,U7="Out"),W7,0) | AD7: =IF(AND(Z7=1,U7="In"),W7,0)
B8: TX-0002 | C8: 46026 | D8: Money In | E8: Product Sales | F8: Counter sales week 1 | I8: Cash | K8: Cash on Hand | L8: 43084.99 | M8: 4616.25 | O8: =IF(Z8=1,L8-W8,"") | P8: =IF(V8="","",IFERROR(INDEX(coa_Type,MATCH(V8,coa_Name,0)),"")) | Q8: =IF(Z8=1,IF(U8="In",K8&"",V8),"") | R8: =IF(Z8=1,IF(U8="In",V8,K8&""),"") | S8: =IF(X8<>"","⛔ "&X8&" — not posted",IF(Y8<>"","⚠ "&Y8,IF(Z8=1,"✓ OK",""))) | T8: =IF(AND(C8="",D8="",E8="",L8="",K8=""),1,0) | U8: =IFERROR(INDEX(tt_Dir,MATCH(D8,tt_Type,0)),"") | V8: =IF(D8="","",IFERROR(IF(INDEX(tt_Other,MATCH(D8,tt_Type,0))="",E8&"",INDEX(tt_Other,MATCH(D8,tt_Type,0))),"")) | W8: =IF(OR(TaxOn<>"Yes",NOT(ISNUMBER(M8))),0,IF(IFERROR(INDEX(tt_Tax,MATCH(D8,tt_Type,0)),"No")="Yes",M8,0)) | X8: =IF(T8=1,"",IF(C8="","Missing transaction date",IF(NOT(ISNUMBER(C8)),"Invalid date",IF(OR(C8<DATE(2000,1,1),C8>DATE(2099,12,31)),"Invalid date",IF(D8="","Select a type",IF(U8="","Unknown type: "&D8,IF(V8="","Select an account (Category)",IF(ISNA(MATCH(V8,coa_Name,0)),"Unknown account: "&V8,IF(K8="","Select Paid From / Deposited To",IF(ISNA(MATCH(K8,coa_Name,0)),"Unknown account: "&K8,IF(NOT(ISNUMBER(L8)),"Enter an amount",IF(L8=0,"Enter an amount",IF(ABS(W8)>ABS(L8),"Tax is larger than the amount",""))))))))))))) | Y8: =IF(OR(T8=1,X8<>""),"",IF(AND(B8<>"",COUNTIF(tx_ID,B8)>1),"Duplicate transaction ID",IF(AND(L8<0,D8<>"Adjustment"),"Negative amount — check this entry",IF(AND(D8="Customer Payment",G8=""),"Add the customer",IF(AND(D8="Customer Payment",OR(J8="",COUNTIF(ar_No,J8&"")=0)),"Invoice # in Reference not found on AR sheet",IF(AND(D8="Bill Payment",H8=""),"Add the vendor",IF(AND(D8="Bill Payment",OR(J8="",COUNTIFS(ap_No,J8&"",ap_Party,H8&"")=0)),"Bill # + vendor not found on AP sheet",IF(AND(ISNUMBER(M8),N(M8)<>0,W8=0),"Tax ignored (tax tracking off, or not allowed for this type)",IF(V8=K8&"","Same account on both sides",IF(AND(ISNUMBER(StartDate),C8<StartDate),"Date is before the accounting start date",IF(AND(D8<>"Adjustment",IFERROR(INDEX(coa_Pay,MATCH(K8&"",coa_Name,0)),"")<>"Yes"),"Paid From / Deposited To is not a payment account",""))))))))))) | Z8: =IF(AND(T8=0,X8=""),1,0) | AA8: =IF(Z8=1,IF(U8="In",L8,L8-W8),0) | AB8: =IF(Z8=1,IF(U8="In",L8-W8,L8),0) | AC8: =IF(AND(Z8=1,U8="Out"),W8,0) | AD8: =IF(AND(Z8=1,U8="In"),W8,0)
B9: TX-0003 | C9: 46027 | D9: Money In | E9: Product Sales | F9: GCash / online orders week 1 | I9: E-Wallet | K9: E-Wallet / Online Payments | L9: 16978.36 | M9: 1819.11 | O9: =IF(Z9=1,L9-W9,"") | P9: =IF(V9="","",IFERROR(INDEX(coa_Type,MATCH(V9,coa_Name,0)),"")) | Q9: =IF(Z9=1,IF(U9="In",K9&"",V9),"") | R9: =IF(Z9=1,IF(U9="In",V9,K9&""),"") | S9: =IF(X9<>"","⛔ "&X9&" — not posted",IF(Y9<>"","⚠ "&Y9,IF(Z9=1,"✓ OK",""))) | T9: =IF(AND(C9="",D9="",E9="",L9="",K9=""),1,0) | U9: =IFERROR(INDEX(tt_Dir,MATCH(D9,tt_Type,0)),"") | V9: =IF(D9="","",IFERROR(IF(INDEX(tt_Other,MATCH(D9,tt_Type,0))="",E9&"",INDEX(tt_Other,MATCH(D9,tt_Type,0))),"")) | W9: =IF(OR(TaxOn<>"Yes",NOT(ISNUMBER(M9))),0,IF(IFERROR(INDEX(tt_Tax,MATCH(D9,tt_Type,0)),"No")="Yes",M9,0)) | X9: =IF(T9=1,"",IF(C9="","Missing transaction date",IF(NOT(ISNUMBER(C9)),"Invalid date",IF(OR(C9<DATE(2000,1,1),C9>DATE(2099,12,31)),"Invalid date",IF(D9="","Select a type",IF(U9="","Unknown type: "&D9,IF(V9="","Select an account (Category)",IF(ISNA(MATCH(V9,coa_Name,0)),"Unknown account: "&V9,IF(K9="","Select Paid From / Deposited To",IF(ISNA(MATCH(K9,coa_Name,0)),"Unknown account: "&K9,IF(NOT(ISNUMBER(L9)),"Enter an amount",IF(L9=0,"Enter an amount",IF(ABS(W9)>ABS(L9),"Tax is larger than the amount",""))))))))))))) | Y9: =IF(OR(T9=1,X9<>""),"",IF(AND(B9<>"",COUNTIF(tx_ID,B9)>1),"Duplicate transaction ID",IF(AND(L9<0,D9<>"Adjustment"),"Negative amount — check this entry",IF(AND(D9="Customer Payment",G9=""),"Add the customer",IF(AND(D9="Customer Payment",OR(J9="",COUNTIF(ar_No,J9&"")=0)),"Invoice # in Reference not found on AR sheet",IF(AND(D9="Bill Payment",H9=""),"Add the vendor",IF(AND(D9="Bill Payment",OR(J9="",COUNTIFS(ap_No,J9&"",ap_Party,H9&"")=0)),"Bill # + vendor not found on AP sheet",IF(AND(ISNUMBER(M9),N(M9)<>0,W9=0),"Tax ignored (tax tracking off, or not allowed for this type)",IF(V9=K9&"","Same account on both sides",IF(AND(ISNUMBER(StartDate),C9<StartDate),"Date is before the accounting start date",IF(AND(D9<>"Adjustment",IFERROR(INDEX(coa_Pay,MATCH(K9&"",coa_Name,0)),"")<>"Yes"),"Paid From / Deposited To is not a payment account",""))))))))))) | Z9: =IF(AND(T9=0,X9=""),1,0) | AA9: =IF(Z9=1,IF(U9="In",L9,L9-W9),0) | AB9: =IF(Z9=1,IF(U9="In",L9-W9,L9),0) | AC9: =IF(AND(Z9=1,U9="Out"),W9,0) | AD9: =IF(AND(Z9=1,U9="In"),W9,0)
B10: TX-0004 | C10: 46028 | D10: Transfer | E10: Bank Account | F10: Cash deposit to bank | I10: Cash | K10: Cash on Hand | L10: 36600 | O10: =IF(Z10=1,L10-W10,"") | P10: =IF(V10="","",IFERROR(INDEX(coa_Type,MATCH(V10,coa_Name,0)),"")) | Q10: =IF(Z10=1,IF(U10="In",K10&"",V10),"") | R10: =IF(Z10=1,IF(U10="In",V10,K10&""),"") | S10: =IF(X10<>"","⛔ "&X10&" — not posted",IF(Y10<>"","⚠ "&Y10,IF(Z10=1,"✓ OK",""))) | T10: =IF(AND(C10="",D10="",E10="",L10="",K10=""),1,0) | U10: =IFERROR(INDEX(tt_Dir,MATCH(D10,tt_Type,0)),"") | V10: =IF(D10="","",IFERROR(IF(INDEX(tt_Other,MATCH(D10,tt_Type,0))="",E10&"",INDEX(tt_Other,MATCH(D10,tt_Type,0))),"")) | W10: =IF(OR(TaxOn<>"Yes",NOT(ISNUMBER(M10))),0,IF(IFERROR(INDEX(tt_Tax,MATCH(D10,tt_Type,0)),"No")="Yes",M10,0)) | X10: =IF(T10=1,"",IF(C10="","Missing transaction date",IF(NOT(ISNUMBER(C10)),"Invalid date",IF(OR(C10<DATE(2000,1,1),C10>DATE(2099,12,31)),"Invalid date",IF(D10="","Select a type",IF(U10="","Unknown type: "&D10,IF(V10="","Select an account (Category)",IF(ISNA(MATCH(V10,coa_Name,0)),"Unknown account: "&V10,IF(K10="","Select Paid From / Deposited To",IF(ISNA(MATCH(K10,coa_Name,0)),"Unknown account: "&K10,IF(NOT(ISNUMBER(L10)),"Enter an amount",IF(L10=0,"Enter an amount",IF(ABS(W10)>ABS(L10),"Tax is larger than the amount",""))))))))))))) | Y10: =IF(OR(T10=1,X10<>""),"",IF(AND(B10<>"",COUNTIF(tx_ID,B10)>1),"Duplicate transaction ID",IF(AND(L10<0,D10<>"Adjustment"),"Negative amount — check this entry",IF(AND(D10="Customer Payment",G10=""),"Add the customer",IF(AND(D10="Customer Payment",OR(J10="",COUNTIF(ar_No,J10&"")=0)),"Invoice # in Reference not found on AR sheet",IF(AND(D10="Bill Payment",H10=""),"Add the vendor",IF(AND(D10="Bill Payment",OR(J10="",COUNTIFS(ap_No,J10&"",ap_Party,H10&"")=0)),"Bill # + vendor not found on AP sheet",IF(AND(ISNUMBER(M10),N(M10)<>0,W10=0),"Tax ignored (tax tracking off, or not allowed for this type)",IF(V10=K10&"","Same account on both sides",IF(AND(ISNUMBER(StartDate),C10<StartDate),"Date is before the accounting start date",IF(AND(D10<>"Adjustment",IFERROR(INDEX(coa_Pay,MATCH(K10&"",coa_Name,0)),"")<>"Yes"),"Paid From / Deposited To is not a payment account",""))))))))))) | Z10: =IF(AND(T10=0,X10=""),1,0) | AA10: =IF(Z10=1,IF(U10="In",L10,L10-W10),0) | AB10: =IF(Z10=1,IF(U10="In",L10-W10,L10),0) | AC10: =IF(AND(Z10=1,U10="Out"),W10,0) | AD10: =IF(AND(Z10=1,U10="In"),W10,0)
B11: TX-0005 | C11: 46028 | D11: Money Out | E11: Other Direct Costs | F11: Boxes & paper bags (market) | I11: Cash | K11: Cash on Hand | L11: 2776.35 | M11: 297.47 | O11: =IF(Z11=1,L11-W11,"") | P11: =IF(V11="","",IFERROR(INDEX(coa_Type,MATCH(V11,coa_Name,0)),"")) | Q11: =IF(Z11=1,IF(U11="In",K11&"",V11),"") | R11: =IF(Z11=1,IF(U11="In",V11,K11&""),"") | S11: =IF(X11<>"","⛔ "&X11&" — not posted",IF(Y11<>"","⚠ "&Y11,IF(Z11=1,"✓ OK",""))) | T11: =IF(AND(C11="",D11="",E11="",L11="",K11=""),1,0) | U11: =IFERROR(INDEX(tt_Dir,MATCH(D11,tt_Type,0)),"") | V11: =IF(D11="","",IFERROR(IF(INDEX(tt_Other,MATCH(D11,tt_Type,0))="",E11&"",INDEX(tt_Other,MATCH(D11,tt_Type,0))),"")) | W11: =IF(OR(TaxOn<>"Yes",NOT(ISNUMBER(M11))),0,IF(IFERROR(INDEX(tt_Tax,MATCH(D11,tt_Type,0)),"No")="Yes",M11,0)) | X11: =IF(T11=1,"",IF(C11="","Missing transaction date",IF(NOT(ISNUMBER(C11)),"Invalid date",IF(OR(C11<DATE(2000,1,1),C11>DATE(2099,12,31)),"Invalid date",IF(D11="","Select a type",IF(U11="","Unknown type: "&D11,IF(V11="","Select an account (Category)",IF(ISNA(MATCH(V11,coa_Name,0)),"Unknown account: "&V11,IF(K11="","Select Paid From / Deposited To",IF(ISNA(MATCH(K11,coa_Name,0)),"Unknown account: "&K11,IF(NOT(ISNUMBER(L11)),"Enter an amount",IF(L11=0,"Enter an amount",IF(ABS(W11)>ABS(L11),"Tax is larger than the amount",""))))))))))))) | Y11: =IF(OR(T11=1,X11<>""),"",IF(AND(B11<>"",COUNTIF(tx_ID,B11)>1),"Duplicate transaction ID",IF(AND(L11<0,D11<>"Adjustment"),"Negative amount — check this entry",IF(AND(D11="Customer Payment",G11=""),"Add the customer",IF(AND(D11="Customer Payment",OR(J11="",COUNTIF(ar_No,J11&"")=0)),"Invoice # in Reference not found on AR sheet",IF(AND(D11="Bill Payment",H11=""),"Add the vendor",IF(AND(D11="Bill Payment",OR(J11="",COUNTIFS(ap_No,J11&"",ap_Party,H11&"")=0)),"Bill # + vendor not found on AP sheet",IF(AND(ISNUMBER(M11),N(M11)<>0,W11=0),"Tax ignored (tax tracking off, or not allowed for this type)",IF(V11=K11&"","Same account on both sides",IF(AND(ISNUMBER(StartDate),C11<StartDate),"Date is before the accounting start date",IF(AND(D11<>"Adjustment",IFERROR(INDEX(coa_Pay,MATCH(K11&"",coa_Name,0)),"")<>"Yes"),"Paid From / Deposited To is not a payment account",""))))))))))) | Z11: =IF(AND(T11=0,X11=""),1,0) | AA11: =IF(Z11=1,IF(U11="In",L11,L11-W11),0) | AB11: =IF(Z11=1,IF(U11="In",L11-W11,L11),0) | AC11: =IF(AND(Z11=1,U11="Out"),W11,0) | AD11: =IF(AND(Z11=1,U11="In"),W11,0)
B12: TX-0006 | C12: 46030 | D12: Money Out | E12: Advertising & Marketing | F12: Facebook / Instagram ads | I12: Credit Card | K12: Credit Card | L12: 3835.19 | M12: 410.91 | O12: =IF(Z12=1,L12-W12,"") | P12: =IF(V12="","",IFERROR(INDEX(coa_Type,MATCH(V12,coa_Name,0)),"")) | Q12: =IF(Z12=1,IF(U12="In",K12&"",V12),"") | R12: =IF(Z12=1,IF(U12="In",V12,K12&""),"") | S12: =IF(X12<>"","⛔ "&X12&" — not posted",IF(Y12<>"","⚠ "&Y12,IF(Z12=1,"✓ OK",""))) | T12: =IF(AND(C12="",D12="",E12="",L12="",K12=""),1,0) | U12: =IFERROR(INDEX(tt_Dir,MATCH(D12,tt_Type,0)),"") | V12: =IF(D12="","",IFERROR(IF(INDEX(tt_Other,MATCH(D12,tt_Type,0))="",E12&"",INDEX(tt_Other,MATCH(D12,tt_Type,0))),"")) | W12: =IF(OR(TaxOn<>"Yes",NOT(ISNUMBER(M12))),0,IF(IFERROR(INDEX(tt_Tax,MATCH(D12,tt_Type,0)),"No")="Yes",M12,0)) | X12: =IF(T12=1,"",IF(C12="","Missing transaction date",IF(NOT(ISNUMBER(C12)),"Invalid date",IF(OR(C12<DATE(2000,1,1),C12>DATE(2099,12,31)),"Invalid date",IF(D12="","Select a type",IF(U12="","Unknown type: "&D12,IF(V12="","Select an account (Category)",IF(ISNA(MATCH(V12,coa_Name,0)),"Unknown account: "&V12,IF(K12="","Select Paid From / Deposited To",IF(ISNA(MATCH(K12,coa_Name,0)),"Unknown account: "&K12,IF(NOT(ISNUMBER(L12)),"Enter an amount",IF(L12=0,"Enter an amount",IF(ABS(W12)>ABS(L12),"Tax is larger than the amount",""))))))))))))) | Y12: =IF(OR(T12=1,X12<>""),"",IF(AND(B12<>"",COUNTIF(tx_ID,B12)>1),"Duplicate transaction ID",IF(AND(L12<0,D12<>"Adjustment"),"Negative amount — check this entry",IF(AND(D12="Customer Payment",G12=""),"Add the customer",IF(AND(D12="Customer Payment",OR(J12="",COUNTIF(ar_No,J12&"")=0)),"Invoice # in Reference not found on AR sheet",IF(AND(D12="Bill Payment",H12=""),"Add the vendor",IF(AND(D12="Bill Payment",OR(J12="",COUNTIFS(ap_No,J12&"",ap_Party,H12&"")=0)),"Bill # + vendor not found on AP sheet",IF(AND(ISNUMBER(M12),N(M12)<>0,W12=0),"Tax ignored (tax tracking off, or not allowed for this type)",IF(V12=K12&"","Same account on both sides",IF(AND(ISNUMBER(StartDate),C12<StartDate),"Date is before the accounting start date",IF(AND(D12<>"Adjustment",IFERROR(INDEX(coa_Pay,MATCH(K12&"",coa_Name,0)),"")<>"Yes"),"Paid From / Deposited To is not a payment account",""))))))))))) | Z12: =IF(AND(T12=0,X12=""),1,0) | AA12: =IF(Z12=1,IF(U12="In",L12,L12-W12),0) | AB12: =IF(Z12=1,IF(U12="In",L12-W12,L12),0) | AC12: =IF(AND(Z12=1,U12="Out"),W12,0) | AD12: =IF(AND(Z12=1,U12="In"),W12,0)
B13: TX-0007 | C13: 46031 | D13: Money Out | E13: Software & Subscriptions | F13: POS app subscription | I13: Credit Card | K13: Credit Card | L13: 1450 | M13: 155.36 | O13: =IF(Z13=1,L13-W13,"") | P13: =IF(V13="","",IFERROR(INDEX(coa_Type,MATCH(V13,coa_Name,0)),"")) | Q13: =IF(Z13=1,IF(U13="In",K13&"",V13),"") | R13: =IF(Z13=1,IF(U13="In",V13,K13&""),"") | S13: =IF(X13<>"","⛔ "&X13&" — not posted",IF(Y13<>"","⚠ "&Y13,IF(Z13=1,"✓ OK",""))) | T13: =IF(AND(C13="",D13="",E13="",L13="",K13=""),1,0) | U13: =IFERROR(INDEX(tt_Dir,MATCH(D13,tt_Type,0)),"") | V13: =IF(D13="","",IFERROR(IF(INDEX(tt_Other,MATCH(D13,tt_Type,0))="",E13&"",INDEX(tt_Other,MATCH(D13,tt_Type,0))),"")) | W13: =IF(OR(TaxOn<>"Yes",NOT(ISNUMBER(M13))),0,IF(IFERROR(INDEX(tt_Tax,MATCH(D13,tt_Type,0)),"No")="Yes",M13,0)) | X13: =IF(T13=1,"",IF(C13="","Missing transaction date",IF(NOT(ISNUMBER(C13)),"Invalid date",IF(OR(C13<DATE(2000,1,1),C13>DATE(2099,12,31)),"Invalid date",IF(D13="","Select a type",IF(U13="","Unknown type: "&D13,IF(V13="","Select an account (Category)",IF(ISNA(MATCH(V13,coa_Name,0)),"Unknown account: "&V13,IF(K13="","Select Paid From / Deposited To",IF(ISNA(MATCH(K13,coa_Name,0)),"Unknown account: "&K13,IF(NOT(ISNUMBER(L13)),"Enter an amount",IF(L13=0,"Enter an amount",IF(ABS(W13)>ABS(L13),"Tax is larger than the amount",""))))))))))))) | Y13: =IF(OR(T13=1,X13<>""),"",IF(AND(B13<>"",COUNTIF(tx_ID,B13)>1),"Duplicate transaction ID",IF(AND(L13<0,D13<>"Adjustment"),"Negative amount — check this entry",IF(AND(D13="Customer Payment",G13=""),"Add the customer",IF(AND(D13="Customer Payment",OR(J13="",COUNTIF(ar_No,J13&"")=0)),"Invoice # in Reference not found on AR sheet",IF(AND(D13="Bill Payment",H13=""),"Add the vendor",IF(AND(D13="Bill Payment",OR(J13="",COUNTIFS(ap_No,J13&"",ap_Party,H13&"")=0)),"Bill # + vendor not found on AP sheet",IF(AND(ISNUMBER(M13),N(M13)<>0,W13=0),"Tax ignored (tax tracking off, or not allowed for this type)",IF(V13=K13&"","Same account on both sides",IF(AND(ISNUMBER(StartDate),C13<StartDate),"Date is before the accounting start date",IF(AND(D13<>"Adjustment",IFERROR(INDEX(coa_Pay,MATCH(K13&"",coa_Name,0)),"")<>"Yes"),"Paid From / Deposited To is not a payment account",""))))))))))) | Z13: =IF(AND(T13=0,X13=""),1,0) | AA13: =IF(Z13=1,IF(U13="In",L13,L13-W13),0) | AB13: =IF(Z13=1,IF(U13="In",L13-W13,L13),0) | AC13: =IF(AND(Z13=1,U13="Out"),W13,0) | AD13: =IF(AND(Z13=1,U13="In"),W13,0)
B14: TX-0008 | C14: 46032 | D14: Money Out | E14: Loans Payable | F14: Loan principal | I14: Bank Transfer | J14: LOAN | K14: Bank Account | L14: 8000 | O14: =IF(Z14=1,L14-W14,"") | P14: =IF(V14="","",IFERROR(INDEX(coa_Type,MATCH(V14,coa_Name,0)),"")) | Q14: =IF(Z14=1,IF(U14="In",K14&"",V14),"") | R14: =IF(Z14=1,IF(U14="In",V14,K14&""),"") | S14: =IF(X14<>"","⛔ "&X14&" — not posted",IF(Y14<>"","⚠ "&Y14,IF(Z14=1,"✓ OK",""))) | T14: =IF(AND(C14="",D14="",E14="",L14="",K14=""),1,0) | U14: =IFERROR(INDEX(tt_Dir,MATCH(D14,tt_Type,0)),"") | V14: =IF(D14="","",IFERROR(IF(INDEX(tt_Other,MATCH(D14,tt_Type,0))="",E14&"",INDEX(tt_Other,MATCH(D14,tt_Type,0))),"")) | W14: =IF(OR(TaxOn<>"Yes",NOT(ISNUMBER(M14))),0,IF(IFERROR(INDEX(tt_Tax,MATCH(D14,tt_Type,0)),"No")="Yes",M14,0)) | X14: =IF(T14=1,"",IF(C14="","Missing transaction date",IF(NOT(ISNUMBER(C14)),"Invalid date",IF(OR(C14<DATE(2000,1,1),C14>DATE(2099,12,31)),"Invalid date",IF(D14="","Select a type",IF(U14="","Unknown type: "&D14,IF(V14="","Select an account (Category)",IF(ISNA(MATCH(V14,coa_Name,0)),"Unknown account: "&V14,IF(K14="","Select Paid From / Deposited To",IF(ISNA(MATCH(K14,coa_Name,0)),"Unknown account: "&K14,IF(NOT(ISNUMBER(L14)),"Enter an amount",IF(L14=0,"Enter an amount",IF(ABS(W14)>ABS(L14),"Tax is larger than the amount",""))))))))))))) | Y14: =IF(OR(T14=1,X14<>""),"",IF(AND(B14<>"",COUNTIF(tx_ID,B14)>1),"Duplicate transaction ID",IF(AND(L14<0,D14<>"Adjustment"),"Negative amount — check this entry",IF(AND(D14="Customer Payment",G14=""),"Add the customer",IF(AND(D14="Customer Payment",OR(J14="",COUNTIF(ar_No,J14&"")=0)),"Invoice # in Reference not found on AR sheet",IF(AND(D14="Bill Payment",H14=""),"Add the vendor",IF(AND(D14="Bill Payment",OR(J14="",COUNTIFS(ap_No,J14&"",ap_Party,H14&"")=0)),"Bill # + vendor not found on AP sheet",IF(AND(ISNUMBER(M14),N(M14)<>0,W14=0),"Tax ignored (tax tracking off, or not allowed for this type)",IF(V14=K14&"","Same account on both sides",IF(AND(ISNUMBER(StartDate),C14<StartDate),"Date is before the accounting start date",IF(AND(D14<>"Adjustment",IFERROR(INDEX(coa_Pay,MATCH(K14&"",coa_Name,0)),"")<>"Yes"),"Paid From / Deposited To is not a payment account",""))))))))))) | Z14: =IF(AND(T14=0,X14=""),1,0) | AA14: =IF(Z14=1,IF(U14="In",L14,L14-W14),0) | AB14: =IF(Z14=1,IF(U14="In",L14-W14,L14),0) | AC14: =IF(AND(Z14=1,U14="Out"),W14,0) | AD14: =IF(AND(Z14=1,U14="In"),W14,0)
B15: TX-0009 | C15: 46032 | D15: Money Out | E15: Interest Expense | F15: Loan interest | I15: Bank Transfer | J15: LOAN | K15: Bank Account | L15: 1500 | O15: =IF(Z15=1,L15-W15,"") | P15: =IF(V15="","",IFERROR(INDEX(coa_Type,MATCH(V15,coa_Name,0)),"")) | Q15: =IF(Z15=1,IF(U15="In",K15&"",V15),"") | R15: =IF(Z15=1,IF(U15="In",V15,K15&""),"") | S15: =IF(X15<>"","⛔ "&X15&" — not posted",IF(Y15<>"","⚠ "&Y15,IF(Z15=1,"✓ OK",""))) | T15: =IF(AND(C15="",D15="",E15="",L15="",K15=""),1,0) | U15: =IFERROR(INDEX(tt_Dir,MATCH(D15,tt_Type,0)),"") | V15: =IF(D15="","",IFERROR(IF(INDEX(tt_Other,MATCH(D15,tt_Type,0))="",E15&"",INDEX(tt_Other,MATCH(D15,tt_Type,0))),"")) | W15: =IF(OR(TaxOn<>"Yes",NOT(ISNUMBER(M15))),0,IF(IFERROR(INDEX(tt_Tax,MATCH(D15,tt_Type,0)),"No")="Yes",M15,0)) | X15: =IF(T15=1,"",IF(C15="","Missing transaction date",IF(NOT(ISNUMBER(C15)),"Invalid date",IF(OR(C15<DATE(2000,1,1),C15>DATE(2099,12,31)),"Invalid date",IF(D15="","Select a type",IF(U15="","Unknown type: "&D15,IF(V15="","Select an account (Category)",IF(ISNA(MATCH(V15,coa_Name,0)),"Unknown account: "&V15,IF(K15="","Select Paid From / Deposited To",IF(ISNA(MATCH(K15,coa_Name,0)),"Unknown account: "&K15,IF(NOT(ISNUMBER(L15)),"Enter an amount",IF(L15=0,"Enter an amount",IF(ABS(W15)>ABS(L15),"Tax is larger than the amount",""))))))))))))) | Y15: =IF(OR(T15=1,X15<>""),"",IF(AND(B15<>"",COUNTIF(tx_ID,B15)>1),"Duplicate transaction ID",IF(AND(L15<0,D15<>"Adjustment"),"Negative amount — check this entry",IF(AND(D15="Customer Payment",G15=""),"Add the customer",IF(AND(D15="Customer Payment",OR(J15="",COUNTIF(ar_No,J15&"")=0)),"Invoice # in Reference not found on AR sheet",IF(AND(D15="Bill Payment",H15=""),"Add the vendor",IF(AND(D15="Bill Payment",OR(J15="",COUNTIFS(ap_No,J15&"",ap_Party,H15&"")=0)),"Bill # + vendor not found on AP sheet",IF(AND(ISNUMBER(M15),N(M15)<>0,W15=0),"Tax ignored (tax tracking off, or not allowed for this type)",IF(V15=K15&"","Same account on both sides",IF(AND(ISNUMBER(StartDate),C15<StartDate),"Date is before the accounting start date",IF(AND(D15<>"Adjustment",IFERROR(INDEX(coa_Pay,MATCH(K15&"",coa_Name,0)),"")<>"Yes"),"Paid From / Deposited To is not a payment account",""))))))))))) | Z15: =IF(AND(T15=0,X15=""),1,0) | AA15: =IF(Z15=1,IF(U15="In",L15,L15-W15),0) | AB15: =IF(Z15=1,IF(U15="In",L15-W15,L15),0) | AC15: =IF(AND(Z15=1,U15="Out"),W15,0) | AD15: =IF(AND(Z15=1,U15="In"),W15,0)
B16: TX-0010 | C16: 46033 | D16: Money In | E16: Product Sales | F16: Counter sales week 2 | I16: Cash | K16: Cash on Hand | L16: 42316.87 | M16: 4533.95 | O16: =IF(Z16=1,L16-W16,"") | P16: =IF(V16="","",IFERROR(INDEX(coa_Type,MATCH(V16,coa_Name,0)),"")) | Q16: =IF(Z16=1,IF(U16="In",K16&"",V16),"") | R16: =IF(Z16=1,IF(U16="In",V16,K16&""),"") | S16: =IF(X16<>"","⛔ "&X16&" — not posted",IF(Y16<>"","⚠ "&Y16,IF(Z16=1,"✓ OK",""))) | T16: =IF(AND(C16="",D16="",E16="",L16="",K16=""),1,0) | U16: =IFERROR(INDEX(tt_Dir,MATCH(D16,tt_Type,0)),"") | V16: =IF(D16="","",IFERROR(IF(INDEX(tt_Other,MATCH(D16,tt_Type,0))="",E16&"",INDEX(tt_Other,MATCH(D16,tt_Type,0))),"")) | W16: =IF(OR(TaxOn<>"Yes",NOT(ISNUMBER(M16))),0,IF(IFERROR(INDEX(tt_Tax,MATCH(D16,tt_Type,0)),"No")="Yes",M16,0)) | X16: =IF(T16=1,"",IF(C16="","Missing transaction date",IF(NOT(ISNUMBER(C16)),"Invalid date",IF(OR(C16<DATE(2000,1,1),C16>DATE(2099,12,31)),"Invalid date",IF(D16="","Select a type",IF(U16="","Unknown type: "&D16,IF(V16="","Select an account (Category)",IF(ISNA(MATCH(V16,coa_Name,0)),"Unknown account: "&V16,IF(K16="","Select Paid From / Deposited To",IF(ISNA(MATCH(K16,coa_Name,0)),"Unknown account: "&K16,IF(NOT(ISNUMBER(L16)),"Enter an amount",IF(L16=0,"Enter an amount",IF(ABS(W16)>ABS(L16),"Tax is larger than the amount",""))))))))))))) | Y16: =IF(OR(T16=1,X16<>""),"",IF(AND(B16<>"",COUNTIF(tx_ID,B16)>1),"Duplicate transaction ID",IF(AND(L16<0,D16<>"Adjustment"),"Negative amount — check this entry",IF(AND(D16="Customer Payment",G16=""),"Add the customer",IF(AND(D16="Customer Payment",OR(J16="",COUNTIF(ar_No,J16&"")=0)),"Invoice # in Reference not found on AR sheet",IF(AND(D16="Bill Payment",H16=""),"Add the vendor",IF(AND(D16="Bill Payment",OR(J16="",COUNTIFS(ap_No,J16&"",ap_Party,H16&"")=0)),"Bill # + vendor not found on AP sheet",IF(AND(ISNUMBER(M16),N(M16)<>0,W16=0),"Tax ignored (tax tracking off, or not allowed for this type)",IF(V16=K16&"","Same account on both sides",IF(AND(ISNUMBER(StartDate),C16<StartDate),"Date is before the accounting start date",IF(AND(D16<>"Adjustment",IFERROR(INDEX(coa_Pay,MATCH(K16&"",coa_Name,0)),"")<>"Yes"),"Paid From / Deposited To is not a payment account",""))))))))))) | Z16: =IF(AND(T16=0,X16=""),1,0) | AA16: =IF(Z16=1,IF(U16="In",L16,L16-W16),0) | AB16: =IF(Z16=1,IF(U16="In",L16-W16,L16),0) | AC16: =IF(AND(Z16=1,U16="Out"),W16,0) | AD16: =IF(AND(Z16=1,U16="In"),W16,0)
B17: TX-0011 | C17: 46034 | D17: Money In | E17: Product Sales | F17: GCash / online orders week 2 | I17: E-Wallet | K17: E-Wallet / Online Payments | L17: 22825.17 | M17: 2445.55 | O17: =IF(Z17=1,L17-W17,"") | P17: =IF(V17="","",IFERROR(INDEX(coa_Type,MATCH(V17,coa_Name,0)),"")) | Q17: =IF(Z17=1,IF(U17="In",K17&"",V17),"") | R17: =IF(Z17=1,IF(U17="In",V17,K17&""),"") | S17: =IF(X17<>"","⛔ "&X17&" — not posted",IF(Y17<>"","⚠ "&Y17,IF(Z17=1,"✓ OK",""))) | T17: =IF(AND(C17="",D17="",E17="",L17="",K17=""),1,0) | U17: =IFERROR(INDEX(tt_Dir,MATCH(D17,tt_Type,0)),"") | V17: =IF(D17="","",IFERROR(IF(INDEX(tt_Other,MATCH(D17,tt_Type,0))="",E17&"",INDEX(tt_Other,MATCH(D17,tt_Type,0))),"")) | W17: =IF(OR(TaxOn<>"Yes",NOT(ISNUMBER(M17))),0,IF(IFERROR(INDEX(tt_Tax,MATCH(D17,tt_Type,0)),"No")="Yes",M17,0)) | X17: =IF(T17=1,"",IF(C17="","Missing transaction date",IF(NOT(ISNUMBER(C17)),"Invalid date",IF(OR(C17<DATE(2000,1,1),C17>DATE(2099,12,31)),"Invalid date",IF(D17="","Select a type",IF(U17="","Unknown type: "&D17,IF(V17="","Select an account (Category)",IF(ISNA(MATCH(V17,coa_Name,0)),"Unknown account: "&V17,IF(K17="","Select Paid From / Deposited To",IF(ISNA(MATCH(K17,coa_Name,0)),"Unknown account: "&K17,IF(NOT(ISNUMBER(L17)),"Enter an amount",IF(L17=0,"Enter an amount",IF(ABS(W17)>ABS(L17),"Tax is larger than the amount",""))))))))))))) | Y17: =IF(OR(T17=1,X17<>""),"",IF(AND(B17<>"",COUNTIF(tx_ID,B17)>1),"Duplicate transaction ID",IF(AND(L17<0,D17<>"Adjustment"),"Negative amount — check this entry",IF(AND(D17="Customer Payment",G17=""),"Add the customer",IF(AND(D17="Customer Payment",OR(J17="",COUNTIF(ar_No,J17&"")=0)),"Invoice # in Reference not found on AR sheet",IF(AND(D17="Bill Payment",H17=""),"Add the vendor",IF(AND(D17="Bill Payment",OR(J17="",COUNTIFS(ap_No,J17&"",ap_Party,H17&"")=0)),"Bill # + vendor not found on AP sheet",IF(AND(ISNUMBER(M17),N(M17)<>0,W17=0),"Tax ignored (tax tracking off, or not allowed for this type)",IF(V17=K17&"","Same account on both sides",IF(AND(ISNUMBER(StartDate),C17<StartDate),"Date is before the accounting start date",IF(AND(D17<>"Adjustment",IFERROR(INDEX(coa_Pay,MATCH(K17&"",coa_Name,0)),"")<>"Yes"),"Paid From / Deposited To is not a payment account",""))))))))))) | Z17: =IF(AND(T17=0,X17=""),1,0) | AA17: =IF(Z17=1,IF(U17="In",L17,L17-W17),0) | AB17: =IF(Z17=1,IF(U17="In",L17-W17,L17),0) | AC17: =IF(AND(Z17=1,U17="Out"),W17,0) | AD17: =IF(AND(Z17=1,U17="In"),W17,0)
B18: TX-0012 | C18: 46034 | D18: Money Out | E18: Utilities | F18: Electricity & water | I18: Bank Transfer | K18: Bank Account | L18: 9162.96 | M18: 981.75 | O18: =IF(Z18=1,L18-W18,"") | P18: =IF(V18="","",IFERROR(INDEX(coa_Type,MATCH(V18,coa_Name,0)),"")) | Q18: =IF(Z18=1,IF(U18="In",K18&"",V18),"") | R18: =IF(Z18=1,IF(U18="In",V18,K18&""),"") | S18: =IF(X18<>"","⛔ "&X18&" — not posted",IF(Y18<>"","⚠ "&Y18,IF(Z18=1,"✓ OK",""))) | T18: =IF(AND(C18="",D18="",E18="",L18="",K18=""),1,0) | U18: =IFERROR(INDEX(tt_Dir,MATCH(D18,tt_Type,0)),"") | V18: =IF(D18="","",IFERROR(IF(INDEX(tt_Other,MATCH(D18,tt_Type,0))="",E18&"",INDEX(tt_Other,MATCH(D18,tt_Type,0))),"")) | W18: =IF(OR(TaxOn<>"Yes",NOT(ISNUMBER(M18))),0,IF(IFERROR(INDEX(tt_Tax,MATCH(D18,tt_Type,0)),"No")="Yes",M18,0)) | X18: =IF(T18=1,"",IF(C18="","Missing transaction date",IF(NOT(ISNUMBER(C18)),"Invalid date",IF(OR(C18<DATE(2000,1,1),C18>DATE(2099,12,31)),"Invalid date",IF(D18="","Select a type",IF(U18="","Unknown type: "&D18,IF(V18="","Select an account (Category)",IF(ISNA(MATCH(V18,coa_Name,0)),"Unknown account: "&V18,IF(K18="","Select Paid From / Deposited To",IF(ISNA(MATCH(K18,coa_Name,0)),"Unknown account: "&K18,IF(NOT(ISNUMBER(L18)),"Enter an amount",IF(L18=0,"Enter an amount",IF(ABS(W18)>ABS(L18),"Tax is larger than the amount",""))))))))))))) | Y18: =IF(OR(T18=1,X18<>""),"",IF(AND(B18<>"",COUNTIF(tx_ID,B18)>1),"Duplicate transaction ID",IF(AND(L18<0,D18<>"Adjustment"),"Negative amount — check this entry",IF(AND(D18="Customer Payment",G18=""),"Add the customer",IF(AND(D18="Customer Payment",OR(J18="",COUNTIF(ar_No,J18&"")=0)),"Invoice # in Reference not found on AR sheet",IF(AND(D18="Bill Payment",H18=""),"Add the vendor",IF(AND(D18="Bill Payment",OR(J18="",COUNTIFS(ap_No,J18&"",ap_Party,H18&"")=0)),"Bill # + vendor not found on AP sheet",IF(AND(ISNUMBER(M18),N(M18)<>0,W18=0),"Tax ignored (tax tracking off, or not allowed for this type)",IF(V18=K18&"","Same account on both sides",IF(AND(ISNUMBER(StartDate),C18<StartDate),"Date is before the accounting start date",IF(AND(D18<>"Adjustment",IFERROR(INDEX(coa_Pay,MATCH(K18&"",coa_Name,0)),"")<>"Yes"),"Paid From / Deposited To is not a payment account",""))))))))))) | Z18: =IF(AND(T18=0,X18=""),1,0) | AA18: =IF(Z18=1,IF(U18="In",L18,L18-W18),0) | AB18: =IF(Z18=1,IF(U18="In",L18-W18,L18),0) | AC18: =IF(AND(Z18=1,U18="Out"),W18,0) | AD18: =IF(AND(Z18=1,U18="In"),W18,0)
B19: TX-0013 | C19: 46035 | D19: Transfer | E19: Bank Account | F19: Cash deposit to bank | I19: Cash | K19: Cash on Hand | L19: 36000 | O19: =IF(Z19=1,L19-W19,"") | P19: =IF(V19="","",IFERROR(INDEX(coa_Type,MATCH(V19,coa_Name,0)),"")) | Q19: =IF(Z19=1,IF(U19="In",K19&"",V19),"") | R19: =IF(Z19=1,IF(U19="In",V19,K19&""),"") | S19: =IF(X19<>"","⛔ "&X19&" — not posted",IF(Y19<>"","⚠ "&Y19,IF(Z19=1,"✓ OK",""))) | T19: =IF(AND(C19="",D19="",E19="",L19="",K19=""),1,0) | U19: =IFERROR(INDEX(tt_Dir,MATCH(D19,tt_Type,0)),"") | V19: =IF(D19="","",IFERROR(IF(INDEX(tt_Other,MATCH(D19,tt_Type,0))="",E19&"",INDEX(tt_Other,MATCH(D19,tt_Type,0))),"")) | W19: =IF(OR(TaxOn<>"Yes",NOT(ISNUMBER(M19))),0,IF(IFERROR(INDEX(tt_Tax,MATCH(D19,tt_Type,0)),"No")="Yes",M19,0)) | X19: =IF(T19=1,"",IF(C19="","Missing transaction date",IF(NOT(ISNUMBER(C19)),"Invalid date",IF(OR(C19<DATE(2000,1,1),C19>DATE(2099,12,31)),"Invalid date",IF(D19="","Select a type",IF(U19="","Unknown type: "&D19,IF(V19="","Select an account (Category)",IF(ISNA(MATCH(V19,coa_Name,0)),"Unknown account: "&V19,IF(K19="","Select Paid From / Deposited To",IF(ISNA(MATCH(K19,coa_Name,0)),"Unknown account: "&K19,IF(NOT(ISNUMBER(L19)),"Enter an amount",IF(L19=0,"Enter an amount",IF(ABS(W19)>ABS(L19),"Tax is larger than the amount",""))))))))))))) | Y19: =IF(OR(T19=1,X19<>""),"",IF(AND(B19<>"",COUNTIF(tx_ID,B19)>1),"Duplicate transaction ID",IF(AND(L19<0,D19<>"Adjustment"),"Negative amount — check this entry",IF(AND(D19="Customer Payment",G19=""),"Add the customer",IF(AND(D19="Customer Payment",OR(J19="",COUNTIF(ar_No,J19&"")=0)),"Invoice # in Reference not found on AR sheet",IF(AND(D19="Bill Payment",H19=""),"Add the vendor",IF(AND(D19="Bill Payment",OR(J19="",COUNTIFS(ap_No,J19&"",ap_Party,H19&"")=0)),"Bill # + vendor not found on AP sheet",IF(AND(ISNUMBER(M19),N(M19)<>0,W19=0),"Tax ignored (tax tracking off, or not allowed for this type)",IF(V19=K19&"","Same account on both sides",IF(AND(ISNUMBER(StartDate),C19<StartDate),"Date is before the accounting start date",IF(AND(D19<>"Adjustment",IFERROR(INDEX(coa_Pay,MATCH(K19&"",coa_Name,0)),"")<>"Yes"),"Paid From / Deposited To is not a payment account",""))))))))))) | Z19: =IF(AND(T19=0,X19=""),1,0) | AA19: =IF(Z19=1,IF(U19="In",L19,L19-W19),0) | AB19: =IF(Z19=1,IF(U19="In",L19-W19,L19),0) | AC19: =IF(AND(Z19=1,U19="Out"),W19,0) | AD19: =IF(AND(Z19=1,U19="In"),W19,0)
B20: TX-0014 | C20: 46037 | D20: Money Out | E20: Internet & Phone | F20: Fiber internet | I20: Bank Transfer | K20: Bank Account | L20: 2499 | M20: 267.75 | O20: =IF(Z20=1,L20-W20,"") | P20: =IF(V20="","",IFERROR(INDEX(coa_Type,MATCH(V20,coa_Name,0)),"")) | Q20: =IF(Z20=1,IF(U20="In",K20&"",V20),"") | R20: =IF(Z20=1,IF(U20="In",V20,K20&""),"") | S20: =IF(X20<>"","⛔ "&X20&" — not posted",IF(Y20<>"","⚠ "&Y20,IF(Z20=1,"✓ OK",""))) | T20: =IF(AND(C20="",D20="",E20="",L20="",K20=""),1,0) | U20: =IFERROR(INDEX(tt_Dir,MATCH(D20,tt_Type,0)),"") | V20: =IF(D20="","",IFERROR(IF(INDEX(tt_Other,MATCH(D20,tt_Type,0))="",E20&"",INDEX(tt_Other,MATCH(D20,tt_Type,0))),"")) | W20: =IF(OR(TaxOn<>"Yes",NOT(ISNUMBER(M20))),0,IF(IFERROR(INDEX(tt_Tax,MATCH(D20,tt_Type,0)),"No")="Yes",M20,0)) | X20: =IF(T20=1,"",IF(C20="","Missing transaction date",IF(NOT(ISNUMBER(C20)),"Invalid date",IF(OR(C20<DATE(2000,1,1),C20>DATE(2099,12,31)),"Invalid date",IF(D20="","Select a type",IF(U20="","Unknown type: "&D20,IF(V20="","Select an account (Category)",IF(ISNA(MATCH(V20,coa_Name,0)),"Unknown account: "&V20,IF(K20="","Select Paid From / Deposited To",IF(ISNA(MATCH(K20,coa_Name,0)),"Unknown account: "&K20,IF(NOT(ISNUMBER(L20)),"Enter an amount",IF(L20=0,"Enter an amount",IF(ABS(W20)>ABS(L20),"Tax is larger than the amount",""))))))))))))) | Y20: =IF(OR(T20=1,X20<>""),"",IF(AND(B20<>"",COUNTIF(tx_ID,B20)>1),"Duplicate transaction ID",IF(AND(L20<0,D20<>"Adjustment"),"Negative amount — check this entry",IF(AND(D20="Customer Payment",G20=""),"Add the customer",IF(AND(D20="Customer Payment",OR(J20="",COUNTIF(ar_No,J20&"")=0)),"Invoice # in Reference not found on AR sheet",IF(AND(D20="Bill Payment",H20=""),"Add the vendor",IF(AND(D20="Bill Payment",OR(J20="",COUNTIFS(ap_No,J20&"",ap_Party,H20&"")=0)),"Bill # + vendor not found on AP sheet",IF(AND(ISNUMBER(M20),N(M20)<>0,W20=0),"Tax ignored (tax tracking off, or not allowed for this type)",IF(V20=K20&"","Same account on both sides",IF(AND(ISNUMBER(StartDate),C20<StartDate),"Date is before the accounting start date",IF(AND(D20<>"Adjustment",IFERROR(INDEX(coa_Pay,MATCH(K20&"",coa_Name,0)),"")<>"Yes"),"Paid From / Deposited To is not a payment account",""))))))))))) | Z20: =IF(AND(T20=0,X20=""),1,0) | AA20: =IF(Z20=1,IF(U20="In",L20,L20-W20),0) | AB20: =IF(Z20=1,IF(U20="In",L20-W20,L20),0) | AC20: =IF(AND(Z20=1,U20="Out"),W20,0) | AD20: =IF(AND(Z20=1,U20="In"),W20,0)
B21: TX-0015 | C21: 46037 | D21: Money Out | E21: Direct Labor | F21: Bakers' salaries (1st-15th) | I21: Bank Transfer | K21: Bank Account | L21: 38000 | O21: =IF(Z21=1,L21-W21,"") | P21: =IF(V21="","",IFERROR(INDEX(coa_Type,MATCH(V21,coa_Name,0)),"")) | Q21: =IF(Z21=1,IF(U21="In",K21&"",V21),"") | R21: =IF(Z21=1,IF(U21="In",V21,K21&""),"") | S21: =IF(X21<>"","⛔ "&X21&" — not posted",IF(Y21<>"","⚠ "&Y21,IF(Z21=1,"✓ OK",""))) | T21: =IF(AND(C21="",D21="",E21="",L21="",K21=""),1,0) | U21: =IFERROR(INDEX(tt_Dir,MATCH(D21,tt_Type,0)),"") | V21: =IF(D21="","",IFERROR(IF(INDEX(tt_Other,MATCH(D21,tt_Type,0))="",E21&"",INDEX(tt_Other,MATCH(D21,tt_Type,0))),"")) | W21: =IF(OR(TaxOn<>"Yes",NOT(ISNUMBER(M21))),0,IF(IFERROR(INDEX(tt_Tax,MATCH(D21,tt_Type,0)),"No")="Yes",M21,0)) | X21: =IF(T21=1,"",IF(C21="","Missing transaction date",IF(NOT(ISNUMBER(C21)),"Invalid date",IF(OR(C21<DATE(2000,1,1),C21>DATE(2099,12,31)),"Invalid date",IF(D21="","Select a type",IF(U21="","Unknown type: "&D21,IF(V21="","Select an account (Category)",IF(ISNA(MATCH(V21,coa_Name,0)),"Unknown account: "&V21,IF(K21="","Select Paid From / Deposited To",IF(ISNA(MATCH(K21,coa_Name,0)),"Unknown account: "&K21,IF(NOT(ISNUMBER(L21)),"Enter an amount",IF(L21=0,"Enter an amount",IF(ABS(W21)>ABS(L21),"Tax is larger than the amount",""))))))))))))) | Y21: =IF(OR(T21=1,X21<>""),"",IF(AND(B21<>"",COUNTIF(tx_ID,B21)>1),"Duplicate transaction ID",IF(AND(L21<0,D21<>"Adjustment"),"Negative amount — check this entry",IF(AND(D21="Customer Payment",G21=""),"Add the customer",IF(AND(D21="Customer Payment",OR(J21="",COUNTIF(ar_No,J21&"")=0)),"Invoice # in Reference not found on AR sheet",IF(AND(D21="Bill Payment",H21=""),"Add the vendor",IF(AND(D21="Bill Payment",OR(J21="",COUNTIFS(ap_No,J21&"",ap_Party,H21&"")=0)),"Bill # + vendor not found on AP sheet",IF(AND(ISNUMBER(M21),N(M21)<>0,W21=0),"Tax ignored (tax tracking off, or not allowed for this type)",IF(V21=K21&"","Same account on both sides",IF(AND(ISNUMBER(StartDate),C21<StartDate),"Date is before the accounting start date",IF(AND(D21<>"Adjustment",IFERROR(INDEX(coa_Pay,MATCH(K21&"",coa_Name,0)),"")<>"Yes"),"Paid From / Deposited To is not a payment account",""))))))))))) | Z21: =IF(AND(T21=0,X21=""),1,0) | AA21: =IF(Z21=1,IF(U21="In",L21,L21-W21),0) | AB21: =IF(Z21=1,IF(U21="In",L21-W21,L21),0) | AC21: =IF(AND(Z21=1,U21="Out"),W21,0) | AD21: =IF(AND(Z21=1,U21="In"),W21,0)
B22: TX-0016 | C22: 46037 | D22: Money Out | E22: Salaries & Wages | F22: Cashier salary (1st-15th) | I22: Bank Transfer | K22: Bank Account | L22: 9000 | O22: =IF(Z22=1,L22-W22,"") | P22: =IF(V22="","",IFERROR(INDEX(coa_Type,MATCH(V22,coa_Name,0)),"")) | Q22: =IF(Z22=1,IF(U22="In",K22&"",V22),"") | R22: =IF(Z22=1,IF(U22="In",V22,K22&""),"") | S22: =IF(X22<>"","⛔ "&X22&" — not posted",IF(Y22<>"","⚠ "&Y22,IF(Z22=1,"✓ OK",""))) | T22: =IF(AND(C22="",D22="",E22="",L22="",K22=""),1,0) | U22: =IFERROR(INDEX(tt_Dir,MATCH(D22,tt_Type,0)),"") | V22: =IF(D22="","",IFERROR(IF(INDEX(tt_Other,MATCH(D22,tt_Type,0))="",E22&"",INDEX(tt_Other,MATCH(D22,tt_Type,0))),"")) | W22: =IF(OR(TaxOn<>"Yes",NOT(ISNUMBER(M22))),0,IF(IFERROR(INDEX(tt_Tax,MATCH(D22,tt_Type,0)),"No")="Yes",M22,0)) | X22: =IF(T22=1,"",IF(C22="","Missing transaction date",IF(NOT(ISNUMBER(C22)),"Invalid date",IF(OR(C22<DATE(2000,1,1),C22>DATE(2099,12,31)),"Invalid date",IF(D22="","Select a type",IF(U22="","Unknown type: "&D22,IF(V22="","Select an account (Category)",IF(ISNA(MATCH(V22,coa_Name,0)),"Unknown account: "&V22,IF(K22="","Select Paid From / Deposited To",IF(ISNA(MATCH(K22,coa_Name,0)),"Unknown account: "&K22,IF(NOT(ISNUMBER(L22)),"Enter an amount",IF(L22=0,"Enter an amount",IF(ABS(W22)>ABS(L22),"Tax is larger than the amount",""))))))))))))) | Y22: =IF(OR(T22=1,X22<>""),"",IF(AND(B22<>"",COUNTIF(tx_ID,B22)>1),"Duplicate transaction ID",IF(AND(L22<0,D22<>"Adjustment"),"Negative amount — check this entry",IF(AND(D22="Customer Payment",G22=""),"Add the customer",IF(AND(D22="Customer Payment",OR(J22="",COUNTIF(ar_No,J22&"")=0)),"Invoice # in Reference not found on AR sheet",IF(AND(D22="Bill Payment",H22=""),"Add the vendor",IF(AND(D22="Bill Payment",OR(J22="",COUNTIFS(ap_No,J22&"",ap_Party,H22&"")=0)),"Bill # + vendor not found on AP sheet",IF(AND(ISNUMBER(M22),N(M22)<>0,W22=0),"Tax ignored (tax tracking off, or not allowed for this type)",IF(V22=K22&"","Same account on both sides",IF(AND(ISNUMBER(StartDate),C22<StartDate),"Date is before the accounting start date",IF(AND(D22<>"Adjustment",IFERROR(INDEX(coa_Pay,MATCH(K22&"",coa_Name,0)),"")<>"Yes"),"Paid From / Deposited To is not a payment account",""))))))))))) | Z22: =IF(AND(T22=0,X22=""),1,0) | AA22: =IF(Z22=1,IF(U22="In",L22,L22-W22),0) | AB22: =IF(Z22=1,IF(U22="In",L22-W22,L22),0) | AC22: =IF(AND(Z22=1,U22="Out"),W22,0) | AD22: =IF(AND(Z22=1,U22="In"),W22,0)
B23: TX-0017 | C23: 46040 | D23: Money In | E23: Product Sales | F23: Counter sales week 3 | I23: Cash | K23: Cash on Hand | L23: 61115.56 | M23: 6548.1 | O23: =IF(Z23=1,L23-W23,"") | P23: =IF(V23="","",IFERROR(INDEX(coa_Type,MATCH(V23,coa_Name,0)),"")) | Q23: =IF(Z23=1,IF(U23="In",K23&"",V23),"") | R23: =IF(Z23=1,IF(U23="In",V23,K23&""),"") | S23: =IF(X23<>"","⛔ "&X23&" — not posted",IF(Y23<>"","⚠ "&Y23,IF(Z23=1,"✓ OK",""))) | T23: =IF(AND(C23="",D23="",E23="",L23="",K23=""),1,0) | U23: =IFERROR(INDEX(tt_Dir,MATCH(D23,tt_Type,0)),"") | V23: =IF(D23="","",IFERROR(IF(INDEX(tt_Other,MATCH(D23,tt_Type,0))="",E23&"",INDEX(tt_Other,MATCH(D23,tt_Type,0))),"")) | W23: =IF(OR(TaxOn<>"Yes",NOT(ISNUMBER(M23))),0,IF(IFERROR(INDEX(tt_Tax,MATCH(D23,tt_Type,0)),"No")="Yes",M23,0)) | X23: =IF(T23=1,"",IF(C23="","Missing transaction date",IF(NOT(ISNUMBER(C23)),"Invalid date",IF(OR(C23<DATE(2000,1,1),C23>DATE(2099,12,31)),"Invalid date",IF(D23="","Select a type",IF(U23="","Unknown type: "&D23,IF(V23="","Select an account (Category)",IF(ISNA(MATCH(V23,coa_Name,0)),"Unknown account: "&V23,IF(K23="","Select Paid From / Deposited To",IF(ISNA(MATCH(K23,coa_Name,0)),"Unknown account: "&K23,IF(NOT(ISNUMBER(L23)),"Enter an amount",IF(L23=0,"Enter an amount",IF(ABS(W23)>ABS(L23),"Tax is larger than the amount",""))))))))))))) | Y23: =IF(OR(T23=1,X23<>""),"",IF(AND(B23<>"",COUNTIF(tx_ID,B23)>1),"Duplicate transaction ID",IF(AND(L23<0,D23<>"Adjustment"),"Negative amount — check this entry",IF(AND(D23="Customer Payment",G23=""),"Add the customer",IF(AND(D23="Customer Payment",OR(J23="",COUNTIF(ar_No,J23&"")=0)),"Invoice # in Reference not found on AR sheet",IF(AND(D23="Bill Payment",H23=""),"Add the vendor",IF(AND(D23="Bill Payment",OR(J23="",COUNTIFS(ap_No,J23&"",ap_Party,H23&"")=0)),"Bill # + vendor not found on AP sheet",IF(AND(ISNUMBER(M23),N(M23)<>0,W23=0),"Tax ignored (tax tracking off, or not allowed for this type)",IF(V23=K23&"","Same account on both sides",IF(AND(ISNUMBER(StartDate),C23<StartDate),"Date is before the accounting start date",IF(AND(D23<>"Adjustment",IFERROR(INDEX(coa_Pay,MATCH(K23&"",coa_Name,0)),"")<>"Yes"),"Paid From / Deposited To is not a payment account",""))))))))))) | Z23: =IF(AND(T23=0,X23=""),1,0) | AA23: =IF(Z23=1,IF(U23="In",L23,L23-W23),0) | AB23: =IF(Z23=1,IF(U23="In",L23-W23,L23),0) | AC23: =IF(AND(Z23=1,U23="Out"),W23,0) | AD23: =IF(AND(Z23=1,U23="In"),W23,0)
B24: TX-0018 | C24: 46041 | D24: Money In | E24: Product Sales | F24: GCash / online orders week 3 | I24: E-Wallet | K24: E-Wallet / Online Payments | L24: 17837.56 | M24: 1911.17 | O24: =IF(Z24=1,L24-W24,"") | P24: =IF(V24="","",IFERROR(INDEX(coa_Type,MATCH(V24,coa_Name,0)),"")) | Q24: =IF(Z24=1,IF(U24="In",K24&"",V24),"") | R24: =IF(Z24=1,IF(U24="In",V24,K24&""),"") | S24: =IF(X24<>"","⛔ "&X24&" — not posted",IF(Y24<>"","⚠ "&Y24,IF(Z24=1,"✓ OK",""))) | T24: =IF(AND(C24="",D24="",E24="",L24="",K24=""),1,0) | U24: =IFERROR(INDEX(tt_Dir,MATCH(D24,tt_Type,0)),"") | V24: =IF(D24="","",IFERROR(IF(INDEX(tt_Other,MATCH(D24,tt_Type,0))="",E24&"",INDEX(tt_Other,MATCH(D24,tt_Type,0))),"")) | W24: =IF(OR(TaxOn<>"Yes",NOT(ISNUMBER(M24))),0,IF(IFERROR(INDEX(tt_Tax,MATCH(D24,tt_Type,0)),"No")="Yes",M24,0)) | X24: =IF(T24=1,"",IF(C24="","Missing transaction date",IF(NOT(ISNUMBER(C24)),"Invalid date",IF(OR(C24<DATE(2000,1,1),C24>DATE(2099,12,31)),"Invalid date",IF(D24="","Select a type",IF(U24="","Unknown type: "&D24,IF(V24="","Select an account (Category)",IF(ISNA(MATCH(V24,coa_Name,0)),"Unknown account: "&V24,IF(K24="","Select Paid From / Deposited To",IF(ISNA(MATCH(K24,coa_Name,0)),"Unknown account: "&K24,IF(NOT(ISNUMBER(L24)),"Enter an amount",IF(L24=0,"Enter an amount",IF(ABS(W24)>ABS(L24),"Tax is larger than the amount",""))))))))))))) | Y24: =IF(OR(T24=1,X24<>""),"",IF(AND(B24<>"",COUNTIF(tx_ID,B24)>1),"Duplicate transaction ID",IF(AND(L24<0,D24<>"Adjustment"),"Negative amount — check this entry",IF(AND(D24="Customer Payment",G24=""),"Add the customer",IF(AND(D24="Customer Payment",OR(J24="",COUNTIF(ar_No,J24&"")=0)),"Invoice # in Reference not found on AR sheet",IF(AND(D24="Bill Payment",H24=""),"Add the vendor",IF(AND(D24="Bill Payment",OR(J24="",COUNTIFS(ap_No,J24&"",ap_Party,H24&"")=0)),"Bill # + vendor not found on AP sheet",IF(AND(ISNUMBER(M24),N(M24)<>0,W24=0),"Tax ignored (tax tracking off, or not allowed for this type)",IF(V24=K24&"","Same account on both sides",IF(AND(ISNUMBER(StartDate),C24<StartDate),"Date is before the accounting start date",IF(AND(D24<>"Adjustment",IFERROR(INDEX(coa_Pay,MATCH(K24&"",coa_Name,0)),"")<>"Yes"),"Paid From / Deposited To is not a payment account",""))))))))))) | Z24: =IF(AND(T24=0,X24=""),1,0) | AA24: =IF(Z24=1,IF(U24="In",L24,L24-W24),0) | AB24: =IF(Z24=1,IF(U24="In",L24-W24,L24),0) | AC24: =IF(AND(Z24=1,U24="Out"),W24,0) | AD24: =IF(AND(Z24=1,U24="In"),W24,0)
B25: TX-0019 | C25: 46042 | D25: Transfer | E25: Bank Account | F25: Cash deposit to bank | I25: Cash | K25: Cash on Hand | L25: 51900 | O25: =IF(Z25=1,L25-W25,"") | P25: =IF(V25="","",IFERROR(INDEX(coa_Type,MATCH(V25,coa_Name,0)),"")) | Q25: =IF(Z25=1,IF(U25="In",K25&"",V25),"") | R25: =IF(Z25=1,IF(U25="In",V25,K25&""),"") | S25: =IF(X25<>"","⛔ "&X25&" — not posted",IF(Y25<>"","⚠ "&Y25,IF(Z25=1,"✓ OK",""))) | T25: =IF(AND(C25="",D25="",E25="",L25="",K25=""),1,0) | U25: =IFERROR(INDEX(tt_Dir,MATCH(D25,tt_Type,0)),"") | V25: =IF(D25="","",IFERROR(IF(INDEX(tt_Other,MATCH(D25,tt_Type,0))="",E25&"",INDEX(tt_Other,MATCH(D25,tt_Type,0))),"")) | W25: =IF(OR(TaxOn<>"Yes",NOT(ISNUMBER(M25))),0,IF(IFERROR(INDEX(tt_Tax,MATCH(D25,tt_Type,0)),"No")="Yes",M25,0)) | X25: =IF(T25=1,"",IF(C25="","Missing transaction date",IF(NOT(ISNUMBER(C25)),"Invalid date",IF(OR(C25<DATE(2000,1,1),C25>DATE(2099,12,31)),"Invalid date",IF(D25="","Select a type",IF(U25="","Unknown type: "&D25,IF(V25="","Select an account (Category)",IF(ISNA(MATCH(V25,coa_Name,0)),"Unknown account: "&V25,IF(K25="","Select Paid From / Deposited To",IF(ISNA(MATCH(K25,coa_Name,0)),"Unknown account: "&K25,IF(NOT(ISNUMBER(L25)),"Enter an amount",IF(L25=0,"Enter an amount",IF(ABS(W25)>ABS(L25),"Tax is larger than the amount",""))))))))))))) | Y25: =IF(OR(T25=1,X25<>""),"",IF(AND(B25<>"",COUNTIF(tx_ID,B25)>1),"Duplicate transaction ID",IF(AND(L25<0,D25<>"Adjustment"),"Negative amount — check this entry",IF(AND(D25="Customer Payment",G25=""),"Add the customer",IF(AND(D25="Customer Payment",OR(J25="",COUNTIF(ar_No,J25&"")=0)),"Invoice # in Reference not found on AR sheet",IF(AND(D25="Bill Payment",H25=""),"Add the vendor",IF(AND(D25="Bill Payment",OR(J25="",COUNTIFS(ap_No,J25&"",ap_Party,H25&"")=0)),"Bill # + vendor not found on AP sheet",IF(AND(ISNUMBER(M25),N(M25)<>0,W25=0),"Tax ignored (tax tracking off, or not allowed for this type)",IF(V25=K25&"","Same account on both sides",IF(AND(ISNUMBER(StartDate),C25<StartDate),"Date is before the accounting start date",IF(AND(D25<>"Adjustment",IFERROR(INDEX(coa_Pay,MATCH(K25&"",coa_Name,0)),"")<>"Yes"),"Paid From / Deposited To is not a payment account",""))))))))))) | Z25: =IF(AND(T25=0,X25=""),1,0) | AA25: =IF(Z25=1,IF(U25="In",L25,L25-W25),0) | AB25: =IF(Z25=1,IF(U25="In",L25-W25,L25),0) | AC25: =IF(AND(Z25=1,U25="Out"),W25,0) | AD25: =IF(AND(Z25=1,U25="In"),W25,0)
B26: TX-0020 | C26: 46042 | D26: Money Out | E26: Transportation & Delivery | F26: Delivery fuel | I26: Cash | K26: Cash on Hand | L26: 4029.57 | M26: 431.74 | O26: =IF(Z26=1,L26-W26,"") | P26: =IF(V26="","",IFERROR(INDEX(coa_Type,MATCH(V26,coa_Name,0)),"")) | Q26: =IF(Z26=1,IF(U26="In",K26&"",V26),"") | R26: =IF(Z26=1,IF(U26="In",V26,K26&""),"") | S26: =IF(X26<>"","⛔ "&X26&" — not posted",IF(Y26<>"","⚠ "&Y26,IF(Z26=1,"✓ OK",""))) | T26: =IF(AND(C26="",D26="",E26="",L26="",K26=""),1,0) | U26: =IFERROR(INDEX(tt_Dir,MATCH(D26,tt_Type,0)),"") | V26: =IF(D26="","",IFERROR(IF(INDEX(tt_Other,MATCH(D26,tt_Type,0))="",E26&"",INDEX(tt_Other,MATCH(D26,tt_Type,0))),"")) | W26: =IF(OR(TaxOn<>"Yes",NOT(ISNUMBER(M26))),0,IF(IFERROR(INDEX(tt_Tax,MATCH(D26,tt_Type,0)),"No")="Yes",M26,0)) | X26: =IF(T26=1,"",IF(C26="","Missing transaction date",IF(NOT(ISNUMBER(C26)),"Invalid date",IF(OR(C26<DATE(2000,1,1),C26>DATE(2099,12,31)),"Invalid date",IF(D26="","Select a type",IF(U26="","Unknown type: "&D26,IF(V26="","Select an account (Category)",IF(ISNA(MATCH(V26,coa_Name,0)),"Unknown account: "&V26,IF(K26="","Select Paid From / Deposited To",IF(ISNA(MATCH(K26,coa_Name,0)),"Unknown account: "&K26,IF(NOT(ISNUMBER(L26)),"Enter an amount",IF(L26=0,"Enter an amount",IF(ABS(W26)>ABS(L26),"Tax is larger than the amount",""))))))))))))) | Y26: =IF(OR(T26=1,X26<>""),"",IF(AND(B26<>"",COUNTIF(tx_ID,B26)>1),"Duplicate transaction ID",IF(AND(L26<0,D26<>"Adjustment"),"Negative amount — check this entry",IF(AND(D26="Customer Payment",G26=""),"Add the customer",IF(AND(D26="Customer Payment",OR(J26="",COUNTIF(ar_No,J26&"")=0)),"Invoice # in Reference not found on AR sheet",IF(AND(D26="Bill Payment",H26=""),"Add the vendor",IF(AND(D26="Bill Payment",OR(J26="",COUNTIFS(ap_No,J26&"",ap_Party,H26&"")=0)),"Bill # + vendor not found on AP sheet",IF(AND(ISNUMBER(M26),N(M26)<>0,W26=0),"Tax ignored (tax tracking off, or not allowed for this type)",IF(V26=K26&"","Same account on both sides",IF(AND(ISNUMBER(StartDate),C26<StartDate),"Date is before the accounting start date",IF(AND(D26<>"Adjustment",IFERROR(INDEX(coa_Pay,MATCH(K26&"",coa_Name,0)),"")<>"Yes"),"Paid From / Deposited To is not a payment account",""))))))))))) | Z26: =IF(AND(T26=0,X26=""),1,0) | AA26: =IF(Z26=1,IF(U26="In",L26,L26-W26),0) | AB26: =IF(Z26=1,IF(U26="In",L26-W26,L26),0) | AC26: =IF(AND(Z26=1,U26="Out"),W26,0) | AD26: =IF(AND(Z26=1,U26="In"),W26,0)
B27: TX-0021 | C27: 46047 | D27: Money In | E27: Product Sales | F27: Counter sales week 4 | I27: Cash | K27: Cash on Hand | L27: 60161.37 | M27: 6445.86 | O27: =IF(Z27=1,L27-W27,"") | P27: =IF(V27="","",IFERROR(INDEX(coa_Type,MATCH(V27,coa_Name,0)),"")) | Q27: =IF(Z27=1,IF(U27="In",K27&"",V27),"") | R27: =IF(Z27=1,IF(U27="In",V27,K27&""),"") | S27: =IF(X27<>"","⛔ "&X27&" — not posted",IF(Y27<>"","⚠ "&Y27,IF(Z27=1,"✓ OK",""))) | T27: =IF(AND(C27="",D27="",E27="",L27="",K27=""),1,0) | U27: =IFERROR(INDEX(tt_Dir,MATCH(D27,tt_Type,0)),"") | V27: =IF(D27="","",IFERROR(IF(INDEX(tt_Other,MATCH(D27,tt_Type,0))="",E27&"",INDEX(tt_Other,MATCH(D27,tt_Type,0))),"")) | W27: =IF(OR(TaxOn<>"Yes",NOT(ISNUMBER(M27))),0,IF(IFERROR(INDEX(tt_Tax,MATCH(D27,tt_Type,0)),"No")="Yes",M27,0)) | X27: =IF(T27=1,"",IF(C27="","Missing transaction date",IF(NOT(ISNUMBER(C27)),"Invalid date",IF(OR(C27<DATE(2000,1,1),C27>DATE(2099,12,31)),"Invalid date",IF(D27="","Select a type",IF(U27="","Unknown type: "&D27,IF(V27="","Select an account (Category)",IF(ISNA(MATCH(V27,coa_Name,0)),"Unknown account: "&V27,IF(K27="","Select Paid From / Deposited To",IF(ISNA(MATCH(K27,coa_Name,0)),"Unknown account: "&K27,IF(NOT(ISNUMBER(L27)),"Enter an amount",IF(L27=0,"Enter an amount",IF(ABS(W27)>ABS(L27),"Tax is larger than the amount",""))))))))))))) | Y27: =IF(OR(T27=1,X27<>""),"",IF(AND(B27<>"",COUNTIF(tx_ID,B27)>1),"Duplicate transaction ID",IF(AND(L27<0,D27<>"Adjustment"),"Negative amount — check this entry",IF(AND(D27="Customer Payment",G27=""),"Add the customer",IF(AND(D27="Customer Payment",OR(J27="",COUNTIF(ar_No,J27&"")=0)),"Invoice # in Reference not found on AR sheet",IF(AND(D27="Bill Payment",H27=""),"Add the vendor",IF(AND(D27="Bill Payment",OR(J27="",COUNTIFS(ap_No,J27&"",ap_Party,H27&"")=0)),"Bill # + vendor not found on AP sheet",IF(AND(ISNUMBER(M27),N(M27)<>0,W27=0),"Tax ignored (tax tracking off, or not allowed for this type)",IF(V27=K27&"","Same account on both sides",IF(AND(ISNUMBER(StartDate),C27<StartDate),"Date is before the accounting start date",IF(AND(D27<>"Adjustment",IFERROR(INDEX(coa_Pay,MATCH(K27&"",coa_Name,0)),"")<>"Yes"),"Paid From / Deposited To is not a payment account",""))))))))))) | Z27: =IF(AND(T27=0,X27=""),1,0) | AA27: =IF(Z27=1,IF(U27="In",L27,L27-W27),0) | AB27: =IF(Z27=1,IF(U27="In",L27-W27,L27),0) | AC27: =IF(AND(Z27=1,U27="Out"),W27,0) | AD27: =IF(AND(Z27=1,U27="In"),W27,0)
B28: TX-0022 | C28: 46047 | D28: Owner Draw | F28: Owner salary / personal draw | I28: Bank Transfer | K28: Bank Account | L28: 20000 | O28: =IF(Z28=1,L28-W28,"") | P28: =IF(V28="","",IFERROR(INDEX(coa_Type,MATCH(V28,coa_Name,0)),"")) | Q28: =IF(Z28=1,IF(U28="In",K28&"",V28),"") | R28: =IF(Z28=1,IF(U28="In",V28,K28&""),"") | S28: =IF(X28<>"","⛔ "&X28&" — not posted",IF(Y28<>"","⚠ "&Y28,IF(Z28=1,"✓ OK",""))) | T28: =IF(AND(C28="",D28="",E28="",L28="",K28=""),1,0) | U28: =IFERROR(INDEX(tt_Dir,MATCH(D28,tt_Type,0)),"") | V28: =IF(D28="","",IFERROR(IF(INDEX(tt_Other,MATCH(D28,tt_Type,0))="",E28&"",INDEX(tt_Other,MATCH(D28,tt_Type,0))),"")) | W28: =IF(OR(TaxOn<>"Yes",NOT(ISNUMBER(M28))),0,IF(IFERROR(INDEX(tt_Tax,MATCH(D28,tt_Type,0)),"No")="Yes",M28,0)) | X28: =IF(T28=1,"",IF(C28="","Missing transaction date",IF(NOT(ISNUMBER(C28)),"Invalid date",IF(OR(C28<DATE(2000,1,1),C28>DATE(2099,12,31)),"Invalid date",IF(D28="","Select a type",IF(U28="","Unknown type: "&D28,IF(V28="","Select an account (Category)",IF(ISNA(MATCH(V28,coa_Name,0)),"Unknown account: "&V28,IF(K28="","Select Paid From / Deposited To",IF(ISNA(MATCH(K28,coa_Name,0)),"Unknown account: "&K28,IF(NOT(ISNUMBER(L28)),"Enter an amount",IF(L28=0,"Enter an amount",IF(ABS(W28)>ABS(L28),"Tax is larger than the amount",""))))))))))))) | Y28: =IF(OR(T28=1,X28<>""),"",IF(AND(B28<>"",COUNTIF(tx_ID,B28)>1),"Duplicate transaction ID",IF(AND(L28<0,D28<>"Adjustment"),"Negative amount — check this entry",IF(AND(D28="Customer Payment",G28=""),"Add the customer",IF(AND(D28="Customer Payment",OR(J28="",COUNTIF(ar_No,J28&"")=0)),"Invoice # in Reference not found on AR sheet",IF(AND(D28="Bill Payment",H28=""),"Add the vendor",IF(AND(D28="Bill Payment",OR(J28="",COUNTIFS(ap_No,J28&"",ap_Party,H28&"")=0)),"Bill # + vendor not found on AP sheet",IF(AND(ISNUMBER(M28),N(M28)<>0,W28=0),"Tax ignored (tax tracking off, or not allowed for this type)",IF(V28=K28&"","Same account on both sides",IF(AND(ISNUMBER(StartDate),C28<StartDate),"Date is before the accounting start date",IF(AND(D28<>"Adjustment",IFERROR(INDEX(coa_Pay,MATCH(K28&"",coa_Name,0)),"")<>"Yes"),"Paid From / Deposited To is not a payment account",""))))))))))) | Z28: =IF(AND(T28=0,X28=""),1,0) | AA28: =IF(Z28=1,IF(U28="In",L28,L28-W28),0) | AB28: =IF(Z28=1,IF(U28="In",L28-W28,L28),0) | AC28: =IF(AND(Z28=1,U28="Out"),W28,0) | AD28: =IF(AND(Z28=1,U28="In"),W28,0)
B29: TX-0023 | C29: 46048 | D29: Money In | E29: Product Sales | F29: GCash / online orders week 4 | I29: E-Wallet | K29: E-Wallet / Online Payments | L29: 15775.69 | M29: 1690.25 | O29: =IF(Z29=1,L29-W29,"") | P29: =IF(V29="","",IFERROR(INDEX(coa_Type,MATCH(V29,coa_Name,0)),"")) | Q29: =IF(Z29=1,IF(U29="In",K29&"",V29),"") | R29: =IF(Z29=1,IF(U29="In",V29,K29&""),"") | S29: =IF(X29<>"","⛔ "&X29&" — not posted",IF(Y29<>"","⚠ "&Y29,IF(Z29=1,"✓ OK",""))) | T29: =IF(AND(C29="",D29="",E29="",L29="",K29=""),1,0) | U29: =IFERROR(INDEX(tt_Dir,MATCH(D29,tt_Type,0)),"") | V29: =IF(D29="","",IFERROR(IF(INDEX(tt_Other,MATCH(D29,tt_Type,0))="",E29&"",INDEX(tt_Other,MATCH(D29,tt_Type,0))),"")) | W29: =IF(OR(TaxOn<>"Yes",NOT(ISNUMBER(M29))),0,IF(IFERROR(INDEX(tt_Tax,MATCH(D29,tt_Type,0)),"No")="Yes",M29,0)) | X29: =IF(T29=1,"",IF(C29="","Missing transaction date",IF(NOT(ISNUMBER(C29)),"Invalid date",IF(OR(C29<DATE(2000,1,1),C29>DATE(2099,12,31)),"Invalid date",IF(D29="","Select a type",IF(U29="","Unknown type: "&D29,IF(V29="","Select an account (Category)",IF(ISNA(MATCH(V29,coa_Name,0)),"Unknown account: "&V29,IF(K29="","Select Paid From / Deposited To",IF(ISNA(MATCH(K29,coa_Name,0)),"Unknown account: "&K29,IF(NOT(ISNUMBER(L29)),"Enter an amount",IF(L29=0,"Enter an amount",IF(ABS(W29)>ABS(L29),"Tax is larger than the amount",""))))))))))))) | Y29: =IF(OR(T29=1,X29<>""),"",IF(AND(B29<>"",COUNTIF(tx_ID,B29)>1),"Duplicate transaction ID",IF(AND(L29<0,D29<>"Adjustment"),"Negative amount — check this entry",IF(AND(D29="Customer Payment",G29=""),"Add the customer",IF(AND(D29="Customer Payment",OR(J29="",COUNTIF(ar_No,J29&"")=0)),"Invoice # in Reference not found on AR sheet",IF(AND(D29="Bill Payment",H29=""),"Add the vendor",IF(AND(D29="Bill Payment",OR(J29="",COUNTIFS(ap_No,J29&"",ap_Party,H29&"")=0)),"Bill # + vendor not found on AP sheet",IF(AND(ISNUMBER(M29),N(M29)<>0,W29=0),"Tax ignored (tax tracking off, or not allowed for this type)",IF(V29=K29&"","Same account on both sides",IF(AND(ISNUMBER(StartDate),C29<StartDate),"Date is before the accounting start date",IF(AND(D29<>"Adjustment",IFERROR(INDEX(coa_Pay,MATCH(K29&"",coa_Name,0)),"")<>"Yes"),"Paid From / Deposited To is not a payment account",""))))))))))) | Z29: =IF(AND(T29=0,X29=""),1,0) | AA29: =IF(Z29=1,IF(U29="In",L29,L29-W29),0) | AB29: =IF(Z29=1,IF(U29="In",L29-W29,L29),0) | AC29: =IF(AND(Z29=1,U29="Out"),W29,0) | AD29: =IF(AND(Z29=1,U29="In"),W29,0)
B30: TX-0024 | C30: 46048 | D30: Bill Payment | F30: Supplier payment | H30: Fresh Dairy Co. | I30: Bank Transfer | J30: FR-012 | K30: Bank Account | L30: 18581.84 | O30: =IF(Z30=1,L30-W30,"") | P30: =IF(V30="","",IFERROR(INDEX(coa_Type,MATCH(V30,coa_Name,0)),"")) | Q30: =IF(Z30=1,IF(U30="In",K30&"",V30),"") | R30: =IF(Z30=1,IF(U30="In",V30,K30&""),"") | S30: =IF(X30<>"","⛔ "&X30&" — not posted",IF(Y30<>"","⚠ "&Y30,IF(Z30=1,"✓ OK",""))) | T30: =IF(AND(C30="",D30="",E30="",L30="",K30=""),1,0) | U30: =IFERROR(INDEX(tt_Dir,MATCH(D30,tt_Type,0)),"") | V30: =IF(D30="","",IFERROR(IF(INDEX(tt_Other,MATCH(D30,tt_Type,0))="",E30&"",INDEX(tt_Other,MATCH(D30,tt_Type,0))),"")) | W30: =IF(OR(TaxOn<>"Yes",NOT(ISNUMBER(M30))),0,IF(IFERROR(INDEX(tt_Tax,MATCH(D30,tt_Type,0)),"No")="Yes",M30,0)) | X30: =IF(T30=1,"",IF(C30="","Missing transaction date",IF(NOT(ISNUMBER(C30)),"Invalid date",IF(OR(C30<DATE(2000,1,1),C30>DATE(2099,12,31)),"Invalid date",IF(D30="","Select a type",IF(U30="","Unknown type: "&D30,IF(V30="","Select an account (Category)",IF(ISNA(MATCH(V30,coa_Name,0)),"Unknown account: "&V30,IF(K30="","Select Paid From / Deposited To",IF(ISNA(MATCH(K30,coa_Name,0)),"Unknown account: "&K30,IF(NOT(ISNUMBER(L30)),"Enter an amount",IF(L30=0,"Enter an amount",IF(ABS(W30)>ABS(L30),"Tax is larger than the amount",""))))))))))))) | Y30: =IF(OR(T30=1,X30<>""),"",IF(AND(B30<>"",COUNTIF(tx_ID,B30)>1),"Duplicate transaction ID",IF(AND(L30<0,D30<>"Adjustment"),"Negative amount — check this entry",IF(AND(D30="Customer Payment",G30=""),"Add the customer",IF(AND(D30="Customer Payment",OR(J30="",COUNTIF(ar_No,J30&"")=0)),"Invoice # in Reference not found on AR sheet",IF(AND(D30="Bill Payment",H30=""),"Add the vendor",IF(AND(D30="Bill Payment",OR(J30="",COUNTIFS(ap_No,J30&"",ap_Party,H30&"")=0)),"Bill # + vendor not found on AP sheet",IF(AND(ISNUMBER(M30),N(M30)<>0,W30=0),"Tax ignored (tax tracking off, or not allowed for this type)",IF(V30=K30&"","Same account on both sides",IF(AND(ISNUMBER(StartDate),C30<StartDate),"Date is before the accounting start date",IF(AND(D30<>"Adjustment",IFERROR(INDEX(coa_Pay,MATCH(K30&"",coa_Name,0)),"")<>"Yes"),"Paid From / Deposited To is not a payment account",""))))))))))) | Z30: =IF(AND(T30=0,X30=""),1,0) | AA30: =IF(Z30=1,IF(U30="In",L30,L30-W30),0) | AB30: =IF(Z30=1,IF(U30="In",L30-W30,L30),0) | AC30: =IF(AND(Z30=1,U30="Out"),W30,0) | AD30: =IF(AND(Z30=1,U30="In"),W30,0)
B31: TX-0025 | C31: 46049 | D31: Transfer | E31: Bank Account | F31: Cash deposit to bank | I31: Cash | K31: Cash on Hand | L31: 51100 | O31: =IF(Z31=1,L31-W31,"") | P31: =IF(V31="","",IFERROR(INDEX(coa_Type,MATCH(V31,coa_Name,0)),"")) | Q31: =IF(Z31=1,IF(U31="In",K31&"",V31),"") | R31: =IF(Z31=1,IF(U31="In",V31,K31&""),"") | S31: =IF(X31<>"","⛔ "&X31&" — not posted",IF(Y31<>"","⚠ "&Y31,IF(Z31=1,"✓ OK",""))) | T31: =IF(AND(C31="",D31="",E31="",L31="",K31=""),1,0) | U31: =IFERROR(INDEX(tt_Dir,MATCH(D31,tt_Type,0)),"") | V31: =IF(D31="","",IFERROR(IF(INDEX(tt_Other,MATCH(D31,tt_Type,0))="",E31&"",INDEX(tt_Other,MATCH(D31,tt_Type,0))),"")) | W31: =IF(OR(TaxOn<>"Yes",NOT(ISNUMBER(M31))),0,IF(IFERROR(INDEX(tt_Tax,MATCH(D31,tt_Type,0)),"No")="Yes",M31,0)) | X31: =IF(T31=1,"",IF(C31="","Missing transaction date",IF(NOT(ISNUMBER(C31)),"Invalid date",IF(OR(C31<DATE(2000,1,1),C31>DATE(2099,12,31)),"Invalid date",IF(D31="","Select a type",IF(U31="","Unknown type: "&D31,IF(V31="","Select an account (Category)",IF(ISNA(MATCH(V31,coa_Name,0)),"Unknown account: "&V31,IF(K31="","Select Paid From / Deposited To",IF(ISNA(MATCH(K31,coa_Name,0)),"Unknown account: "&K31,IF(NOT(ISNUMBER(L31)),"Enter an amount",IF(L31=0,"Enter an amount",IF(ABS(W31)>ABS(L31),"Tax is larger than the amount",""))))))))))))) | Y31: =IF(OR(T31=1,X31<>""),"",IF(AND(B31<>"",COUNTIF(tx_ID,B31)>1),"Duplicate transaction ID",IF(AND(L31<0,D31<>"Adjustment"),"Negative amount — check this entry",IF(AND(D31="Customer Payment",G31=""),"Add the customer",IF(AND(D31="Customer Payment",OR(J31="",COUNTIF(ar_No,J31&"")=0)),"Invoice # in Reference not found on AR sheet",IF(AND(D31="Bill Payment",H31=""),"Add the vendor",IF(AND(D31="Bill Payment",OR(J31="",COUNTIFS(ap_No,J31&"",ap_Party,H31&"")=0)),"Bill # + vendor not found on AP sheet",IF(AND(ISNUMBER(M31),N(M31)<>0,W31=0),"Tax ignored (tax tracking off, or not allowed for this type)",IF(V31=K31&"","Same account on both sides",IF(AND(ISNUMBER(StartDate),C31<StartDate),"Date is before the accounting start date",IF(AND(D31<>"Adjustment",IFERROR(INDEX(coa_Pay,MATCH(K31&"",coa_Name,0)),"")<>"Yes"),"Paid From / Deposited To is not a payment account",""))))))))))) | Z31: =IF(AND(T31=0,X31=""),1,0) | AA31: =IF(Z31=1,IF(U31="In",L31,L31-W31),0) | AB31: =IF(Z31=1,IF(U31="In",L31-W31,L31),0) | AC31: =IF(AND(Z31=1,U31="Out"),W31,0) | AD31: =IF(AND(Z31=1,U31="In"),W31,0)
B32: TX-0026 | C32: 46049 | D32: Money Out | E32: Bank & Payment Fees | F32: Monthly bank charge | I32: Bank Transfer | K32: Bank Account | L32: 150 | O32: =IF(Z32=1,L32-W32,"") | P32: =IF(V32="","",IFERROR(INDEX(coa_Type,MATCH(V32,coa_Name,0)),"")) | Q32: =IF(Z32=1,IF(U32="In",K32&"",V32),"") | R32: =IF(Z32=1,IF(U32="In",V32,K32&""),"") | S32: =IF(X32<>"","⛔ "&X32&" — not posted",IF(Y32<>"","⚠ "&Y32,IF(Z32=1,"✓ OK",""))) | T32: =IF(AND(C32="",D32="",E32="",L32="",K32=""),1,0) | U32: =IFERROR(INDEX(tt_Dir,MATCH(D32,tt_Type,0)),"") | V32: =IF(D32="","",IFERROR(IF(INDEX(tt_Other,MATCH(D32,tt_Type,0))="",E32&"",INDEX(tt_Other,MATCH(D32,tt_Type,0))),"")) | W32: =IF(OR(TaxOn<>"Yes",NOT(ISNUMBER(M32))),0,IF(IFERROR(INDEX(tt_Tax,MATCH(D32,tt_Type,0)),"No")="Yes",M32,0)) | X32: =IF(T32=1,"",IF(C32="","Missing transaction date",IF(NOT(ISNUMBER(C32)),"Invalid date",IF(OR(C32<DATE(2000,1,1),C32>DATE(2099,12,31)),"Invalid date",IF(D32="","Select a type",IF(U32="","Unknown type: "&D32,IF(V32="","Select an account (Category)",IF(ISNA(MATCH(V32,coa_Name,0)),"Unknown account: "&V32,IF(K32="","Select Paid From / Deposited To",IF(ISNA(MATCH(K32,coa_Name,0)),"Unknown account: "&K32,IF(NOT(ISNUMBER(L32)),"Enter an amount",IF(L32=0,"Enter an amount",IF(ABS(W32)>ABS(L32),"Tax is larger than the amount",""))))))))))))) | Y32: =IF(OR(T32=1,X32<>""),"",IF(AND(B32<>"",COUNTIF(tx_ID,B32)>1),"Duplicate transaction ID",IF(AND(L32<0,D32<>"Adjustment"),"Negative amount — check this entry",IF(AND(D32="Customer Payment",G32=""),"Add the customer",IF(AND(D32="Customer Payment",OR(J32="",COUNTIF(ar_No,J32&"")=0)),"Invoice # in Reference not found on AR sheet",IF(AND(D32="Bill Payment",H32=""),"Add the vendor",IF(AND(D32="Bill Payment",OR(J32="",COUNTIFS(ap_No,J32&"",ap_Party,H32&"")=0)),"Bill # + vendor not found on AP sheet",IF(AND(ISNUMBER(M32),N(M32)<>0,W32=0),"Tax ignored (tax tracking off, or not allowed for this type)",IF(V32=K32&"","Same account on both sides",IF(AND(ISNUMBER(StartDate),C32<StartDate),"Date is before the accounting start date",IF(AND(D32<>"Adjustment",IFERROR(INDEX(coa_Pay,MATCH(K32&"",coa_Name,0)),"")<>"Yes"),"Paid From / Deposited To is not a payment account",""))))))))))) | Z32: =IF(AND(T32=0,X32=""),1,0) | AA32: =IF(Z32=1,IF(U32="In",L32,L32-W32),0) | AB32: =IF(Z32=1,IF(U32="In",L32-W32,L32),0) | AC32: =IF(AND(Z32=1,U32="Out"),W32,0) | AD32: =IF(AND(Z32=1,U32="In"),W32,0)
B33: TX-0027 | C33: 46050 | D33: Transfer | E33: Bank Account | F33: E-wallet cash-out to bank | I33: Online Payment | K33: E-Wallet / Online Payments | L33: 50200 | O33: =IF(Z33=1,L33-W33,"") | P33: =IF(V33="","",IFERROR(INDEX(coa_Type,MATCH(V33,coa_Name,0)),"")) | Q33: =IF(Z33=1,IF(U33="In",K33&"",V33),"") | R33: =IF(Z33=1,IF(U33="In",V33,K33&""),"") | S33: =IF(X33<>"","⛔ "&X33&" — not posted",IF(Y33<>"","⚠ "&Y33,IF(Z33=1,"✓ OK",""))) | T33: =IF(AND(C33="",D33="",E33="",L33="",K33=""),1,0) | U33: =IFERROR(INDEX(tt_Dir,MATCH(D33,tt_Type,0)),"") | V33: =IF(D33="","",IFERROR(IF(INDEX(tt_Other,MATCH(D33,tt_Type,0))="",E33&"",INDEX(tt_Other,MATCH(D33,tt_Type,0))),"")) | W33: =IF(OR(TaxOn<>"Yes",NOT(ISNUMBER(M33))),0,IF(IFERROR(INDEX(tt_Tax,MATCH(D33,tt_Type,0)),"No")="Yes",M33,0)) | X33: =IF(T33=1,"",IF(C33="","Missing transaction date",IF(NOT(ISNUMBER(C33)),"Invalid date",IF(OR(C33<DATE(2000,1,1),C33>DATE(2099,12,31)),"Invalid date",IF(D33="","Select a type",IF(U33="","Unknown type: "&D33,IF(V33="","Select an account (Category)",IF(ISNA(MATCH(V33,coa_Name,0)),"Unknown account: "&V33,IF(K33="","Select Paid From / Deposited To",IF(ISNA(MATCH(K33,coa_Name,0)),"Unknown account: "&K33,IF(NOT(ISNUMBER(L33)),"Enter an amount",IF(L33=0,"Enter an amount",IF(ABS(W33)>ABS(L33),"Tax is larger than the amount",""))))))))))))) | Y33: =IF(OR(T33=1,X33<>""),"",IF(AND(B33<>"",COUNTIF(tx_ID,B33)>1),"Duplicate transaction ID",IF(AND(L33<0,D33<>"Adjustment"),"Negative amount — check this entry",IF(AND(D33="Customer Payment",G33=""),"Add the customer",IF(AND(D33="Customer Payment",OR(J33="",COUNTIF(ar_No,J33&"")=0)),"Invoice # in Reference not found on AR sheet",IF(AND(D33="Bill Payment",H33=""),"Add the vendor",IF(AND(D33="Bill Payment",OR(J33="",COUNTIFS(ap_No,J33&"",ap_Party,H33&"")=0)),"Bill # + vendor not found on AP sheet",IF(AND(ISNUMBER(M33),N(M33)<>0,W33=0),"Tax ignored (tax tracking off, or not allowed for this type)",IF(V33=K33&"","Same account on both sides",IF(AND(ISNUMBER(StartDate),C33<StartDate),"Date is before the accounting start date",IF(AND(D33<>"Adjustment",IFERROR(INDEX(coa_Pay,MATCH(K33&"",coa_Name,0)),"")<>"Yes"),"Paid From / Deposited To is not a payment account",""))))))))))) | Z33: =IF(AND(T33=0,X33=""),1,0) | AA33: =IF(Z33=1,IF(U33="In",L33,L33-W33),0) | AB33: =IF(Z33=1,IF(U33="In",L33-W33,L33),0) | AC33: =IF(AND(Z33=1,U33="Out"),W33,0) | AD33: =IF(AND(Z33=1,U33="In"),W33,0)
B34: TX-0028 | C34: 46050 | D34: Money Out | E34: Direct Labor | F34: Bakers' salaries (16th-end) | I34: Bank Transfer | K34: Bank Account | L34: 38000 | O34: =IF(Z34=1,L34-W34,"") | P34: =IF(V34="","",IFERROR(INDEX(coa_Type,MATCH(V34,coa_Name,0)),"")) | Q34: =IF(Z34=1,IF(U34="In",K34&"",V34),"") | R34: =IF(Z34=1,IF(U34="In",V34,K34&""),"") | S34: =IF(X34<>"","⛔ "&X34&" — not posted",IF(Y34<>"","⚠ "&Y34,IF(Z34=1,"✓ OK",""))) | T34: =IF(AND(C34="",D34="",E34="",L34="",K34=""),1,0) | U34: =IFERROR(INDEX(tt_Dir,MATCH(D34,tt_Type,0)),"") | V34: =IF(D34="","",IFERROR(IF(INDEX(tt_Other,MATCH(D34,tt_Type,0))="",E34&"",INDEX(tt_Other,MATCH(D34,tt_Type,0))),"")) | W34: =IF(OR(TaxOn<>"Yes",NOT(ISNUMBER(M34))),0,IF(IFERROR(INDEX(tt_Tax,MATCH(D34,tt_Type,0)),"No")="Yes",M34,0)) | X34: =IF(T34=1,"",IF(C34="","Missing transaction date",IF(NOT(ISNUMBER(C34)),"Invalid date",IF(OR(C34<DATE(2000,1,1),C34>DATE(2099,12,31)),"Invalid date",IF(D34="","Select a type",IF(U34="","Unknown type: "&D34,IF(V34="","Select an account (Category)",IF(ISNA(MATCH(V34,coa_Name,0)),"Unknown account: "&V34,IF(K34="","Select Paid From / Deposited To",IF(ISNA(MATCH(K34,coa_Name,0)),"Unknown account: "&K34,IF(NOT(ISNUMBER(L34)),"Enter an amount",IF(L34=0,"Enter an amount",IF(ABS(W34)>ABS(L34),"Tax is larger than the amount",""))))))))))))) | Y34: =IF(OR(T34=1,X34<>""),"",IF(AND(B34<>"",COUNTIF(tx_ID,B34)>1),"Duplicate transaction ID",IF(AND(L34<0,D34<>"Adjustment"),"Negative amount — check this entry",IF(AND(D34="Customer Payment",G34=""),"Add the customer",IF(AND(D34="Customer Payment",OR(J34="",COUNTIF(ar_No,J34&"")=0)),"Invoice # in Reference not found on AR sheet",IF(AND(D34="Bill Payment",H34=""),"Add the vendor",IF(AND(D34="Bill Payment",OR(J34="",COUNTIFS(ap_No,J34&"",ap_Party,H34&"")=0)),"Bill # + vendor not found on AP sheet",IF(AND(ISNUMBER(M34),N(M34)<>0,W34=0),"Tax ignored (tax tracking off, or not allowed for this type)",IF(V34=K34&"","Same account on both sides",IF(AND(ISNUMBER(StartDate),C34<StartDate),"Date is before the accounting start date",IF(AND(D34<>"Adjustment",IFERROR(INDEX(coa_Pay,MATCH(K34&"",coa_Name,0)),"")<>"Yes"),"Paid From / Deposited To is not a payment account",""))))))))))) | Z34: =IF(AND(T34=0,X34=""),1,0) | AA34: =IF(Z34=1,IF(U34="In",L34,L34-W34),0) | AB34: =IF(Z34=1,IF(U34="In",L34-W34,L34),0) | AC34: =IF(AND(Z34=1,U34="Out"),W34,0) | AD34: =IF(AND(Z34=1,U34="In"),W34,0)
B35: TX-0029 | C35: 46050 | D35: Money Out | E35: Salaries & Wages | F35: Cashier salary (16th-end) | I35: Bank Transfer | K35: Bank Account | L35: 9000 | O35: =IF(Z35=1,L35-W35,"") | P35: =IF(V35="","",IFERROR(INDEX(coa_Type,MATCH(V35,coa_Name,0)),"")) | Q35: =IF(Z35=1,IF(U35="In",K35&"",V35),"") | R35: =IF(Z35=1,IF(U35="In",V35,K35&""),"") | S35: =IF(X35<>"","⛔ "&X35&" — not posted",IF(Y35<>"","⚠ "&Y35,IF(Z35=1,"✓ OK",""))) | T35: =IF(AND(C35="",D35="",E35="",L35="",K35=""),1,0) | U35: =IFERROR(INDEX(tt_Dir,MATCH(D35,tt_Type,0)),"") | V35: =IF(D35="","",IFERROR(IF(INDEX(tt_Other,MATCH(D35,tt_Type,0))="",E35&"",INDEX(tt_Other,MATCH(D35,tt_Type,0))),"")) | W35: =IF(OR(TaxOn<>"Yes",NOT(ISNUMBER(M35))),0,IF(IFERROR(INDEX(tt_Tax,MATCH(D35,tt_Type,0)),"No")="Yes",M35,0)) | X35: =IF(T35=1,"",IF(C35="","Missing transaction date",IF(NOT(ISNUMBER(C35)),"Invalid date",IF(OR(C35<DATE(2000,1,1),C35>DATE(2099,12,31)),"Invalid date",IF(D35="","Select a type",IF(U35="","Unknown type: "&D35,IF(V35="","Select an account (Category)",IF(ISNA(MATCH(V35,coa_Name,0)),"Unknown account: "&V35,IF(K35="","Select Paid From / Deposited To",IF(ISNA(MATCH(K35,coa_Name,0)),"Unknown account: "&K35,IF(NOT(ISNUMBER(L35)),"Enter an amount",IF(L35=0,"Enter an amount",IF(ABS(W35)>ABS(L35),"Tax is larger than the amount",""))))))))))))) | Y35: =IF(OR(T35=1,X35<>""),"",IF(AND(B35<>"",COUNTIF(tx_ID,B35)>1),"Duplicate transaction ID",IF(AND(L35<0,D35<>"Adjustment"),"Negative amount — check this entry",IF(AND(D35="Customer Payment",G35=""),"Add the customer",IF(AND(D35="Customer Payment",OR(J35="",COUNTIF(ar_No,J35&"")=0)),"Invoice # in Reference not found on AR sheet",IF(AND(D35="Bill Payment",H35=""),"Add the vendor",IF(AND(D35="Bill Payment",OR(J35="",COUNTIFS(ap_No,J35&"",ap_Party,H35&"")=0)),"Bill # + vendor not found on AP sheet",IF(AND(ISNUMBER(M35),N(M35)<>0,W35=0),"Tax ignored (tax tracking off, or not allowed for this type)",IF(V35=K35&"","Same account on both sides",IF(AND(ISNUMBER(StartDate),C35<StartDate),"Date is before the accounting start date",IF(AND(D35<>"Adjustment",IFERROR(INDEX(coa_Pay,MATCH(K35&"",coa_Name,0)),"")<>"Yes"),"Paid From / Deposited To is not a payment account",""))))))))))) | Z35: =IF(AND(T35=0,X35=""),1,0) | AA35: =IF(Z35=1,IF(U35="In",L35,L35-W35),0) | AB35: =IF(Z35=1,IF(U35="In",L35-W35,L35),0) | AC35: =IF(AND(Z35=1,U35="Out"),W35,0) | AD35: =IF(AND(Z35=1,U35="In"),W35,0)
B36: TX-0030 | C36: 46052 | D36: Adjustment | E36: Depreciation | F36: Monthly depreciation of equipment | K36: Accumulated Depreciation | L36: 3000 | O36: =IF(Z36=1,L36-W36,"") | P36: =IF(V36="","",IFERROR(INDEX(coa_Type,MATCH(V36,coa_Name,0)),"")) | Q36: =IF(Z36=1,IF(U36="In",K36&"",V36),"") | R36: =IF(Z36=1,IF(U36="In",V36,K36&""),"") | S36: =IF(X36<>"","⛔ "&X36&" — not posted",IF(Y36<>"","⚠ "&Y36,IF(Z36=1,"✓ OK",""))) | T36: =IF(AND(C36="",D36="",E36="",L36="",K36=""),1,0) | U36: =IFERROR(INDEX(tt_Dir,MATCH(D36,tt_Type,0)),"") | V36: =IF(D36="","",IFERROR(IF(INDEX(tt_Other,MATCH(D36,tt_Type,0))="",E36&"",INDEX(tt_Other,MATCH(D36,tt_Type,0))),"")) | W36: =IF(OR(TaxOn<>"Yes",NOT(ISNUMBER(M36))),0,IF(IFERROR(INDEX(tt_Tax,MATCH(D36,tt_Type,0)),"No")="Yes",M36,0)) | X36: =IF(T36=1,"",IF(C36="","Missing transaction date",IF(NOT(ISNUMBER(C36)),"Invalid date",IF(OR(C36<DATE(2000,1,1),C36>DATE(2099,12,31)),"Invalid date",IF(D36="","Select a type",IF(U36="","Unknown type: "&D36,IF(V36="","Select an account (Category)",IF(ISNA(MATCH(V36,coa_Name,0)),"Unknown account: "&V36,IF(K36="","Select Paid From / Deposited To",IF(ISNA(MATCH(K36,coa_Name,0)),"Unknown account: "&K36,IF(NOT(ISNUMBER(L36)),"Enter an amount",IF(L36=0,"Enter an amount",IF(ABS(W36)>ABS(L36),"Tax is larger than the amount",""))))))))))))) | Y36: =IF(OR(T36=1,X36<>""),"",IF(AND(B36<>"",COUNTIF(tx_ID,B36)>1),"Duplicate transaction ID",IF(AND(L36<0,D36<>"Adjustment"),"Negative amount — check this entry",IF(AND(D36="Customer Payment",G36=""),"Add the customer",IF(AND(D36="Customer Payment",OR(J36="",COUNTIF(ar_No,J36&"")=0)),"Invoice # in Reference not found on AR sheet",IF(AND(D36="Bill Payment",H36=""),"Add the vendor",IF(AND(D36="Bill Payment",OR(J36="",COUNTIFS(ap_No,J36&"",ap_Party,H36&"")=0)),"Bill # + vendor not found on AP sheet",IF(AND(ISNUMBER(M36),N(M36)<>0,W36=0),"Tax ignored (tax tracking off, or not allowed for this type)",IF(V36=K36&"","Same account on both sides",IF(AND(ISNUMBER(StartDate),C36<StartDate),"Date is before the accounting start date",IF(AND(D36<>"Adjustment",IFERROR(INDEX(coa_Pay,MATCH(K36&"",coa_Name,0)),"")<>"Yes"),"Paid From / Deposited To is not a payment account",""))))))))))) | Z36: =IF(AND(T36=0,X36=""),1,0) | AA36: =IF(Z36=1,IF(U36="In",L36,L36-W36),0) | AB36: =IF(Z36=1,IF(U36="In",L36-W36,L36),0) | AC36: =IF(AND(Z36=1,U36="Out"),W36,0) | AD36: =IF(AND(Z36=1,U36="In"),W36,0)
B37: TX-0031 | C37: 46054 | D37: Money Out | E37: Rent | F37: Shop rent | I37: Bank Transfer | J37: RENT-02 | K37: Bank Account | L37: 28000 | M37: 3000 | O37: =IF(Z37=1,L37-W37,"") | P37: =IF(V37="","",IFERROR(INDEX(coa_Type,MATCH(V37,coa_Name,0)),"")) | Q37: =IF(Z37=1,IF(U37="In",K37&"",V37),"") | R37: =IF(Z37=1,IF(U37="In",V37,K37&""),"") | S37: =IF(X37<>"","⛔ "&X37&" — not posted",IF(Y37<>"","⚠ "&Y37,IF(Z37=1,"✓ OK",""))) | T37: =IF(AND(C37="",D37="",E37="",L37="",K37=""),1,0) | U37: =IFERROR(INDEX(tt_Dir,MATCH(D37,tt_Type,0)),"") | V37: =IF(D37="","",IFERROR(IF(INDEX(tt_Other,MATCH(D37,tt_Type,0))="",E37&"",INDEX(tt_Other,MATCH(D37,tt_Type,0))),"")) | W37: =IF(OR(TaxOn<>"Yes",NOT(ISNUMBER(M37))),0,IF(IFERROR(INDEX(tt_Tax,MATCH(D37,tt_Type,0)),"No")="Yes",M37,0)) | X37: =IF(T37=1,"",IF(C37="","Missing transaction date",IF(NOT(ISNUMBER(C37)),"Invalid date",IF(OR(C37<DATE(2000,1,1),C37>DATE(2099,12,31)),"Invalid date",IF(D37="","Select a type",IF(U37="","Unknown type: "&D37,IF(V37="","Select an account (Category)",IF(ISNA(MATCH(V37,coa_Name,0)),"Unknown account: "&V37,IF(K37="","Select Paid From / Deposited To",IF(ISNA(MATCH(K37,coa_Name,0)),"Unknown account: "&K37,IF(NOT(ISNUMBER(L37)),"Enter an amount",IF(L37=0,"Enter an amount",IF(ABS(W37)>ABS(L37),"Tax is larger than the amount",""))))))))))))) | Y37: =IF(OR(T37=1,X37<>""),"",IF(AND(B37<>"",COUNTIF(tx_ID,B37)>1),"Duplicate transaction ID",IF(AND(L37<0,D37<>"Adjustment"),"Negative amount — check this entry",IF(AND(D37="Customer Payment",G37=""),"Add the customer",IF(AND(D37="Customer Payment",OR(J37="",COUNTIF(ar_No,J37&"")=0)),"Invoice # in Reference not found on AR sheet",IF(AND(D37="Bill Payment",H37=""),"Add the vendor",IF(AND(D37="Bill Payment",OR(J37="",COUNTIFS(ap_No,J37&"",ap_Party,H37&"")=0)),"Bill # + vendor not found on AP sheet",IF(AND(ISNUMBER(M37),N(M37)<>0,W37=0),"Tax ignored (tax tracking off, or not allowed for this type)",IF(V37=K37&"","Same account on both sides",IF(AND(ISNUMBER(StartDate),C37<StartDate),"Date is before the accounting start date",IF(AND(D37<>"Adjustment",IFERROR(INDEX(coa_Pay,MATCH(K37&"",coa_Name,0)),"")<>"Yes"),"Paid From / Deposited To is not a payment account",""))))))))))) | Z37: =IF(AND(T37=0,X37=""),1,0) | AA37: =IF(Z37=1,IF(U37="In",L37,L37-W37),0) | AB37: =IF(Z37=1,IF(U37="In",L37-W37,L37),0) | AC37: =IF(AND(Z37=1,U37="Out"),W37,0) | AD37: =IF(AND(Z37=1,U37="In"),W37,0)
B38: TX-0032 | C38: 46055 | D38: Bill Payment | F38: Supplier payment | H38: Fresh Dairy Co. | I38: Bank Transfer | J38: FR-011 | K38: Bank Account | L38: 18464.42 | O38: =IF(Z38=1,L38-W38,"") | P38: =IF(V38="","",IFERROR(INDEX(coa_Type,MATCH(V38,coa_Name,0)),"")) | Q38: =IF(Z38=1,IF(U38="In",K38&"",V38),"") | R38: =IF(Z38=1,IF(U38="In",V38,K38&""),"") | S38: =IF(X38<>"","⛔ "&X38&" — not posted",IF(Y38<>"","⚠ "&Y38,IF(Z38=1,"✓ OK",""))) | T38: =IF(AND(C38="",D38="",E38="",L38="",K38=""),1,0) | U38: =IFERROR(INDEX(tt_Dir,MATCH(D38,tt_Type,0)),"") | V38: =IF(D38="","",IFERROR(IF(INDEX(tt_Other,MATCH(D38,tt_Type,0))="",E38&"",INDEX(tt_Other,MATCH(D38,tt_Type,0))),"")) | W38: =IF(OR(TaxOn<>"Yes",NOT(ISNUMBER(M38))),0,IF(IFERROR(INDEX(tt_Tax,MATCH(D38,tt_Type,0)),"No")="Yes",M38,0)) | X38: =IF(T38=1,"",IF(C38="","Missing transaction date",IF(NOT(ISNUMBER(C38)),"Invalid date",IF(OR(C38<DATE(2000,1,1),C38>DATE(2099,12,31)),"Invalid date",IF(D38="","Select a type",IF(U38="","Unknown type: "&D38,IF(V38="","Select an account (Category)",IF(ISNA(MATCH(V38,coa_Name,0)),"Unknown account: "&V38,IF(K38="","Select Paid From / Deposited To",IF(ISNA(MATCH(K38,coa_Name,0)),"Unknown account: "&K38,IF(NOT(ISNUMBER(L38)),"Enter an amount",IF(L38=0,"Enter an amount",IF(ABS(W38)>ABS(L38),"Tax is larger than the amount",""))))))))))))) | Y38: =IF(OR(T38=1,X38<>""),"",IF(AND(B38<>"",COUNTIF(tx_ID,B38)>1),"Duplicate transaction ID",IF(AND(L38<0,D38<>"Adjustment"),"Negative amount — check this entry",IF(AND(D38="Customer Payment",G38=""),"Add the customer",IF(AND(D38="Customer Payment",OR(J38="",COUNTIF(ar_No,J38&"")=0)),"Invoice # in Reference not found on AR sheet",IF(AND(D38="Bill Payment",H38=""),"Add the vendor",IF(AND(D38="Bill Payment",OR(J38="",COUNTIFS(ap_No,J38&"",ap_Party,H38&"")=0)),"Bill # + vendor not found on AP sheet",IF(AND(ISNUMBER(M38),N(M38)<>0,W38=0),"Tax ignored (tax tracking off, or not allowed for this type)",IF(V38=K38&"","Same account on both sides",IF(AND(ISNUMBER(StartDate),C38<StartDate),"Date is before the accounting start date",IF(AND(D38<>"Adjustment",IFERROR(INDEX(coa_Pay,MATCH(K38&"",coa_Name,0)),"")<>"Yes"),"Paid From / Deposited To is not a payment account",""))))))))))) | Z38: =IF(AND(T38=0,X38=""),1,0) | AA38: =IF(Z38=1,IF(U38="In",L38,L38-W38),0) | AB38: =IF(Z38=1,IF(U38="In",L38-W38,L38),0) | AC38: =IF(AND(Z38=1,U38="Out"),W38,0) | AD38: =IF(AND(Z38=1,U38="In"),W38,0)
B39: TX-0033 | C39: 46057 | D39: Money In | E39: Product Sales | F39: Counter sales week 1 | I39: Cash | K39: Cash on Hand | L39: 54543.17 | M39: 5843.91 | O39: =IF(Z39=1,L39-W39,"") | P39: =IF(V39="","",IFERROR(INDEX(coa_Type,MATCH(V39,coa_Name,0)),"")) | Q39: =IF(Z39=1,IF(U39="In",K39&"",V39),"") | R39: =IF(Z39=1,IF(U39="In",V39,K39&""),"") | S39: =IF(X39<>"","⛔ "&X39&" — not posted",IF(Y39<>"","⚠ "&Y39,IF(Z39=1,"✓ OK",""))) | T39: =IF(AND(C39="",D39="",E39="",L39="",K39=""),1,0) | U39: =IFERROR(INDEX(tt_Dir,MATCH(D39,tt_Type,0)),"") | V39: =IF(D39="","",IFERROR(IF(INDEX(tt_Other,MATCH(D39,tt_Type,0))="",E39&"",INDEX(tt_Other,MATCH(D39,tt_Type,0))),"")) | W39: =IF(OR(TaxOn<>"Yes",NOT(ISNUMBER(M39))),0,IF(IFERROR(INDEX(tt_Tax,MATCH(D39,tt_Type,0)),"No")="Yes",M39,0)) | X39: =IF(T39=1,"",IF(C39="","Missing transaction date",IF(NOT(ISNUMBER(C39)),"Invalid date",IF(OR(C39<DATE(2000,1,1),C39>DATE(2099,12,31)),"Invalid date",IF(D39="","Select a type",IF(U39="","Unknown type: "&D39,IF(V39="","Select an account (Category)",IF(ISNA(MATCH(V39,coa_Name,0)),"Unknown account: "&V39,IF(K39="","Select Paid From / Deposited To",IF(ISNA(MATCH(K39,coa_Name,0)),"Unknown account: "&K39,IF(NOT(ISNUMBER(L39)),"Enter an amount",IF(L39=0,"Enter an amount",IF(ABS(W39)>ABS(L39),"Tax is larger than the amount",""))))))))))))) | Y39: =IF(OR(T39=1,X39<>""),"",IF(AND(B39<>"",COUNTIF(tx_ID,B39)>1),"Duplicate transaction ID",IF(AND(L39<0,D39<>"Adjustment"),"Negative amount — check this entry",IF(AND(D39="Customer Payment",G39=""),"Add the customer",IF(AND(D39="Customer Payment",OR(J39="",COUNTIF(ar_No,J39&"")=0)),"Invoice # in Reference not found on AR sheet",IF(AND(D39="Bill Payment",H39=""),"Add the vendor",IF(AND(D39="Bill Payment",OR(J39="",COUNTIFS(ap_No,J39&"",ap_Party,H39&"")=0)),"Bill # + vendor not found on AP sheet",IF(AND(ISNUMBER(M39),N(M39)<>0,W39=0),"Tax ignored (tax tracking off, or not allowed for this type)",IF(V39=K39&"","Same account on both sides",IF(AND(ISNUMBER(StartDate),C39<StartDate),"Date is before the accounting start date",IF(AND(D39<>"Adjustment",IFERROR(INDEX(coa_Pay,MATCH(K39&"",coa_Name,0)),"")<>"Yes"),"Paid From / Deposited To is not a payment account",""))))))))))) | Z39: =IF(AND(T39=0,X39=""),1,0) | AA39: =IF(Z39=1,IF(U39="In",L39,L39-W39),0) | AB39: =IF(Z39=1,IF(U39="In",L39-W39,L39),0) | AC39: =IF(AND(Z39=1,U39="Out"),W39,0) | AD39: =IF(AND(Z39=1,U39="In"),W39,0)
B40: TX-0034 | C40: 46058 | D40: Customer Payment | F40: Partial payment | G40: Brightpath Academy | I40: Bank Transfer | J40: INV-1002 | K40: Bank Account | L40: 20273.83 | O40: =IF(Z40=1,L40-W40,"") | P40: =IF(V40="","",IFERROR(INDEX(coa_Type,MATCH(V40,coa_Name,0)),"")) | Q40: =IF(Z40=1,IF(U40="In",K40&"",V40),"") | R40: =IF(Z40=1,IF(U40="In",V40,K40&""),"") | S40: =IF(X40<>"","⛔ "&X40&" — not posted",IF(Y40<>"","⚠ "&Y40,IF(Z40=1,"✓ OK",""))) | T40: =IF(AND(C40="",D40="",E40="",L40="",K40=""),1,0) | U40: =IFERROR(INDEX(tt_Dir,MATCH(D40,tt_Type,0)),"") | V40: =IF(D40="","",IFERROR(IF(INDEX(tt_Other,MATCH(D40,tt_Type,0))="",E40&"",INDEX(tt_Other,MATCH(D40,tt_Type,0))),"")) | W40: =IF(OR(TaxOn<>"Yes",NOT(ISNUMBER(M40))),0,IF(IFERROR(INDEX(tt_Tax,MATCH(D40,tt_Type,0)),"No")="Yes",M40,0)) | X40: =IF(T40=1,"",IF(C40="","Missing transaction date",IF(NOT(ISNUMBER(C40)),"Invalid date",IF(OR(C40<DATE(2000,1,1),C40>DATE(2099,12,31)),"Invalid date",IF(D40="","Select a type",IF(U40="","Unknown type: "&D40,IF(V40="","Select an account (Category)",IF(ISNA(MATCH(V40,coa_Name,0)),"Unknown account: "&V40,IF(K40="","Select Paid From / Deposited To",IF(ISNA(MATCH(K40,coa_Name,0)),"Unknown account: "&K40,IF(NOT(ISNUMBER(L40)),"Enter an amount",IF(L40=0,"Enter an amount",IF(ABS(W40)>ABS(L40),"Tax is larger than the amount",""))))))))))))) | Y40: =IF(OR(T40=1,X40<>""),"",IF(AND(B40<>"",COUNTIF(tx_ID,B40)>1),"Duplicate transaction ID",IF(AND(L40<0,D40<>"Adjustment"),"Negative amount — check this entry",IF(AND(D40="Customer Payment",G40=""),"Add the customer",IF(AND(D40="Customer Payment",OR(J40="",COUNTIF(ar_No,J40&"")=0)),"Invoice # in Reference not found on AR sheet",IF(AND(D40="Bill Payment",H40=""),"Add the vendor",IF(AND(D40="Bill Payment",OR(J40="",COUNTIFS(ap_No,J40&"",ap_Party,H40&"")=0)),"Bill # + vendor not found on AP sheet",IF(AND(ISNUMBER(M40),N(M40)<>0,W40=0),"Tax ignored (tax tracking off, or not allowed for this type)",IF(V40=K40&"","Same account on both sides",IF(AND(ISNUMBER(StartDate),C40<StartDate),"Date is before the accounting start date",IF(AND(D40<>"Adjustment",IFERROR(INDEX(coa_Pay,MATCH(K40&"",coa_Name,0)),"")<>"Yes"),"Paid From / Deposited To is not a payment account",""))))))))))) | Z40: =IF(AND(T40=0,X40=""),1,0) | AA40: =IF(Z40=1,IF(U40="In",L40,L40-W40),0) | AB40: =IF(Z40=1,IF(U40="In",L40-W40,L40),0) | AC40: =IF(AND(Z40=1,U40="Out"),W40,0) | AD40: =IF(AND(Z40=1,U40="In"),W40,0)
B41: TX-0035 | C41: 46058 | D41: Money In | E41: Product Sales | F41: GCash / online orders week 1 | I41: E-Wallet | K41: E-Wallet / Online Payments | L41: 22766.39 | M41: 2439.26 | O41: =IF(Z41=1,L41-W41,"") | P41: =IF(V41="","",IFERROR(INDEX(coa_Type,MATCH(V41,coa_Name,0)),"")) | Q41: =IF(Z41=1,IF(U41="In",K41&"",V41),"") | R41: =IF(Z41=1,IF(U41="In",V41,K41&""),"") | S41: =IF(X41<>"","⛔ "&X41&" — not posted",IF(Y41<>"","⚠ "&Y41,IF(Z41=1,"✓ OK",""))) | T41: =IF(AND(C41="",D41="",E41="",L41="",K41=""),1,0) | U41: =IFERROR(INDEX(tt_Dir,MATCH(D41,tt_Type,0)),"") | V41: =IF(D41="","",IFERROR(IF(INDEX(tt_Other,MATCH(D41,tt_Type,0))="",E41&"",INDEX(tt_Other,MATCH(D41,tt_Type,0))),"")) | W41: =IF(OR(TaxOn<>"Yes",NOT(ISNUMBER(M41))),0,IF(IFERROR(INDEX(tt_Tax,MATCH(D41,tt_Type,0)),"No")="Yes",M41,0)) | X41: =IF(T41=1,"",IF(C41="","Missing transaction date",IF(NOT(ISNUMBER(C41)),"Invalid date",IF(OR(C41<DATE(2000,1,1),C41>DATE(2099,12,31)),"Invalid date",IF(D41="","Select a type",IF(U41="","Unknown type: "&D41,IF(V41="","Select an account (Category)",IF(ISNA(MATCH(V41,coa_Name,0)),"Unknown account: "&V41,IF(K41="","Select Paid From / Deposited To",IF(ISNA(MATCH(K41,coa_Name,0)),"Unknown account: "&K41,IF(NOT(ISNUMBER(L41)),"Enter an amount",IF(L41=0,"Enter an amount",IF(ABS(W41)>ABS(L41),"Tax is larger than the amount",""))))))))))))) | Y41: =IF(OR(T41=1,X41<>""),"",IF(AND(B41<>"",COUNTIF(tx_ID,B41)>1),"Duplicate transaction ID",IF(AND(L41<0,D41<>"Adjustment"),"Negative amount — check this entry",IF(AND(D41="Customer Payment",G41=""),"Add the customer",IF(AND(D41="Customer Payment",OR(J41="",COUNTIF(ar_No,J41&"")=0)),"Invoice # in Reference not found on AR sheet",IF(AND(D41="Bill Payment",H41=""),"Add the vendor",IF(AND(D41="Bill Payment",OR(J41="",COUNTIFS(ap_No,J41&"",ap_Party,H41&"")=0)),"Bill # + vendor not found on AP sheet",IF(AND(ISNUMBER(M41),N(M41)<>0,W41=0),"Tax ignored (tax tracking off, or not allowed for this type)",IF(V41=K41&"","Same account on both sides",IF(AND(ISNUMBER(StartDate),C41<StartDate),"Date is before the accounting start date",IF(AND(D41<>"Adjustment",IFERROR(INDEX(coa_Pay,MATCH(K41&"",coa_Name,0)),"")<>"Yes"),"Paid From / Deposited To is not a payment account",""))))))))))) | Z41: =IF(AND(T41=0,X41=""),1,0) | AA41: =IF(Z41=1,IF(U41="In",L41,L41-W41),0) | AB41: =IF(Z41=1,IF(U41="In",L41-W41,L41),0) | AC41: =IF(AND(Z41=1,U41="Out"),W41,0) | AD41: =IF(AND(Z41=1,U41="In"),W41,0)
B42: TX-0036 | C42: 46058 | D42: Transfer | E42: Credit Card | F42: Credit card payment | I42: Bank Transfer | K42: Bank Account | L42: 5285.19 | O42: =IF(Z42=1,L42-W42,"") | P42: =IF(V42="","",IFERROR(INDEX(coa_Type,MATCH(V42,coa_Name,0)),"")) | Q42: =IF(Z42=1,IF(U42="In",K42&"",V42),"") | R42: =IF(Z42=1,IF(U42="In",V42,K42&""),"") | S42: =IF(X42<>"","⛔ "&X42&" — not posted",IF(Y42<>"","⚠ "&Y42,IF(Z42=1,"✓ OK",""))) | T42: =IF(AND(C42="",D42="",E42="",L42="",K42=""),1,0) | U42: =IFERROR(INDEX(tt_Dir,MATCH(D42,tt_Type,0)),"") | V42: =IF(D42="","",IFERROR(IF(INDEX(tt_Other,MATCH(D42,tt_Type,0))="",E42&"",INDEX(tt_Other,MATCH(D42,tt_Type,0))),"")) | W42: =IF(OR(TaxOn<>"Yes",NOT(ISNUMBER(M42))),0,IF(IFERROR(INDEX(tt_Tax,MATCH(D42,tt_Type,0)),"No")="Yes",M42,0)) | X42: =IF(T42=1,"",IF(C42="","Missing transaction date",IF(NOT(ISNUMBER(C42)),"Invalid date",IF(OR(C42<DATE(2000,1,1),C42>DATE(2099,12,31)),"Invalid date",IF(D42="","Select a type",IF(U42="","Unknown type: "&D42,IF(V42="","Select an account (Category)",IF(ISNA(MATCH(V42,coa_Name,0)),"Unknown account: "&V42,IF(K42="","Select Paid From / Deposited To",IF(ISNA(MATCH(K42,coa_Name,0)),"Unknown account: "&K42,IF(NOT(ISNUMBER(L42)),"Enter an amount",IF(L42=0,"Enter an amount",IF(ABS(W42)>ABS(L42),"Tax is larger than the amount",""))))))))))))) | Y42: =IF(OR(T42=1,X42<>""),"",IF(AND(B42<>"",COUNTIF(tx_ID,B42)>1),"Duplicate transaction ID",IF(AND(L42<0,D42<>"Adjustment"),"Negative amount — check this entry",IF(AND(D42="Customer Payment",G42=""),"Add the customer",IF(AND(D42="Customer Payment",OR(J42="",COUNTIF(ar_No,J42&"")=0)),"Invoice # in Reference not found on AR sheet",IF(AND(D42="Bill Payment",H42=""),"Add the vendor",IF(AND(D42="Bill Payment",OR(J42="",COUNTIFS(ap_No,J42&"",ap_Party,H42&"")=0)),"Bill # + vendor not found on AP sheet",IF(AND(ISNUMBER(M42),N(M42)<>0,W42=0),"Tax ignored (tax tracking off, or not allowed for this type)",IF(V42=K42&"","Same account on both sides",IF(AND(ISNUMBER(StartDate),C42<StartDate),"Date is before the accounting start date",IF(AND(D42<>"Adjustment",IFERROR(INDEX(coa_Pay,MATCH(K42&"",coa_Name,0)),"")<>"Yes"),"Paid From / Deposited To is not a payment account",""))))))))))) | Z42: =IF(AND(T42=0,X42=""),1,0) | AA42: =IF(Z42=1,IF(U42="In",L42,L42-W42),0) | AB42: =IF(Z42=1,IF(U42="In",L42-W42,L42),0) | AC42: =IF(AND(Z42=1,U42="Out"),W42,0) | AD42: =IF(AND(Z42=1,U42="In"),W42,0)
B43: TX-0037 | C43: 46059 | D43: Transfer | E43: Bank Account | F43: Cash deposit to bank | I43: Cash | K43: Cash on Hand | L43: 46400 | O43: =IF(Z43=1,L43-W43,"") | P43: =IF(V43="","",IFERROR(INDEX(coa_Type,MATCH(V43,coa_Name,0)),"")) | Q43: =IF(Z43=1,IF(U43="In",K43&"",V43),"") | R43: =IF(Z43=1,IF(U43="In",V43,K43&""),"") | S43: =IF(X43<>"","⛔ "&X43&" — not posted",IF(Y43<>"","⚠ "&Y43,IF(Z43=1,"✓ OK",""))) | T43: =IF(AND(C43="",D43="",E43="",L43="",K43=""),1,0) | U43: =IFERROR(INDEX(tt_Dir,MATCH(D43,tt_Type,0)),"") | V43: =IF(D43="","",IFERROR(IF(INDEX(tt_Other,MATCH(D43,tt_Type,0))="",E43&"",INDEX(tt_Other,MATCH(D43,tt_Type,0))),"")) | W43: =IF(OR(TaxOn<>"Yes",NOT(ISNUMBER(M43))),0,IF(IFERROR(INDEX(tt_Tax,MATCH(D43,tt_Type,0)),"No")="Yes",M43,0)) | X43: =IF(T43=1,"",IF(C43="","Missing transaction date",IF(NOT(ISNUMBER(C43)),"Invalid date",IF(OR(C43<DATE(2000,1,1),C43>DATE(2099,12,31)),"Invalid date",IF(D43="","Select a type",IF(U43="","Unknown type: "&D43,IF(V43="","Select an account (Category)",IF(ISNA(MATCH(V43,coa_Name,0)),"Unknown account: "&V43,IF(K43="","Select Paid From / Deposited To",IF(ISNA(MATCH(K43,coa_Name,0)),"Unknown account: "&K43,IF(NOT(ISNUMBER(L43)),"Enter an amount",IF(L43=0,"Enter an amount",IF(ABS(W43)>ABS(L43),"Tax is larger than the amount",""))))))))))))) | Y43: =IF(OR(T43=1,X43<>""),"",IF(AND(B43<>"",COUNTIF(tx_ID,B43)>1),"Duplicate transaction ID",IF(AND(L43<0,D43<>"Adjustment"),"Negative amount — check this entry",IF(AND(D43="Customer Payment",G43=""),"Add the customer",IF(AND(D43="Customer Payment",OR(J43="",COUNTIF(ar_No,J43&"")=0)),"Invoice # in Reference not found on AR sheet",IF(AND(D43="Bill Payment",H43=""),"Add the vendor",IF(AND(D43="Bill Payment",OR(J43="",COUNTIFS(ap_No,J43&"",ap_Party,H43&"")=0)),"Bill # + vendor not found on AP sheet",IF(AND(ISNUMBER(M43),N(M43)<>0,W43=0),"Tax ignored (tax tracking off, or not allowed for this type)",IF(V43=K43&"","Same account on both sides",IF(AND(ISNUMBER(StartDate),C43<StartDate),"Date is before the accounting start date",IF(AND(D43<>"Adjustment",IFERROR(INDEX(coa_Pay,MATCH(K43&"",coa_Name,0)),"")<>"Yes"),"Paid From / Deposited To is not a payment account",""))))))))))) | Z43: =IF(AND(T43=0,X43=""),1,0) | AA43: =IF(Z43=1,IF(U43="In",L43,L43-W43),0) | AB43: =IF(Z43=1,IF(U43="In",L43-W43,L43),0) | AC43: =IF(AND(Z43=1,U43="Out"),W43,0) | AD43: =IF(AND(Z43=1,U43="In"),W43,0)
B44: TX-0038 | C44: 46059 | D44: Money Out | E44: Other Direct Costs | F44: Boxes & paper bags (market) | I44: Cash | K44: Cash on Hand | L44: 2849.94 | M44: 305.35 | O44: =IF(Z44=1,L44-W44,"") | P44: =IF(V44="","",IFERROR(INDEX(coa_Type,MATCH(V44,coa_Name,0)),"")) | Q44: =IF(Z44=1,IF(U44="In",K44&"",V44),"") | R44: =IF(Z44=1,IF(U44="In",V44,K44&""),"") | S44: =IF(X44<>"","⛔ "&X44&" — not posted",IF(Y44<>"","⚠ "&Y44,IF(Z44=1,"✓ OK",""))) | T44: =IF(AND(C44="",D44="",E44="",L44="",K44=""),1,0) | U44: =IFERROR(INDEX(tt_Dir,MATCH(D44,tt_Type,0)),"") | V44: =IF(D44="","",IFERROR(IF(INDEX(tt_Other,MATCH(D44,tt_Type,0))="",E44&"",INDEX(tt_Other,MATCH(D44,tt_Type,0))),"")) | W44: =IF(OR(TaxOn<>"Yes",NOT(ISNUMBER(M44))),0,IF(IFERROR(INDEX(tt_Tax,MATCH(D44,tt_Type,0)),"No")="Yes",M44,0)) | X44: =IF(T44=1,"",IF(C44="","Missing transaction date",IF(NOT(ISNUMBER(C44)),"Invalid date",IF(OR(C44<DATE(2000,1,1),C44>DATE(2099,12,31)),"Invalid date",IF(D44="","Select a type",IF(U44="","Unknown type: "&D44,IF(V44="","Select an account (Category)",IF(ISNA(MATCH(V44,coa_Name,0)),"Unknown account: "&V44,IF(K44="","Select Paid From / Deposited To",IF(ISNA(MATCH(K44,coa_Name,0)),"Unknown account: "&K44,IF(NOT(ISNUMBER(L44)),"Enter an amount",IF(L44=0,"Enter an amount",IF(ABS(W44)>ABS(L44),"Tax is larger than the amount",""))))))))))))) | Y44: =IF(OR(T44=1,X44<>""),"",IF(AND(B44<>"",COUNTIF(tx_ID,B44)>1),"Duplicate transaction ID",IF(AND(L44<0,D44<>"Adjustment"),"Negative amount — check this entry",IF(AND(D44="Customer Payment",G44=""),"Add the customer",IF(AND(D44="Customer Payment",OR(J44="",COUNTIF(ar_No,J44&"")=0)),"Invoice # in Reference not found on AR sheet",IF(AND(D44="Bill Payment",H44=""),"Add the vendor",IF(AND(D44="Bill Payment",OR(J44="",COUNTIFS(ap_No,J44&"",ap_Party,H44&"")=0)),"Bill # + vendor not found on AP sheet",IF(AND(ISNUMBER(M44),N(M44)<>0,W44=0),"Tax ignored (tax tracking off, or not allowed for this type)",IF(V44=K44&"","Same account on both sides",IF(AND(ISNUMBER(StartDate),C44<StartDate),"Date is before the accounting start date",IF(AND(D44<>"Adjustment",IFERROR(INDEX(coa_Pay,MATCH(K44&"",coa_Name,0)),"")<>"Yes"),"Paid From / Deposited To is not a payment account",""))))))))))) | Z44: =IF(AND(T44=0,X44=""),1,0) | AA44: =IF(Z44=1,IF(U44="In",L44,L44-W44),0) | AB44: =IF(Z44=1,IF(U44="In",L44-W44,L44),0) | AC44: =IF(AND(Z44=1,U44="Out"),W44,0) | AD44: =IF(AND(Z44=1,U44="In"),W44,0)
B45: TX-0039 | C45: 46061 | D45: Money Out | E45: Advertising & Marketing | F45: Facebook / Instagram ads | I45: Credit Card | K45: Credit Card | L45: 5589.97 | M45: 598.92 | O45: =IF(Z45=1,L45-W45,"") | P45: =IF(V45="","",IFERROR(INDEX(coa_Type,MATCH(V45,coa_Name,0)),"")) | Q45: =IF(Z45=1,IF(U45="In",K45&"",V45),"") | R45: =IF(Z45=1,IF(U45="In",V45,K45&""),"") | S45: =IF(X45<>"","⛔ "&X45&" — not posted",IF(Y45<>"","⚠ "&Y45,IF(Z45=1,"✓ OK",""))) | T45: =IF(AND(C45="",D45="",E45="",L45="",K45=""),1,0) | U45: =IFERROR(INDEX(tt_Dir,MATCH(D45,tt_Type,0)),"") | V45: =IF(D45="","",IFERROR(IF(INDEX(tt_Other,MATCH(D45,tt_Type,0))="",E45&"",INDEX(tt_Other,MATCH(D45,tt_Type,0))),"")) | W45: =IF(OR(TaxOn<>"Yes",NOT(ISNUMBER(M45))),0,IF(IFERROR(INDEX(tt_Tax,MATCH(D45,tt_Type,0)),"No")="Yes",M45,0)) | X45: =IF(T45=1,"",IF(C45="","Missing transaction date",IF(NOT(ISNUMBER(C45)),"Invalid date",IF(OR(C45<DATE(2000,1,1),C45>DATE(2099,12,31)),"Invalid date",IF(D45="","Select a type",IF(U45="","Unknown type: "&D45,IF(V45="","Select an account (Category)",IF(ISNA(MATCH(V45,coa_Name,0)),"Unknown account: "&V45,IF(K45="","Select Paid From / Deposited To",IF(ISNA(MATCH(K45,coa_Name,0)),"Unknown account: "&K45,IF(NOT(ISNUMBER(L45)),"Enter an amount",IF(L45=0,"Enter an amount",IF(ABS(W45)>ABS(L45),"Tax is larger than the amount",""))))))))))))) | Y45: =IF(OR(T45=1,X45<>""),"",IF(AND(B45<>"",COUNTIF(tx_ID,B45)>1),"Duplicate transaction ID",IF(AND(L45<0,D45<>"Adjustment"),"Negative amount — check this entry",IF(AND(D45="Customer Payment",G45=""),"Add the customer",IF(AND(D45="Customer Payment",OR(J45="",COUNTIF(ar_No,J45&"")=0)),"Invoice # in Reference not found on AR sheet",IF(AND(D45="Bill Payment",H45=""),"Add the vendor",IF(AND(D45="Bill Payment",OR(J45="",COUNTIFS(ap_No,J45&"",ap_Party,H45&"")=0)),"Bill # + vendor not found on AP sheet",IF(AND(ISNUMBER(M45),N(M45)<>0,W45=0),"Tax ignored (tax tracking off, or not allowed for this type)",IF(V45=K45&"","Same account on both sides",IF(AND(ISNUMBER(StartDate),C45<StartDate),"Date is before the accounting start date",IF(AND(D45<>"Adjustment",IFERROR(INDEX(coa_Pay,MATCH(K45&"",coa_Name,0)),"")<>"Yes"),"Paid From / Deposited To is not a payment account",""))))))))))) | Z45: =IF(AND(T45=0,X45=""),1,0) | AA45: =IF(Z45=1,IF(U45="In",L45,L45-W45),0) | AB45: =IF(Z45=1,IF(U45="In",L45-W45,L45),0) | AC45: =IF(AND(Z45=1,U45="Out"),W45,0) | AD45: =IF(AND(Z45=1,U45="In"),W45,0)
B46: TX-0040 | C46: 46062 | D46: Money Out | E46: Software & Subscriptions | F46: POS app subscription | I46: Credit Card | K46: Credit Card | L46: 1450 | M46: 155.36 | O46: =IF(Z46=1,L46-W46,"") | P46: =IF(V46="","",IFERROR(INDEX(coa_Type,MATCH(V46,coa_Name,0)),"")) | Q46: =IF(Z46=1,IF(U46="In",K46&"",V46),"") | R46: =IF(Z46=1,IF(U46="In",V46,K46&""),"") | S46: =IF(X46<>"","⛔ "&X46&" — not posted",IF(Y46<>"","⚠ "&Y46,IF(Z46=1,"✓ OK",""))) | T46: =IF(AND(C46="",D46="",E46="",L46="",K46=""),1,0) | U46: =IFERROR(INDEX(tt_Dir,MATCH(D46,tt_Type,0)),"") | V46: =IF(D46="","",IFERROR(IF(INDEX(tt_Other,MATCH(D46,tt_Type,0))="",E46&"",INDEX(tt_Other,MATCH(D46,tt_Type,0))),"")) | W46: =IF(OR(TaxOn<>"Yes",NOT(ISNUMBER(M46))),0,IF(IFERROR(INDEX(tt_Tax,MATCH(D46,tt_Type,0)),"No")="Yes",M46,0)) | X46: =IF(T46=1,"",IF(C46="","Missing transaction date",IF(NOT(ISNUMBER(C46)),"Invalid date",IF(OR(C46<DATE(2000,1,1),C46>DATE(2099,12,31)),"Invalid date",IF(D46="","Select a type",IF(U46="","Unknown type: "&D46,IF(V46="","Select an account (Category)",IF(ISNA(MATCH(V46,coa_Name,0)),"Unknown account: "&V46,IF(K46="","Select Paid From / Deposited To",IF(ISNA(MATCH(K46,coa_Name,0)),"Unknown account: "&K46,IF(NOT(ISNUMBER(L46)),"Enter an amount",IF(L46=0,"Enter an amount",IF(ABS(W46)>ABS(L46),"Tax is larger than the amount",""))))))))))))) | Y46: =IF(OR(T46=1,X46<>""),"",IF(AND(B46<>"",COUNTIF(tx_ID,B46)>1),"Duplicate transaction ID",IF(AND(L46<0,D46<>"Adjustment"),"Negative amount — check this entry",IF(AND(D46="Customer Payment",G46=""),"Add the customer",IF(AND(D46="Customer Payment",OR(J46="",COUNTIF(ar_No,J46&"")=0)),"Invoice # in Reference not found on AR sheet",IF(AND(D46="Bill Payment",H46=""),"Add the vendor",IF(AND(D46="Bill Payment",OR(J46="",COUNTIFS(ap_No,J46&"",ap_Party,H46&"")=0)),"Bill # + vendor not found on AP sheet",IF(AND(ISNUMBER(M46),N(M46)<>0,W46=0),"Tax ignored (tax tracking off, or not allowed for this type)",IF(V46=K46&"","Same account on both sides",IF(AND(ISNUMBER(StartDate),C46<StartDate),"Date is before the accounting start date",IF(AND(D46<>"Adjustment",IFERROR(INDEX(coa_Pay,MATCH(K46&"",coa_Name,0)),"")<>"Yes"),"Paid From / Deposited To is not a payment account",""))))))))))) | Z46: =IF(AND(T46=0,X46=""),1,0) | AA46: =IF(Z46=1,IF(U46="In",L46,L46-W46),0) | AB46: =IF(Z46=1,IF(U46="In",L46-W46,L46),0) | AC46: =IF(AND(Z46=1,U46="Out"),W46,0) | AD46: =IF(AND(Z46=1,U46="In"),W46,0)
B47: TX-0041 | C47: 46063 | D47: Bill Payment | F47: Supplier payment | H47: Golden Grain Flour Mill | I47: Bank Transfer | J47: GO-012 | K47: Bank Account | L47: 40022.39 | O47: =IF(Z47=1,L47-W47,"") | P47: =IF(V47="","",IFERROR(INDEX(coa_Type,MATCH(V47,coa_Name,0)),"")) | Q47: =IF(Z47=1,IF(U47="In",K47&"",V47),"") | R47: =IF(Z47=1,IF(U47="In",V47,K47&""),"") | S47: =IF(X47<>"","⛔ "&X47&" — not posted",IF(Y47<>"","⚠ "&Y47,IF(Z47=1,"✓ OK",""))) | T47: =IF(AND(C47="",D47="",E47="",L47="",K47=""),1,0) | U47: =IFERROR(INDEX(tt_Dir,MATCH(D47,tt_Type,0)),"") | V47: =IF(D47="","",IFERROR(IF(INDEX(tt_Other,MATCH(D47,tt_Type,0))="",E47&"",INDEX(tt_Other,MATCH(D47,tt_Type,0))),"")) | W47: =IF(OR(TaxOn<>"Yes",NOT(ISNUMBER(M47))),0,IF(IFERROR(INDEX(tt_Tax,MATCH(D47,tt_Type,0)),"No")="Yes",M47,0)) | X47: =IF(T47=1,"",IF(C47="","Missing transaction date",IF(NOT(ISNUMBER(C47)),"Invalid date",IF(OR(C47<DATE(2000,1,1),C47>DATE(2099,12,31)),"Invalid date",IF(D47="","Select a type",IF(U47="","Unknown type: "&D47,IF(V47="","Select an account (Category)",IF(ISNA(MATCH(V47,coa_Name,0)),"Unknown account: "&V47,IF(K47="","Select Paid From / Deposited To",IF(ISNA(MATCH(K47,coa_Name,0)),"Unknown account: "&K47,IF(NOT(ISNUMBER(L47)),"Enter an amount",IF(L47=0,"Enter an amount",IF(ABS(W47)>ABS(L47),"Tax is larger than the amount",""))))))))))))) | Y47: =IF(OR(T47=1,X47<>""),"",IF(AND(B47<>"",COUNTIF(tx_ID,B47)>1),"Duplicate transaction ID",IF(AND(L47<0,D47<>"Adjustment"),"Negative amount — check this entry",IF(AND(D47="Customer Payment",G47=""),"Add the customer",IF(AND(D47="Customer Payment",OR(J47="",COUNTIF(ar_No,J47&"")=0)),"Invoice # in Reference not found on AR sheet",IF(AND(D47="Bill Payment",H47=""),"Add the vendor",IF(AND(D47="Bill Payment",OR(J47="",COUNTIFS(ap_No,J47&"",ap_Party,H47&"")=0)),"Bill # + vendor not found on AP sheet",IF(AND(ISNUMBER(M47),N(M47)<>0,W47=0),"Tax ignored (tax tracking off, or not allowed for this type)",IF(V47=K47&"","Same account on both sides",IF(AND(ISNUMBER(StartDate),C47<StartDate),"Date is before the accounting start date",IF(AND(D47<>"Adjustment",IFERROR(INDEX(coa_Pay,MATCH(K47&"",coa_Name,0)),"")<>"Yes"),"Paid From / Deposited To is not a payment account",""))))))))))) | Z47: =IF(AND(T47=0,X47=""),1,0) | AA47: =IF(Z47=1,IF(U47="In",L47,L47-W47),0) | AB47: =IF(Z47=1,IF(U47="In",L47-W47,L47),0) | AC47: =IF(AND(Z47=1,U47="Out"),W47,0) | AD47: =IF(AND(Z47=1,U47="In"),W47,0)
B48: TX-0042 | C48: 46063 | D48: Money Out | E48: Loans Payable | F48: Loan principal | I48: Bank Transfer | J48: LOAN | K48: Bank Account | L48: 8000 | O48: =IF(Z48=1,L48-W48,"") | P48: =IF(V48="","",IFERROR(INDEX(coa_Type,MATCH(V48,coa_Name,0)),"")) | Q48: =IF(Z48=1,IF(U48="In",K48&"",V48),"") | R48: =IF(Z48=1,IF(U48="In",V48,K48&""),"") | S48: =IF(X48<>"","⛔ "&X48&" — not posted",IF(Y48<>"","⚠ "&Y48,IF(Z48=1,"✓ OK",""))) | T48: =IF(AND(C48="",D48="",E48="",L48="",K48=""),1,0) | U48: =IFERROR(INDEX(tt_Dir,MATCH(D48,tt_Type,0)),"") | V48: =IF(D48="","",IFERROR(IF(INDEX(tt_Other,MATCH(D48,tt_Type,0))="",E48&"",INDEX(tt_Other,MATCH(D48,tt_Type,0))),"")) | W48: =IF(OR(TaxOn<>"Yes",NOT(ISNUMBER(M48))),0,IF(IFERROR(INDEX(tt_Tax,MATCH(D48,tt_Type,0)),"No")="Yes",M48,0)) | X48: =IF(T48=1,"",IF(C48="","Missing transaction date",IF(NOT(ISNUMBER(C48)),"Invalid date",IF(OR(C48<DATE(2000,1,1),C48>DATE(2099,12,31)),"Invalid date",IF(D48="","Select a type",IF(U48="","Unknown type: "&D48,IF(V48="","Select an account (Category)",IF(ISNA(MATCH(V48,coa_Name,0)),"Unknown account: "&V48,IF(K48="","Select Paid From / Deposited To",IF(ISNA(MATCH(K48,coa_Name,0)),"Unknown account: "&K48,IF(NOT(ISNUMBER(L48)),"Enter an amount",IF(L48=0,"Enter an amount",IF(ABS(W48)>ABS(L48),"Tax is larger than the amount",""))))))))))))) | Y48: =IF(OR(T48=1,X48<>""),"",IF(AND(B48<>"",COUNTIF(tx_ID,B48)>1),"Duplicate transaction ID",IF(AND(L48<0,D48<>"Adjustment"),"Negative amount — check this entry",IF(AND(D48="Customer Payment",G48=""),"Add the customer",IF(AND(D48="Customer Payment",OR(J48="",COUNTIF(ar_No,J48&"")=0)),"Invoice # in Reference not found on AR sheet",IF(AND(D48="Bill Payment",H48=""),"Add the vendor",IF(AND(D48="Bill Payment",OR(J48="",COUNTIFS(ap_No,J48&"",ap_Party,H48&"")=0)),"Bill # + vendor not found on AP sheet",IF(AND(ISNUMBER(M48),N(M48)<>0,W48=0),"Tax ignored (tax tracking off, or not allowed for this type)",IF(V48=K48&"","Same account on both sides",IF(AND(ISNUMBER(StartDate),C48<StartDate),"Date is before the accounting start date",IF(AND(D48<>"Adjustment",IFERROR(INDEX(coa_Pay,MATCH(K48&"",coa_Name,0)),"")<>"Yes"),"Paid From / Deposited To is not a payment account",""))))))))))) | Z48: =IF(AND(T48=0,X48=""),1,0) | AA48: =IF(Z48=1,IF(U48="In",L48,L48-W48),0) | AB48: =IF(Z48=1,IF(U48="In",L48-W48,L48),0) | AC48: =IF(AND(Z48=1,U48="Out"),W48,0) | AD48: =IF(AND(Z48=1,U48="In"),W48,0)
B49: TX-0043 | C49: 46063 | D49: Money Out | E49: Interest Expense | F49: Loan interest | I49: Bank Transfer | J49: LOAN | K49: Bank Account | L49: 1440 | O49: =IF(Z49=1,L49-W49,"") | P49: =IF(V49="","",IFERROR(INDEX(coa_Type,MATCH(V49,coa_Name,0)),"")) | Q49: =IF(Z49=1,IF(U49="In",K49&"",V49),"") | R49: =IF(Z49=1,IF(U49="In",V49,K49&""),"") | S49: =IF(X49<>"","⛔ "&X49&" — not posted",IF(Y49<>"","⚠ "&Y49,IF(Z49=1,"✓ OK",""))) | T49: =IF(AND(C49="",D49="",E49="",L49="",K49=""),1,0) | U49: =IFERROR(INDEX(tt_Dir,MATCH(D49,tt_Type,0)),"") | V49: =IF(D49="","",IFERROR(IF(INDEX(tt_Other,MATCH(D49,tt_Type,0))="",E49&"",INDEX(tt_Other,MATCH(D49,tt_Type,0))),"")) | W49: =IF(OR(TaxOn<>"Yes",NOT(ISNUMBER(M49))),0,IF(IFERROR(INDEX(tt_Tax,MATCH(D49,tt_Type,0)),"No")="Yes",M49,0)) | X49: =IF(T49=1,"",IF(C49="","Missing transaction date",IF(NOT(ISNUMBER(C49)),"Invalid date",IF(OR(C49<DATE(2000,1,1),C49>DATE(2099,12,31)),"Invalid date",IF(D49="","Select a type",IF(U49="","Unknown type: "&D49,IF(V49="","Select an account (Category)",IF(ISNA(MATCH(V49,coa_Name,0)),"Unknown account: "&V49,IF(K49="","Select Paid From / Deposited To",IF(ISNA(MATCH(K49,coa_Name,0)),"Unknown account: "&K49,IF(NOT(ISNUMBER(L49)),"Enter an amount",IF(L49=0,"Enter an amount",IF(ABS(W49)>ABS(L49),"Tax is larger than the amount",""))))))))))))) | Y49: =IF(OR(T49=1,X49<>""),"",IF(AND(B49<>"",COUNTIF(tx_ID,B49)>1),"Duplicate transaction ID",IF(AND(L49<0,D49<>"Adjustment"),"Negative amount — check this entry",IF(AND(D49="Customer Payment",G49=""),"Add the customer",IF(AND(D49="Customer Payment",OR(J49="",COUNTIF(ar_No,J49&"")=0)),"Invoice # in Reference not found on AR sheet",IF(AND(D49="Bill Payment",H49=""),"Add the vendor",IF(AND(D49="Bill Payment",OR(J49="",COUNTIFS(ap_No,J49&"",ap_Party,H49&"")=0)),"Bill # + vendor not found on AP sheet",IF(AND(ISNUMBER(M49),N(M49)<>0,W49=0),"Tax ignored (tax tracking off, or not allowed for this type)",IF(V49=K49&"","Same account on both sides",IF(AND(ISNUMBER(StartDate),C49<StartDate),"Date is before the accounting start date",IF(AND(D49<>"Adjustment",IFERROR(INDEX(coa_Pay,MATCH(K49&"",coa_Name,0)),"")<>"Yes"),"Paid From / Deposited To is not a payment account",""))))))))))) | Z49: =IF(AND(T49=0,X49=""),1,0) | AA49: =IF(Z49=1,IF(U49="In",L49,L49-W49),0) | AB49: =IF(Z49=1,IF(U49="In",L49-W49,L49),0) | AC49: =IF(AND(Z49=1,U49="Out"),W49,0) | AD49: =IF(AND(Z49=1,U49="In"),W49,0)
B50: TX-0044 | C50: 46064 | D50: Money In | E50: Product Sales | F50: Counter sales week 2 | I50: Cash | K50: Cash on Hand | L50: 45728.07 | M50: 4899.44 | O50: =IF(Z50=1,L50-W50,"") | P50: =IF(V50="","",IFERROR(INDEX(coa_Type,MATCH(V50,coa_Name,0)),"")) | Q50: =IF(Z50=1,IF(U50="In",K50&"",V50),"") | R50: =IF(Z50=1,IF(U50="In",V50,K50&""),"") | S50: =IF(X50<>"","⛔ "&X50&" — not posted",IF(Y50<>"","⚠ "&Y50,IF(Z50=1,"✓ OK",""))) | T50: =IF(AND(C50="",D50="",E50="",L50="",K50=""),1,0) | U50: =IFERROR(INDEX(tt_Dir,MATCH(D50,tt_Type,0)),"") | V50: =IF(D50="","",IFERROR(IF(INDEX(tt_Other,MATCH(D50,tt_Type,0))="",E50&"",INDEX(tt_Other,MATCH(D50,tt_Type,0))),"")) | W50: =IF(OR(TaxOn<>"Yes",NOT(ISNUMBER(M50))),0,IF(IFERROR(INDEX(tt_Tax,MATCH(D50,tt_Type,0)),"No")="Yes",M50,0)) | X50: =IF(T50=1,"",IF(C50="","Missing transaction date",IF(NOT(ISNUMBER(C50)),"Invalid date",IF(OR(C50<DATE(2000,1,1),C50>DATE(2099,12,31)),"Invalid date",IF(D50="","Select a type",IF(U50="","Unknown type: "&D50,IF(V50="","Select an account (Category)",IF(ISNA(MATCH(V50,coa_Name,0)),"Unknown account: "&V50,IF(K50="","Select Paid From / Deposited To",IF(ISNA(MATCH(K50,coa_Name,0)),"Unknown account: "&K50,IF(NOT(ISNUMBER(L50)),"Enter an amount",IF(L50=0,"Enter an amount",IF(ABS(W50)>ABS(L50),"Tax is larger than the amount",""))))))))))))) | Y50: =IF(OR(T50=1,X50<>""),"",IF(AND(B50<>"",COUNTIF(tx_ID,B50)>1),"Duplicate transaction ID",IF(AND(L50<0,D50<>"Adjustment"),"Negative amount — check this entry",IF(AND(D50="Customer Payment",G50=""),"Add the customer",IF(AND(D50="Customer Payment",OR(J50="",COUNTIF(ar_No,J50&"")=0)),"Invoice # in Reference not found on AR sheet",IF(AND(D50="Bill Payment",H50=""),"Add the vendor",IF(AND(D50="Bill Payment",OR(J50="",COUNTIFS(ap_No,J50&"",ap_Party,H50&"")=0)),"Bill # + vendor not found on AP sheet",IF(AND(ISNUMBER(M50),N(M50)<>0,W50=0),"Tax ignored (tax tracking off, or not allowed for this type)",IF(V50=K50&"","Same account on both sides",IF(AND(ISNUMBER(StartDate),C50<StartDate),"Date is before the accounting start date",IF(AND(D50<>"Adjustment",IFERROR(INDEX(coa_Pay,MATCH(K50&"",coa_Name,0)),"")<>"Yes"),"Paid From / Deposited To is not a payment account",""))))))))))) | Z50: =IF(AND(T50=0,X50=""),1,0) | AA50: =IF(Z50=1,IF(U50="In",L50,L50-W50),0) | AB50: =IF(Z50=1,IF(U50="In",L50-W50,L50),0) | AC50: =IF(AND(Z50=1,U50="Out"),W50,0) | AD50: =IF(AND(Z50=1,U50="In"),W50,0)
B51: TX-0045 | C51: 46065 | D51: Money In | E51: Product Sales | F51: GCash / online orders week 2 | I51: E-Wallet | K51: E-Wallet / Online Payments | L51: 14444.75 | M51: 1547.65 | O51: =IF(Z51=1,L51-W51,"") | P51: =IF(V51="","",IFERROR(INDEX(coa_Type,MATCH(V51,coa_Name,0)),"")) | Q51: =IF(Z51=1,IF(U51="In",K51&"",V51),"") | R51: =IF(Z51=1,IF(U51="In",V51,K51&""),"") | S51: =IF(X51<>"","⛔ "&X51&" — not posted",IF(Y51<>"","⚠ "&Y51,IF(Z51=1,"✓ OK",""))) | T51: =IF(AND(C51="",D51="",E51="",L51="",K51=""),1,0) | U51: =IFERROR(INDEX(tt_Dir,MATCH(D51,tt_Type,0)),"") | V51: =IF(D51="","",IFERROR(IF(INDEX(tt_Other,MATCH(D51,tt_Type,0))="",E51&"",INDEX(tt_Other,MATCH(D51,tt_Type,0))),"")) | W51: =IF(OR(TaxOn<>"Yes",NOT(ISNUMBER(M51))),0,IF(IFERROR(INDEX(tt_Tax,MATCH(D51,tt_Type,0)),"No")="Yes",M51,0)) | X51: =IF(T51=1,"",IF(C51="","Missing transaction date",IF(NOT(ISNUMBER(C51)),"Invalid date",IF(OR(C51<DATE(2000,1,1),C51>DATE(2099,12,31)),"Invalid date",IF(D51="","Select a type",IF(U51="","Unknown type: "&D51,IF(V51="","Select an account (Category)",IF(ISNA(MATCH(V51,coa_Name,0)),"Unknown account: "&V51,IF(K51="","Select Paid From / Deposited To",IF(ISNA(MATCH(K51,coa_Name,0)),"Unknown account: "&K51,IF(NOT(ISNUMBER(L51)),"Enter an amount",IF(L51=0,"Enter an amount",IF(ABS(W51)>ABS(L51),"Tax is larger than the amount",""))))))))))))) | Y51: =IF(OR(T51=1,X51<>""),"",IF(AND(B51<>"",COUNTIF(tx_ID,B51)>1),"Duplicate transaction ID",IF(AND(L51<0,D51<>"Adjustment"),"Negative amount — check this entry",IF(AND(D51="Customer Payment",G51=""),"Add the customer",IF(AND(D51="Customer Payment",OR(J51="",COUNTIF(ar_No,J51&"")=0)),"Invoice # in Reference not found on AR sheet",IF(AND(D51="Bill Payment",H51=""),"Add the vendor",IF(AND(D51="Bill Payment",OR(J51="",COUNTIFS(ap_No,J51&"",ap_Party,H51&"")=0)),"Bill # + vendor not found on AP sheet",IF(AND(ISNUMBER(M51),N(M51)<>0,W51=0),"Tax ignored (tax tracking off, or not allowed for this type)",IF(V51=K51&"","Same account on both sides",IF(AND(ISNUMBER(StartDate),C51<StartDate),"Date is before the accounting start date",IF(AND(D51<>"Adjustment",IFERROR(INDEX(coa_Pay,MATCH(K51&"",coa_Name,0)),"")<>"Yes"),"Paid From / Deposited To is not a payment account",""))))))))))) | Z51: =IF(AND(T51=0,X51=""),1,0) | AA51: =IF(Z51=1,IF(U51="In",L51,L51-W51),0) | AB51: =IF(Z51=1,IF(U51="In",L51-W51,L51),0) | AC51: =IF(AND(Z51=1,U51="Out"),W51,0) | AD51: =IF(AND(Z51=1,U51="In"),W51,0)
B52: TX-0046 | C52: 46065 | D52: Money Out | E52: Utilities | F52: Electricity & water | I52: Bank Transfer | K52: Bank Account | L52: 10133.34 | M52: 1085.72 | O52: =IF(Z52=1,L52-W52,"") | P52: =IF(V52="","",IFERROR(INDEX(coa_Type,MATCH(V52,coa_Name,0)),"")) | Q52: =IF(Z52=1,IF(U52="In",K52&"",V52),"") | R52: =IF(Z52=1,IF(U52="In",V52,K52&""),"") | S52: =IF(X52<>"","⛔ "&X52&" — not posted",IF(Y52<>"","⚠ "&Y52,IF(Z52=1,"✓ OK",""))) | T52: =IF(AND(C52="",D52="",E52="",L52="",K52=""),1,0) | U52: =IFERROR(INDEX(tt_Dir,MATCH(D52,tt_Type,0)),"") | V52: =IF(D52="","",IFERROR(IF(INDEX(tt_Other,MATCH(D52,tt_Type,0))="",E52&"",INDEX(tt_Other,MATCH(D52,tt_Type,0))),"")) | W52: =IF(OR(TaxOn<>"Yes",NOT(ISNUMBER(M52))),0,IF(IFERROR(INDEX(tt_Tax,MATCH(D52,tt_Type,0)),"No")="Yes",M52,0)) | X52: =IF(T52=1,"",IF(C52="","Missing transaction date",IF(NOT(ISNUMBER(C52)),"Invalid date",IF(OR(C52<DATE(2000,1,1),C52>DATE(2099,12,31)),"Invalid date",IF(D52="","Select a type",IF(U52="","Unknown type: "&D52,IF(V52="","Select an account (Category)",IF(ISNA(MATCH(V52,coa_Name,0)),"Unknown account: "&V52,IF(K52="","Select Paid From / Deposited To",IF(ISNA(MATCH(K52,coa_Name,0)),"Unknown account: "&K52,IF(NOT(ISNUMBER(L52)),"Enter an amount",IF(L52=0,"Enter an amount",IF(ABS(W52)>ABS(L52),"Tax is larger than the amount",""))))))))))))) | Y52: =IF(OR(T52=1,X52<>""),"",IF(AND(B52<>"",COUNTIF(tx_ID,B52)>1),"Duplicate transaction ID",IF(AND(L52<0,D52<>"Adjustment"),"Negative amount — check this entry",IF(AND(D52="Customer Payment",G52=""),"Add the customer",IF(AND(D52="Customer Payment",OR(J52="",COUNTIF(ar_No,J52&"")=0)),"Invoice # in Reference not found on AR sheet",IF(AND(D52="Bill Payment",H52=""),"Add the vendor",IF(AND(D52="Bill Payment",OR(J52="",COUNTIFS(ap_No,J52&"",ap_Party,H52&"")=0)),"Bill # + vendor not found on AP sheet",IF(AND(ISNUMBER(M52),N(M52)<>0,W52=0),"Tax ignored (tax tracking off, or not allowed for this type)",IF(V52=K52&"","Same account on both sides",IF(AND(ISNUMBER(StartDate),C52<StartDate),"Date is before the accounting start date",IF(AND(D52<>"Adjustment",IFERROR(INDEX(coa_Pay,MATCH(K52&"",coa_Name,0)),"")<>"Yes"),"Paid From / Deposited To is not a payment account",""))))))))))) | Z52: =IF(AND(T52=0,X52=""),1,0) | AA52: =IF(Z52=1,IF(U52="In",L52,L52-W52),0) | AB52: =IF(Z52=1,IF(U52="In",L52-W52,L52),0) | AC52: =IF(AND(Z52=1,U52="Out"),W52,0) | AD52: =IF(AND(Z52=1,U52="In"),W52,0)
B53: TX-0047 | C53: 46066 | D53: Transfer | E53: Bank Account | F53: Cash deposit to bank | I53: Cash | K53: Cash on Hand | L53: 38900 | O53: =IF(Z53=1,L53-W53,"") | P53: =IF(V53="","",IFERROR(INDEX(coa_Type,MATCH(V53,coa_Name,0)),"")) | Q53: =IF(Z53=1,IF(U53="In",K53&"",V53),"") | R53: =IF(Z53=1,IF(U53="In",V53,K53&""),"") | S53: =IF(X53<>"","⛔ "&X53&" — not posted",IF(Y53<>"","⚠ "&Y53,IF(Z53=1,"✓ OK",""))) | T53: =IF(AND(C53="",D53="",E53="",L53="",K53=""),1,0) | U53: =IFERROR(INDEX(tt_Dir,MATCH(D53,tt_Type,0)),"") | V53: =IF(D53="","",IFERROR(IF(INDEX(tt_Other,MATCH(D53,tt_Type,0))="",E53&"",INDEX(tt_Other,MATCH(D53,tt_Type,0))),"")) | W53: =IF(OR(TaxOn<>"Yes",NOT(ISNUMBER(M53))),0,IF(IFERROR(INDEX(tt_Tax,MATCH(D53,tt_Type,0)),"No")="Yes",M53,0)) | X53: =IF(T53=1,"",IF(C53="","Missing transaction date",IF(NOT(ISNUMBER(C53)),"Invalid date",IF(OR(C53<DATE(2000,1,1),C53>DATE(2099,12,31)),"Invalid date",IF(D53="","Select a type",IF(U53="","Unknown type: "&D53,IF(V53="","Select an account (Category)",IF(ISNA(MATCH(V53,coa_Name,0)),"Unknown account: "&V53,IF(K53="","Select Paid From / Deposited To",IF(ISNA(MATCH(K53,coa_Name,0)),"Unknown account: "&K53,IF(NOT(ISNUMBER(L53)),"Enter an amount",IF(L53=0,"Enter an amount",IF(ABS(W53)>ABS(L53),"Tax is larger than the amount",""))))))))))))) | Y53: =IF(OR(T53=1,X53<>""),"",IF(AND(B53<>"",COUNTIF(tx_ID,B53)>1),"Duplicate transaction ID",IF(AND(L53<0,D53<>"Adjustment"),"Negative amount — check this entry",IF(AND(D53="Customer Payment",G53=""),"Add the customer",IF(AND(D53="Customer Payment",OR(J53="",COUNTIF(ar_No,J53&"")=0)),"Invoice # in Reference not found on AR sheet",IF(AND(D53="Bill Payment",H53=""),"Add the vendor",IF(AND(D53="Bill Payment",OR(J53="",COUNTIFS(ap_No,J53&"",ap_Party,H53&"")=0)),"Bill # + vendor not found on AP sheet",IF(AND(ISNUMBER(M53),N(M53)<>0,W53=0),"Tax ignored (tax tracking off, or not allowed for this type)",IF(V53=K53&"","Same account on both sides",IF(AND(ISNUMBER(StartDate),C53<StartDate),"Date is before the accounting start date",IF(AND(D53<>"Adjustment",IFERROR(INDEX(coa_Pay,MATCH(K53&"",coa_Name,0)),"")<>"Yes"),"Paid From / Deposited To is not a payment account",""))))))))))) | Z53: =IF(AND(T53=0,X53=""),1,0) | AA53: =IF(Z53=1,IF(U53="In",L53,L53-W53),0) | AB53: =IF(Z53=1,IF(U53="In",L53-W53,L53),0) | AC53: =IF(AND(Z53=1,U53="Out"),W53,0) | AD53: =IF(AND(Z53=1,U53="In"),W53,0)
B54: TX-0048 | C54: 46067 | D54: Customer Payment | F54: Invoice payment | G54: Northwind Offices | I54: Bank Transfer | J54: INV-1001 | K54: Bank Account | L54: 23665.51 | O54: =IF(Z54=1,L54-W54,"") | P54: =IF(V54="","",IFERROR(INDEX(coa_Type,MATCH(V54,coa_Name,0)),"")) | Q54: =IF(Z54=1,IF(U54="In",K54&"",V54),"") | R54: =IF(Z54=1,IF(U54="In",V54,K54&""),"") | S54: =IF(X54<>"","⛔ "&X54&" — not posted",IF(Y54<>"","⚠ "&Y54,IF(Z54=1,"✓ OK",""))) | T54: =IF(AND(C54="",D54="",E54="",L54="",K54=""),1,0) | U54: =IFERROR(INDEX(tt_Dir,MATCH(D54,tt_Type,0)),"") | V54: =IF(D54="","",IFERROR(IF(INDEX(tt_Other,MATCH(D54,tt_Type,0))="",E54&"",INDEX(tt_Other,MATCH(D54,tt_Type,0))),"")) | W54: =IF(OR(TaxOn<>"Yes",NOT(ISNUMBER(M54))),0,IF(IFERROR(INDEX(tt_Tax,MATCH(D54,tt_Type,0)),"No")="Yes",M54,0)) | X54: =IF(T54=1,"",IF(C54="","Missing transaction date",IF(NOT(ISNUMBER(C54)),"Invalid date",IF(OR(C54<DATE(2000,1,1),C54>DATE(2099,12,31)),"Invalid date",IF(D54="","Select a type",IF(U54="","Unknown type: "&D54,IF(V54="","Select an account (Category)",IF(ISNA(MATCH(V54,coa_Name,0)),"Unknown account: "&V54,IF(K54="","Select Paid From / Deposited To",IF(ISNA(MATCH(K54,coa_Name,0)),"Unknown account: "&K54,IF(NOT(ISNUMBER(L54)),"Enter an amount",IF(L54=0,"Enter an amount",IF(ABS(W54)>ABS(L54),"Tax is larger than the amount",""))))))))))))) | Y54: =IF(OR(T54=1,X54<>""),"",IF(AND(B54<>"",COUNTIF(tx_ID,B54)>1),"Duplicate transaction ID",IF(AND(L54<0,D54<>"Adjustment"),"Negative amount — check this entry",IF(AND(D54="Customer Payment",G54=""),"Add the customer",IF(AND(D54="Customer Payment",OR(J54="",COUNTIF(ar_No,J54&"")=0)),"Invoice # in Reference not found on AR sheet",IF(AND(D54="Bill Payment",H54=""),"Add the vendor",IF(AND(D54="Bill Payment",OR(J54="",COUNTIFS(ap_No,J54&"",ap_Party,H54&"")=0)),"Bill # + vendor not found on AP sheet",IF(AND(ISNUMBER(M54),N(M54)<>0,W54=0),"Tax ignored (tax tracking off, or not allowed for this type)",IF(V54=K54&"","Same account on both sides",IF(AND(ISNUMBER(StartDate),C54<StartDate),"Date is before the accounting start date",IF(AND(D54<>"Adjustment",IFERROR(INDEX(coa_Pay,MATCH(K54&"",coa_Name,0)),"")<>"Yes"),"Paid From / Deposited To is not a payment account",""))))))))))) | Z54: =IF(AND(T54=0,X54=""),1,0) | AA54: =IF(Z54=1,IF(U54="In",L54,L54-W54),0) | AB54: =IF(Z54=1,IF(U54="In",L54-W54,L54),0) | AC54: =IF(AND(Z54=1,U54="Out"),W54,0) | AD54: =IF(AND(Z54=1,U54="In"),W54,0)
B55: TX-0049 | C55: 46067 | D55: Money Out | E55: Taxes & Licenses | F55: Business permit renewal | I55: Bank Transfer | K55: Bank Account | L55: 7800 | O55: =IF(Z55=1,L55-W55,"") | P55: =IF(V55="","",IFERROR(INDEX(coa_Type,MATCH(V55,coa_Name,0)),"")) | Q55: =IF(Z55=1,IF(U55="In",K55&"",V55),"") | R55: =IF(Z55=1,IF(U55="In",V55,K55&""),"") | S55: =IF(X55<>"","⛔ "&X55&" — not posted",IF(Y55<>"","⚠ "&Y55,IF(Z55=1,"✓ OK",""))) | T55: =IF(AND(C55="",D55="",E55="",L55="",K55=""),1,0) | U55: =IFERROR(INDEX(tt_Dir,MATCH(D55,tt_Type,0)),"") | V55: =IF(D55="","",IFERROR(IF(INDEX(tt_Other,MATCH(D55,tt_Type,0))="",E55&"",INDEX(tt_Other,MATCH(D55,tt_Type,0))),"")) | W55: =IF(OR(TaxOn<>"Yes",NOT(ISNUMBER(M55))),0,IF(IFERROR(INDEX(tt_Tax,MATCH(D55,tt_Type,0)),"No")="Yes",M55,0)) | X55: =IF(T55=1,"",IF(C55="","Missing transaction date",IF(NOT(ISNUMBER(C55)),"Invalid date",IF(OR(C55<DATE(2000,1,1),C55>DATE(2099,12,31)),"Invalid date",IF(D55="","Select a type",IF(U55="","Unknown type: "&D55,IF(V55="","Select an account (Category)",IF(ISNA(MATCH(V55,coa_Name,0)),"Unknown account: "&V55,IF(K55="","Select Paid From / Deposited To",IF(ISNA(MATCH(K55,coa_Name,0)),"Unknown account: "&K55,IF(NOT(ISNUMBER(L55)),"Enter an amount",IF(L55=0,"Enter an amount",IF(ABS(W55)>ABS(L55),"Tax is larger than the amount",""))))))))))))) | Y55: =IF(OR(T55=1,X55<>""),"",IF(AND(B55<>"",COUNTIF(tx_ID,B55)>1),"Duplicate transaction ID",IF(AND(L55<0,D55<>"Adjustment"),"Negative amount — check this entry",IF(AND(D55="Customer Payment",G55=""),"Add the customer",IF(AND(D55="Customer Payment",OR(J55="",COUNTIF(ar_No,J55&"")=0)),"Invoice # in Reference not found on AR sheet",IF(AND(D55="Bill Payment",H55=""),"Add the vendor",IF(AND(D55="Bill Payment",OR(J55="",COUNTIFS(ap_No,J55&"",ap_Party,H55&"")=0)),"Bill # + vendor not found on AP sheet",IF(AND(ISNUMBER(M55),N(M55)<>0,W55=0),"Tax ignored (tax tracking off, or not allowed for this type)",IF(V55=K55&"","Same account on both sides",IF(AND(ISNUMBER(StartDate),C55<StartDate),"Date is before the accounting start date",IF(AND(D55<>"Adjustment",IFERROR(INDEX(coa_Pay,MATCH(K55&"",coa_Name,0)),"")<>"Yes"),"Paid From / Deposited To is not a payment account",""))))))))))) | Z55: =IF(AND(T55=0,X55=""),1,0) | AA55: =IF(Z55=1,IF(U55="In",L55,L55-W55),0) | AB55: =IF(Z55=1,IF(U55="In",L55-W55,L55),0) | AC55: =IF(AND(Z55=1,U55="Out"),W55,0) | AD55: =IF(AND(Z55=1,U55="In"),W55,0)
B56: TX-0050 | C56: 46068 | D56: Money Out | E56: Internet & Phone | F56: Fiber internet | I56: Bank Transfer | K56: Bank Account | L56: 2499 | M56: 267.75 | O56: =IF(Z56=1,L56-W56,"") | P56: =IF(V56="","",IFERROR(INDEX(coa_Type,MATCH(V56,coa_Name,0)),"")) | Q56: =IF(Z56=1,IF(U56="In",K56&"",V56),"") | R56: =IF(Z56=1,IF(U56="In",V56,K56&""),"") | S56: =IF(X56<>"","⛔ "&X56&" — not posted",IF(Y56<>"","⚠ "&Y56,IF(Z56=1,"✓ OK",""))) | T56: =IF(AND(C56="",D56="",E56="",L56="",K56=""),1,0) | U56: =IFERROR(INDEX(tt_Dir,MATCH(D56,tt_Type,0)),"") | V56: =IF(D56="","",IFERROR(IF(INDEX(tt_Other,MATCH(D56,tt_Type,0))="",E56&"",INDEX(tt_Other,MATCH(D56,tt_Type,0))),"")) | W56: =IF(OR(TaxOn<>"Yes",NOT(ISNUMBER(M56))),0,IF(IFERROR(INDEX(tt_Tax,MATCH(D56,tt_Type,0)),"No")="Yes",M56,0)) | X56: =IF(T56=1,"",IF(C56="","Missing transaction date",IF(NOT(ISNUMBER(C56)),"Invalid date",IF(OR(C56<DATE(2000,1,1),C56>DATE(2099,12,31)),"Invalid date",IF(D56="","Select a type",IF(U56="","Unknown type: "&D56,IF(V56="","Select an account (Category)",IF(ISNA(MATCH(V56,coa_Name,0)),"Unknown account: "&V56,IF(K56="","Select Paid From / Deposited To",IF(ISNA(MATCH(K56,coa_Name,0)),"Unknown account: "&K56,IF(NOT(ISNUMBER(L56)),"Enter an amount",IF(L56=0,"Enter an amount",IF(ABS(W56)>ABS(L56),"Tax is larger than the amount",""))))))))))))) | Y56: =IF(OR(T56=1,X56<>""),"",IF(AND(B56<>"",COUNTIF(tx_ID,B56)>1),"Duplicate transaction ID",IF(AND(L56<0,D56<>"Adjustment"),"Negative amount — check this entry",IF(AND(D56="Customer Payment",G56=""),"Add the customer",IF(AND(D56="Customer Payment",OR(J56="",COUNTIF(ar_No,J56&"")=0)),"Invoice # in Reference not found on AR sheet",IF(AND(D56="Bill Payment",H56=""),"Add the vendor",IF(AND(D56="Bill Payment",OR(J56="",COUNTIFS(ap_No,J56&"",ap_Party,H56&"")=0)),"Bill # + vendor not found on AP sheet",IF(AND(ISNUMBER(M56),N(M56)<>0,W56=0),"Tax ignored (tax tracking off, or not allowed for this type)",IF(V56=K56&"","Same account on both sides",IF(AND(ISNUMBER(StartDate),C56<StartDate),"Date is before the accounting start date",IF(AND(D56<>"Adjustment",IFERROR(INDEX(coa_Pay,MATCH(K56&"",coa_Name,0)),"")<>"Yes"),"Paid From / Deposited To is not a payment account",""))))))))))) | Z56: =IF(AND(T56=0,X56=""),1,0) | AA56: =IF(Z56=1,IF(U56="In",L56,L56-W56),0) | AB56: =IF(Z56=1,IF(U56="In",L56-W56,L56),0) | AC56: =IF(AND(Z56=1,U56="Out"),W56,0) | AD56: =IF(AND(Z56=1,U56="In"),W56,0)
B57: TX-0051 | C57: 46068 | D57: Money Out | E57: Direct Labor | F57: Bakers' salaries (1st-15th) | I57: Bank Transfer | K57: Bank Account | L57: 38000 | O57: =IF(Z57=1,L57-W57,"") | P57: =IF(V57="","",IFERROR(INDEX(coa_Type,MATCH(V57,coa_Name,0)),"")) | Q57: =IF(Z57=1,IF(U57="In",K57&"",V57),"") | R57: =IF(Z57=1,IF(U57="In",V57,K57&""),"") | S57: =IF(X57<>"","⛔ "&X57&" — not posted",IF(Y57<>"","⚠ "&Y57,IF(Z57=1,"✓ OK",""))) | T57: =IF(AND(C57="",D57="",E57="",L57="",K57=""),1,0) | U57: =IFERROR(INDEX(tt_Dir,MATCH(D57,tt_Type,0)),"") | V57: =IF(D57="","",IFERROR(IF(INDEX(tt_Other,MATCH(D57,tt_Type,0))="",E57&"",INDEX(tt_Other,MATCH(D57,tt_Type,0))),"")) | W57: =IF(OR(TaxOn<>"Yes",NOT(ISNUMBER(M57))),0,IF(IFERROR(INDEX(tt_Tax,MATCH(D57,tt_Type,0)),"No")="Yes",M57,0)) | X57: =IF(T57=1,"",IF(C57="","Missing transaction date",IF(NOT(ISNUMBER(C57)),"Invalid date",IF(OR(C57<DATE(2000,1,1),C57>DATE(2099,12,31)),"Invalid date",IF(D57="","Select a type",IF(U57="","Unknown type: "&D57,IF(V57="","Select an account (Category)",IF(ISNA(MATCH(V57,coa_Name,0)),"Unknown account: "&V57,IF(K57="","Select Paid From / Deposited To",IF(ISNA(MATCH(K57,coa_Name,0)),"Unknown account: "&K57,IF(NOT(ISNUMBER(L57)),"Enter an amount",IF(L57=0,"Enter an amount",IF(ABS(W57)>ABS(L57),"Tax is larger than the amount",""))))))))))))) | Y57: =IF(OR(T57=1,X57<>""),"",IF(AND(B57<>"",COUNTIF(tx_ID,B57)>1),"Duplicate transaction ID",IF(AND(L57<0,D57<>"Adjustment"),"Negative amount — check this entry",IF(AND(D57="Customer Payment",G57=""),"Add the customer",IF(AND(D57="Customer Payment",OR(J57="",COUNTIF(ar_No,J57&"")=0)),"Invoice # in Reference not found on AR sheet",IF(AND(D57="Bill Payment",H57=""),"Add the vendor",IF(AND(D57="Bill Payment",OR(J57="",COUNTIFS(ap_No,J57&"",ap_Party,H57&"")=0)),"Bill # + vendor not found on AP sheet",IF(AND(ISNUMBER(M57),N(M57)<>0,W57=0),"Tax ignored (tax tracking off, or not allowed for this type)",IF(V57=K57&"","Same account on both sides",IF(AND(ISNUMBER(StartDate),C57<StartDate),"Date is before the accounting start date",IF(AND(D57<>"Adjustment",IFERROR(INDEX(coa_Pay,MATCH(K57&"",coa_Name,0)),"")<>"Yes"),"Paid From / Deposited To is not a payment account",""))))))))))) | Z57: =IF(AND(T57=0,X57=""),1,0) | AA57: =IF(Z57=1,IF(U57="In",L57,L57-W57),0) | AB57: =IF(Z57=1,IF(U57="In",L57-W57,L57),0) | AC57: =IF(AND(Z57=1,U57="Out"),W57,0) | AD57: =IF(AND(Z57=1,U57="In"),W57,0)
B58: TX-0052 | C58: 46068 | D58: Money Out | E58: Salaries & Wages | F58: Cashier salary (1st-15th) | I58: Bank Transfer | K58: Bank Account | L58: 9000 | O58: =IF(Z58=1,L58-W58,"") | P58: =IF(V58="","",IFERROR(INDEX(coa_Type,MATCH(V58,coa_Name,0)),"")) | Q58: =IF(Z58=1,IF(U58="In",K58&"",V58),"") | R58: =IF(Z58=1,IF(U58="In",V58,K58&""),"") | S58: =IF(X58<>"","⛔ "&X58&" — not posted",IF(Y58<>"","⚠ "&Y58,IF(Z58=1,"✓ OK",""))) | T58: =IF(AND(C58="",D58="",E58="",L58="",K58=""),1,0) | U58: =IFERROR(INDEX(tt_Dir,MATCH(D58,tt_Type,0)),"") | V58: =IF(D58="","",IFERROR(IF(INDEX(tt_Other,MATCH(D58,tt_Type,0))="",E58&"",INDEX(tt_Other,MATCH(D58,tt_Type,0))),"")) | W58: =IF(OR(TaxOn<>"Yes",NOT(ISNUMBER(M58))),0,IF(IFERROR(INDEX(tt_Tax,MATCH(D58,tt_Type,0)),"No")="Yes",M58,0)) | X58: =IF(T58=1,"",IF(C58="","Missing transaction date",IF(NOT(ISNUMBER(C58)),"Invalid date",IF(OR(C58<DATE(2000,1,1),C58>DATE(2099,12,31)),"Invalid date",IF(D58="","Select a type",IF(U58="","Unknown type: "&D58,IF(V58="","Select an account (Category)",IF(ISNA(MATCH(V58,coa_Name,0)),"Unknown account: "&V58,IF(K58="","Select Paid From / Deposited To",IF(ISNA(MATCH(K58,coa_Name,0)),"Unknown account: "&K58,IF(NOT(ISNUMBER(L58)),"Enter an amount",IF(L58=0,"Enter an amount",IF(ABS(W58)>ABS(L58),"Tax is larger than the amount",""))))))))))))) | Y58: =IF(OR(T58=1,X58<>""),"",IF(AND(B58<>"",COUNTIF(tx_ID,B58)>1),"Duplicate transaction ID",IF(AND(L58<0,D58<>"Adjustment"),"Negative amount — check this entry",IF(AND(D58="Customer Payment",G58=""),"Add the customer",IF(AND(D58="Customer Payment",OR(J58="",COUNTIF(ar_No,J58&"")=0)),"Invoice # in Reference not found on AR sheet",IF(AND(D58="Bill Payment",H58=""),"Add the vendor",IF(AND(D58="Bill Payment",OR(J58="",COUNTIFS(ap_No,J58&"",ap_Party,H58&"")=0)),"Bill # + vendor not found on AP sheet",IF(AND(ISNUMBER(M58),N(M58)<>0,W58=0),"Tax ignored (tax tracking off, or not allowed for this type)",IF(V58=K58&"","Same account on both sides",IF(AND(ISNUMBER(StartDate),C58<StartDate),"Date is before the accounting start date",IF(AND(D58<>"Adjustment",IFERROR(INDEX(coa_Pay,MATCH(K58&"",coa_Name,0)),"")<>"Yes"),"Paid From / Deposited To is not a payment account",""))))))))))) | Z58: =IF(AND(T58=0,X58=""),1,0) | AA58: =IF(Z58=1,IF(U58="In",L58,L58-W58),0) | AB58: =IF(Z58=1,IF(U58="In",L58-W58,L58),0) | AC58: =IF(AND(Z58=1,U58="Out"),W58,0) | AD58: =IF(AND(Z58=1,U58="In"),W58,0)
B59: TX-0053 | C59: 46069 | D59: Bill Payment | F59: Supplier payment | H59: Golden Grain Flour Mill | I59: Bank Transfer | J59: GO-011 | K59: Bank Account | L59: 44768.62 | O59: =IF(Z59=1,L59-W59,"") | P59: =IF(V59="","",IFERROR(INDEX(coa_Type,MATCH(V59,coa_Name,0)),"")) | Q59: =IF(Z59=1,IF(U59="In",K59&"",V59),"") | R59: =IF(Z59=1,IF(U59="In",V59,K59&""),"") | S59: =IF(X59<>"","⛔ "&X59&" — not posted",IF(Y59<>"","⚠ "&Y59,IF(Z59=1,"✓ OK",""))) | T59: =IF(AND(C59="",D59="",E59="",L59="",K59=""),1,0) | U59: =IFERROR(INDEX(tt_Dir,MATCH(D59,tt_Type,0)),"") | V59: =IF(D59="","",IFERROR(IF(INDEX(tt_Other,MATCH(D59,tt_Type,0))="",E59&"",INDEX(tt_Other,MATCH(D59,tt_Type,0))),"")) | W59: =IF(OR(TaxOn<>"Yes",NOT(ISNUMBER(M59))),0,IF(IFERROR(INDEX(tt_Tax,MATCH(D59,tt_Type,0)),"No")="Yes",M59,0)) | X59: =IF(T59=1,"",IF(C59="","Missing transaction date",IF(NOT(ISNUMBER(C59)),"Invalid date",IF(OR(C59<DATE(2000,1,1),C59>DATE(2099,12,31)),"Invalid date",IF(D59="","Select a type",IF(U59="","Unknown type: "&D59,IF(V59="","Select an account (Category)",IF(ISNA(MATCH(V59,coa_Name,0)),"Unknown account: "&V59,IF(K59="","Select Paid From / Deposited To",IF(ISNA(MATCH(K59,coa_Name,0)),"Unknown account: "&K59,IF(NOT(ISNUMBER(L59)),"Enter an amount",IF(L59=0,"Enter an amount",IF(ABS(W59)>ABS(L59),"Tax is larger than the amount",""))))))))))))) | Y59: =IF(OR(T59=1,X59<>""),"",IF(AND(B59<>"",COUNTIF(tx_ID,B59)>1),"Duplicate transaction ID",IF(AND(L59<0,D59<>"Adjustment"),"Negative amount — check this entry",IF(AND(D59="Customer Payment",G59=""),"Add the customer",IF(AND(D59="Customer Payment",OR(J59="",COUNTIF(ar_No,J59&"")=0)),"Invoice # in Reference not found on AR sheet",IF(AND(D59="Bill Payment",H59=""),"Add the vendor",IF(AND(D59="Bill Payment",OR(J59="",COUNTIFS(ap_No,J59&"",ap_Party,H59&"")=0)),"Bill # + vendor not found on AP sheet",IF(AND(ISNUMBER(M59),N(M59)<>0,W59=0),"Tax ignored (tax tracking off, or not allowed for this type)",IF(V59=K59&"","Same account on both sides",IF(AND(ISNUMBER(StartDate),C59<StartDate),"Date is before the accounting start date",IF(AND(D59<>"Adjustment",IFERROR(INDEX(coa_Pay,MATCH(K59&"",coa_Name,0)),"")<>"Yes"),"Paid From / Deposited To is not a payment account",""))))))))))) | Z59: =IF(AND(T59=0,X59=""),1,0) | AA59: =IF(Z59=1,IF(U59="In",L59,L59-W59),0) | AB59: =IF(Z59=1,IF(U59="In",L59-W59,L59),0) | AC59: =IF(AND(Z59=1,U59="Out"),W59,0) | AD59: =IF(AND(Z59=1,U59="In"),W59,0)
B60: TX-0054 | C60: 46070 | D60: Bill Payment | F60: Supplier payment | H60: PackRight Supplies | I60: Bank Transfer | J60: PA-011 | K60: Bank Account | L60: 9618.83 | O60: =IF(Z60=1,L60-W60,"") | P60: =IF(V60="","",IFERROR(INDEX(coa_Type,MATCH(V60,coa_Name,0)),"")) | Q60: =IF(Z60=1,IF(U60="In",K60&"",V60),"") | R60: =IF(Z60=1,IF(U60="In",V60,K60&""),"") | S60: =IF(X60<>"","⛔ "&X60&" — not posted",IF(Y60<>"","⚠ "&Y60,IF(Z60=1,"✓ OK",""))) | T60: =IF(AND(C60="",D60="",E60="",L60="",K60=""),1,0) | U60: =IFERROR(INDEX(tt_Dir,MATCH(D60,tt_Type,0)),"") | V60: =IF(D60="","",IFERROR(IF(INDEX(tt_Other,MATCH(D60,tt_Type,0))="",E60&"",INDEX(tt_Other,MATCH(D60,tt_Type,0))),"")) | W60: =IF(OR(TaxOn<>"Yes",NOT(ISNUMBER(M60))),0,IF(IFERROR(INDEX(tt_Tax,MATCH(D60,tt_Type,0)),"No")="Yes",M60,0)) | X60: =IF(T60=1,"",IF(C60="","Missing transaction date",IF(NOT(ISNUMBER(C60)),"Invalid date",IF(OR(C60<DATE(2000,1,1),C60>DATE(2099,12,31)),"Invalid date",IF(D60="","Select a type",IF(U60="","Unknown type: "&D60,IF(V60="","Select an account (Category)",IF(ISNA(MATCH(V60,coa_Name,0)),"Unknown account: "&V60,IF(K60="","Select Paid From / Deposited To",IF(ISNA(MATCH(K60,coa_Name,0)),"Unknown account: "&K60,IF(NOT(ISNUMBER(L60)),"Enter an amount",IF(L60=0,"Enter an amount",IF(ABS(W60)>ABS(L60),"Tax is larger than the amount",""))))))))))))) | Y60: =IF(OR(T60=1,X60<>""),"",IF(AND(B60<>"",COUNTIF(tx_ID,B60)>1),"Duplicate transaction ID",IF(AND(L60<0,D60<>"Adjustment"),"Negative amount — check this entry",IF(AND(D60="Customer Payment",G60=""),"Add the customer",IF(AND(D60="Customer Payment",OR(J60="",COUNTIF(ar_No,J60&"")=0)),"Invoice # in Reference not found on AR sheet",IF(AND(D60="Bill Payment",H60=""),"Add the vendor",IF(AND(D60="Bill Payment",OR(J60="",COUNTIFS(ap_No,J60&"",ap_Party,H60&"")=0)),"Bill # + vendor not found on AP sheet",IF(AND(ISNUMBER(M60),N(M60)<>0,W60=0),"Tax ignored (tax tracking off, or not allowed for this type)",IF(V60=K60&"","Same account on both sides",IF(AND(ISNUMBER(StartDate),C60<StartDate),"Date is before the accounting start date",IF(AND(D60<>"Adjustment",IFERROR(INDEX(coa_Pay,MATCH(K60&"",coa_Name,0)),"")<>"Yes"),"Paid From / Deposited To is not a payment account",""))))))))))) | Z60: =IF(AND(T60=0,X60=""),1,0) | AA60: =IF(Z60=1,IF(U60="In",L60,L60-W60),0) | AB60: =IF(Z60=1,IF(U60="In",L60-W60,L60),0) | AC60: =IF(AND(Z60=1,U60="Out"),W60,0) | AD60: =IF(AND(Z60=1,U60="In"),W60,0)
B61: TX-0055 | C61: 46071 | D61: Money In | E61: Product Sales | F61: Counter sales week 3 | I61: Cash | K61: Cash on Hand | L61: 49252.74 | M61: 5277.08 | O61: =IF(Z61=1,L61-W61,"") | P61: =IF(V61="","",IFERROR(INDEX(coa_Type,MATCH(V61,coa_Name,0)),"")) | Q61: =IF(Z61=1,IF(U61="In",K61&"",V61),"") | R61: =IF(Z61=1,IF(U61="In",V61,K61&""),"") | S61: =IF(X61<>"","⛔ "&X61&" — not posted",IF(Y61<>"","⚠ "&Y61,IF(Z61=1,"✓ OK",""))) | T61: =IF(AND(C61="",D61="",E61="",L61="",K61=""),1,0) | U61: =IFERROR(INDEX(tt_Dir,MATCH(D61,tt_Type,0)),"") | V61: =IF(D61="","",IFERROR(IF(INDEX(tt_Other,MATCH(D61,tt_Type,0))="",E61&"",INDEX(tt_Other,MATCH(D61,tt_Type,0))),"")) | W61: =IF(OR(TaxOn<>"Yes",NOT(ISNUMBER(M61))),0,IF(IFERROR(INDEX(tt_Tax,MATCH(D61,tt_Type,0)),"No")="Yes",M61,0)) | X61: =IF(T61=1,"",IF(C61="","Missing transaction date",IF(NOT(ISNUMBER(C61)),"Invalid date",IF(OR(C61<DATE(2000,1,1),C61>DATE(2099,12,31)),"Invalid date",IF(D61="","Select a type",IF(U61="","Unknown type: "&D61,IF(V61="","Select an account (Category)",IF(ISNA(MATCH(V61,coa_Name,0)),"Unknown account: "&V61,IF(K61="","Select Paid From / Deposited To",IF(ISNA(MATCH(K61,coa_Name,0)),"Unknown account: "&K61,IF(NOT(ISNUMBER(L61)),"Enter an amount",IF(L61=0,"Enter an amount",IF(ABS(W61)>ABS(L61),"Tax is larger than the amount",""))))))))))))) | Y61: =IF(OR(T61=1,X61<>""),"",IF(AND(B61<>"",COUNTIF(tx_ID,B61)>1),"Duplicate transaction ID",IF(AND(L61<0,D61<>"Adjustment"),"Negative amount — check this entry",IF(AND(D61="Customer Payment",G61=""),"Add the customer",IF(AND(D61="Customer Payment",OR(J61="",COUNTIF(ar_No,J61&"")=0)),"Invoice # in Reference not found on AR sheet",IF(AND(D61="Bill Payment",H61=""),"Add the vendor",IF(AND(D61="Bill Payment",OR(J61="",COUNTIFS(ap_No,J61&"",ap_Party,H61&"")=0)),"Bill # + vendor not found on AP sheet",IF(AND(ISNUMBER(M61),N(M61)<>0,W61=0),"Tax ignored (tax tracking off, or not allowed for this type)",IF(V61=K61&"","Same account on both sides",IF(AND(ISNUMBER(StartDate),C61<StartDate),"Date is before the accounting start date",IF(AND(D61<>"Adjustment",IFERROR(INDEX(coa_Pay,MATCH(K61&"",coa_Name,0)),"")<>"Yes"),"Paid From / Deposited To is not a payment account",""))))))))))) | Z61: =IF(AND(T61=0,X61=""),1,0) | AA61: =IF(Z61=1,IF(U61="In",L61,L61-W61),0) | AB61: =IF(Z61=1,IF(U61="In",L61-W61,L61),0) | AC61: =IF(AND(Z61=1,U61="Out"),W61,0) | AD61: =IF(AND(Z61=1,U61="In"),W61,0)
B62: TX-0056 | C62: 46072 | D62: Money In | E62: Product Sales | F62: GCash / online orders week 3 | I62: E-Wallet | K62: E-Wallet / Online Payments | L62: 14327.04 | M62: 1535.04 | O62: =IF(Z62=1,L62-W62,"") | P62: =IF(V62="","",IFERROR(INDEX(coa_Type,MATCH(V62,coa_Name,0)),"")) | Q62: =IF(Z62=1,IF(U62="In",K62&"",V62),"") | R62: =IF(Z62=1,IF(U62="In",V62,K62&""),"") | S62: =IF(X62<>"","⛔ "&X62&" — not posted",IF(Y62<>"","⚠ "&Y62,IF(Z62=1,"✓ OK",""))) | T62: =IF(AND(C62="",D62="",E62="",L62="",K62=""),1,0) | U62: =IFERROR(INDEX(tt_Dir,MATCH(D62,tt_Type,0)),"") | V62: =IF(D62="","",IFERROR(IF(INDEX(tt_Other,MATCH(D62,tt_Type,0))="",E62&"",INDEX(tt_Other,MATCH(D62,tt_Type,0))),"")) | W62: =IF(OR(TaxOn<>"Yes",NOT(ISNUMBER(M62))),0,IF(IFERROR(INDEX(tt_Tax,MATCH(D62,tt_Type,0)),"No")="Yes",M62,0)) | X62: =IF(T62=1,"",IF(C62="","Missing transaction date",IF(NOT(ISNUMBER(C62)),"Invalid date",IF(OR(C62<DATE(2000,1,1),C62>DATE(2099,12,31)),"Invalid date",IF(D62="","Select a type",IF(U62="","Unknown type: "&D62,IF(V62="","Select an account (Category)",IF(ISNA(MATCH(V62,coa_Name,0)),"Unknown account: "&V62,IF(K62="","Select Paid From / Deposited To",IF(ISNA(MATCH(K62,coa_Name,0)),"Unknown account: "&K62,IF(NOT(ISNUMBER(L62)),"Enter an amount",IF(L62=0,"Enter an amount",IF(ABS(W62)>ABS(L62),"Tax is larger than the amount",""))))))))))))) | Y62: =IF(OR(T62=1,X62<>""),"",IF(AND(B62<>"",COUNTIF(tx_ID,B62)>1),"Duplicate transaction ID",IF(AND(L62<0,D62<>"Adjustment"),"Negative amount — check this entry",IF(AND(D62="Customer Payment",G62=""),"Add the customer",IF(AND(D62="Customer Payment",OR(J62="",COUNTIF(ar_No,J62&"")=0)),"Invoice # in Reference not found on AR sheet",IF(AND(D62="Bill Payment",H62=""),"Add the vendor",IF(AND(D62="Bill Payment",OR(J62="",COUNTIFS(ap_No,J62&"",ap_Party,H62&"")=0)),"Bill # + vendor not found on AP sheet",IF(AND(ISNUMBER(M62),N(M62)<>0,W62=0),"Tax ignored (tax tracking off, or not allowed for this type)",IF(V62=K62&"","Same account on both sides",IF(AND(ISNUMBER(StartDate),C62<StartDate),"Date is before the accounting start date",IF(AND(D62<>"Adjustment",IFERROR(INDEX(coa_Pay,MATCH(K62&"",coa_Name,0)),"")<>"Yes"),"Paid From / Deposited To is not a payment account",""))))))))))) | Z62: =IF(AND(T62=0,X62=""),1,0) | AA62: =IF(Z62=1,IF(U62="In",L62,L62-W62),0) | AB62: =IF(Z62=1,IF(U62="In",L62-W62,L62),0) | AC62: =IF(AND(Z62=1,U62="Out"),W62,0) | AD62: =IF(AND(Z62=1,U62="In"),W62,0)
B63: TX-0057 | C63: 46073 | D63: Transfer | E63: Bank Account | F63: Cash deposit to bank | I63: Cash | K63: Cash on Hand | L63: 41900 | O63: =IF(Z63=1,L63-W63,"") | P63: =IF(V63="","",IFERROR(INDEX(coa_Type,MATCH(V63,coa_Name,0)),"")) | Q63: =IF(Z63=1,IF(U63="In",K63&"",V63),"") | R63: =IF(Z63=1,IF(U63="In",V63,K63&""),"") | S63: =IF(X63<>"","⛔ "&X63&" — not posted",IF(Y63<>"","⚠ "&Y63,IF(Z63=1,"✓ OK",""))) | T63: =IF(AND(C63="",D63="",E63="",L63="",K63=""),1,0) | U63: =IFERROR(INDEX(tt_Dir,MATCH(D63,tt_Type,0)),"") | V63: =IF(D63="","",IFERROR(IF(INDEX(tt_Other,MATCH(D63,tt_Type,0))="",E63&"",INDEX(tt_Other,MATCH(D63,tt_Type,0))),"")) | W63: =IF(OR(TaxOn<>"Yes",NOT(ISNUMBER(M63))),0,IF(IFERROR(INDEX(tt_Tax,MATCH(D63,tt_Type,0)),"No")="Yes",M63,0)) | X63: =IF(T63=1,"",IF(C63="","Missing transaction date",IF(NOT(ISNUMBER(C63)),"Invalid date",IF(OR(C63<DATE(2000,1,1),C63>DATE(2099,12,31)),"Invalid date",IF(D63="","Select a type",IF(U63="","Unknown type: "&D63,IF(V63="","Select an account (Category)",IF(ISNA(MATCH(V63,coa_Name,0)),"Unknown account: "&V63,IF(K63="","Select Paid From / Deposited To",IF(ISNA(MATCH(K63,coa_Name,0)),"Unknown account: "&K63,IF(NOT(ISNUMBER(L63)),"Enter an amount",IF(L63=0,"Enter an amount",IF(ABS(W63)>ABS(L63),"Tax is larger than the amount",""))))))))))))) | Y63: =IF(OR(T63=1,X63<>""),"",IF(AND(B63<>"",COUNTIF(tx_ID,B63)>1),"Duplicate transaction ID",IF(AND(L63<0,D63<>"Adjustment"),"Negative amount — check this entry",IF(AND(D63="Customer Payment",G63=""),"Add the customer",IF(AND(D63="Customer Payment",OR(J63="",COUNTIF(ar_No,J63&"")=0)),"Invoice # in Reference not found on AR sheet",IF(AND(D63="Bill Payment",H63=""),"Add the vendor",IF(AND(D63="Bill Payment",OR(J63="",COUNTIFS(ap_No,J63&"",ap_Party,H63&"")=0)),"Bill # + vendor not found on AP sheet",IF(AND(ISNUMBER(M63),N(M63)<>0,W63=0),"Tax ignored (tax tracking off, or not allowed for this type)",IF(V63=K63&"","Same account on both sides",IF(AND(ISNUMBER(StartDate),C63<StartDate),"Date is before the accounting start date",IF(AND(D63<>"Adjustment",IFERROR(INDEX(coa_Pay,MATCH(K63&"",coa_Name,0)),"")<>"Yes"),"Paid From / Deposited To is not a payment account",""))))))))))) | Z63: =IF(AND(T63=0,X63=""),1,0) | AA63: =IF(Z63=1,IF(U63="In",L63,L63-W63),0) | AB63: =IF(Z63=1,IF(U63="In",L63-W63,L63),0) | AC63: =IF(AND(Z63=1,U63="Out"),W63,0) | AD63: =IF(AND(Z63=1,U63="In"),W63,0)
B64: TX-0058 | C64: 46073 | D64: Money Out | E64: Transportation & Delivery | F64: Delivery fuel | I64: Cash | K64: Cash on Hand | L64: 4752.29 | M64: 509.17 | O64: =IF(Z64=1,L64-W64,"") | P64: =IF(V64="","",IFERROR(INDEX(coa_Type,MATCH(V64,coa_Name,0)),"")) | Q64: =IF(Z64=1,IF(U64="In",K64&"",V64),"") | R64: =IF(Z64=1,IF(U64="In",V64,K64&""),"") | S64: =IF(X64<>"","⛔ "&X64&" — not posted",IF(Y64<>"","⚠ "&Y64,IF(Z64=1,"✓ OK",""))) | T64: =IF(AND(C64="",D64="",E64="",L64="",K64=""),1,0) | U64: =IFERROR(INDEX(tt_Dir,MATCH(D64,tt_Type,0)),"") | V64: =IF(D64="","",IFERROR(IF(INDEX(tt_Other,MATCH(D64,tt_Type,0))="",E64&"",INDEX(tt_Other,MATCH(D64,tt_Type,0))),"")) | W64: =IF(OR(TaxOn<>"Yes",NOT(ISNUMBER(M64))),0,IF(IFERROR(INDEX(tt_Tax,MATCH(D64,tt_Type,0)),"No")="Yes",M64,0)) | X64: =IF(T64=1,"",IF(C64="","Missing transaction date",IF(NOT(ISNUMBER(C64)),"Invalid date",IF(OR(C64<DATE(2000,1,1),C64>DATE(2099,12,31)),"Invalid date",IF(D64="","Select a type",IF(U64="","Unknown type: "&D64,IF(V64="","Select an account (Category)",IF(ISNA(MATCH(V64,coa_Name,0)),"Unknown account: "&V64,IF(K64="","Select Paid From / Deposited To",IF(ISNA(MATCH(K64,coa_Name,0)),"Unknown account: "&K64,IF(NOT(ISNUMBER(L64)),"Enter an amount",IF(L64=0,"Enter an amount",IF(ABS(W64)>ABS(L64),"Tax is larger than the amount",""))))))))))))) | Y64: =IF(OR(T64=1,X64<>""),"",IF(AND(B64<>"",COUNTIF(tx_ID,B64)>1),"Duplicate transaction ID",IF(AND(L64<0,D64<>"Adjustment"),"Negative amount — check this entry",IF(AND(D64="Customer Payment",G64=""),"Add the customer",IF(AND(D64="Customer Payment",OR(J64="",COUNTIF(ar_No,J64&"")=0)),"Invoice # in Reference not found on AR sheet",IF(AND(D64="Bill Payment",H64=""),"Add the vendor",IF(AND(D64="Bill Payment",OR(J64="",COUNTIFS(ap_No,J64&"",ap_Party,H64&"")=0)),"Bill # + vendor not found on AP sheet",IF(AND(ISNUMBER(M64),N(M64)<>0,W64=0),"Tax ignored (tax tracking off, or not allowed for this type)",IF(V64=K64&"","Same account on both sides",IF(AND(ISNUMBER(StartDate),C64<StartDate),"Date is before the accounting start date",IF(AND(D64<>"Adjustment",IFERROR(INDEX(coa_Pay,MATCH(K64&"",coa_Name,0)),"")<>"Yes"),"Paid From / Deposited To is not a payment account",""))))))))))) | Z64: =IF(AND(T64=0,X64=""),1,0) | AA64: =IF(Z64=1,IF(U64="In",L64,L64-W64),0) | AB64: =IF(Z64=1,IF(U64="In",L64-W64,L64),0) | AC64: =IF(AND(Z64=1,U64="Out"),W64,0) | AD64: =IF(AND(Z64=1,U64="In"),W64,0)
B65: TX-0059 | C65: 46075 | D65: Customer Payment | F65: Invoice payment | G65: Brightpath Academy | I65: Bank Transfer | J65: INV-1005 | K65: Bank Account | L65: 21310.46 | O65: =IF(Z65=1,L65-W65,"") | P65: =IF(V65="","",IFERROR(INDEX(coa_Type,MATCH(V65,coa_Name,0)),"")) | Q65: =IF(Z65=1,IF(U65="In",K65&"",V65),"") | R65: =IF(Z65=1,IF(U65="In",V65,K65&""),"") | S65: =IF(X65<>"","⛔ "&X65&" — not posted",IF(Y65<>"","⚠ "&Y65,IF(Z65=1,"✓ OK",""))) | T65: =IF(AND(C65="",D65="",E65="",L65="",K65=""),1,0) | U65: =IFERROR(INDEX(tt_Dir,MATCH(D65,tt_Type,0)),"") | V65: =IF(D65="","",IFERROR(IF(INDEX(tt_Other,MATCH(D65,tt_Type,0))="",E65&"",INDEX(tt_Other,MATCH(D65,tt_Type,0))),"")) | W65: =IF(OR(TaxOn<>"Yes",NOT(ISNUMBER(M65))),0,IF(IFERROR(INDEX(tt_Tax,MATCH(D65,tt_Type,0)),"No")="Yes",M65,0)) | X65: =IF(T65=1,"",IF(C65="","Missing transaction date",IF(NOT(ISNUMBER(C65)),"Invalid date",IF(OR(C65<DATE(2000,1,1),C65>DATE(2099,12,31)),"Invalid date",IF(D65="","Select a type",IF(U65="","Unknown type: "&D65,IF(V65="","Select an account (Category)",IF(ISNA(MATCH(V65,coa_Name,0)),"Unknown account: "&V65,IF(K65="","Select Paid From / Deposited To",IF(ISNA(MATCH(K65,coa_Name,0)),"Unknown account: "&K65,IF(NOT(ISNUMBER(L65)),"Enter an amount",IF(L65=0,"Enter an amount",IF(ABS(W65)>ABS(L65),"Tax is larger than the amount",""))))))))))))) | Y65: =IF(OR(T65=1,X65<>""),"",IF(AND(B65<>"",COUNTIF(tx_ID,B65)>1),"Duplicate transaction ID",IF(AND(L65<0,D65<>"Adjustment"),"Negative amount — check this entry",IF(AND(D65="Customer Payment",G65=""),"Add the customer",IF(AND(D65="Customer Payment",OR(J65="",COUNTIF(ar_No,J65&"")=0)),"Invoice # in Reference not found on AR sheet",IF(AND(D65="Bill Payment",H65=""),"Add the vendor",IF(AND(D65="Bill Payment",OR(J65="",COUNTIFS(ap_No,J65&"",ap_Party,H65&"")=0)),"Bill # + vendor not found on AP sheet",IF(AND(ISNUMBER(M65),N(M65)<>0,W65=0),"Tax ignored (tax tracking off, or not allowed for this type)",IF(V65=K65&"","Same account on both sides",IF(AND(ISNUMBER(StartDate),C65<StartDate),"Date is before the accounting start date",IF(AND(D65<>"Adjustment",IFERROR(INDEX(coa_Pay,MATCH(K65&"",coa_Name,0)),"")<>"Yes"),"Paid From / Deposited To is not a payment account",""))))))))))) | Z65: =IF(AND(T65=0,X65=""),1,0) | AA65: =IF(Z65=1,IF(U65="In",L65,L65-W65),0) | AB65: =IF(Z65=1,IF(U65="In",L65-W65,L65),0) | AC65: =IF(AND(Z65=1,U65="Out"),W65,0) | AD65: =IF(AND(Z65=1,U65="In"),W65,0)
B66: TX-0060 | C66: 46078 | D66: Customer Payment | F66: Balance payment | G66: Brightpath Academy | I66: Bank Transfer | J66: INV-1002 | K66: Bank Account | L66: 20273.84 | O66: =IF(Z66=1,L66-W66,"") | P66: =IF(V66="","",IFERROR(INDEX(coa_Type,MATCH(V66,coa_Name,0)),"")) | Q66: =IF(Z66=1,IF(U66="In",K66&"",V66),"") | R66: =IF(Z66=1,IF(U66="In",V66,K66&""),"") | S66: =IF(X66<>"","⛔ "&X66&" — not posted",IF(Y66<>"","⚠ "&Y66,IF(Z66=1,"✓ OK",""))) | T66: =IF(AND(C66="",D66="",E66="",L66="",K66=""),1,0) | U66: =IFERROR(INDEX(tt_Dir,MATCH(D66,tt_Type,0)),"") | V66: =IF(D66="","",IFERROR(IF(INDEX(tt_Other,MATCH(D66,tt_Type,0))="",E66&"",INDEX(tt_Other,MATCH(D66,tt_Type,0))),"")) | W66: =IF(OR(TaxOn<>"Yes",NOT(ISNUMBER(M66))),0,IF(IFERROR(INDEX(tt_Tax,MATCH(D66,tt_Type,0)),"No")="Yes",M66,0)) | X66: =IF(T66=1,"",IF(C66="","Missing transaction date",IF(NOT(ISNUMBER(C66)),"Invalid date",IF(OR(C66<DATE(2000,1,1),C66>DATE(2099,12,31)),"Invalid date",IF(D66="","Select a type",IF(U66="","Unknown type: "&D66,IF(V66="","Select an account (Category)",IF(ISNA(MATCH(V66,coa_Name,0)),"Unknown account: "&V66,IF(K66="","Select Paid From / Deposited To",IF(ISNA(MATCH(K66,coa_Name,0)),"Unknown account: "&K66,IF(NOT(ISNUMBER(L66)),"Enter an amount",IF(L66=0,"Enter an amount",IF(ABS(W66)>ABS(L66),"Tax is larger than the amount",""))))))))))))) | Y66: =IF(OR(T66=1,X66<>""),"",IF(AND(B66<>"",COUNTIF(tx_ID,B66)>1),"Duplicate transaction ID",IF(AND(L66<0,D66<>"Adjustment"),"Negative amount — check this entry",IF(AND(D66="Customer Payment",G66=""),"Add the customer",IF(AND(D66="Customer Payment",OR(J66="",COUNTIF(ar_No,J66&"")=0)),"Invoice # in Reference not found on AR sheet",IF(AND(D66="Bill Payment",H66=""),"Add the vendor",IF(AND(D66="Bill Payment",OR(J66="",COUNTIFS(ap_No,J66&"",ap_Party,H66&"")=0)),"Bill # + vendor not found on AP sheet",IF(AND(ISNUMBER(M66),N(M66)<>0,W66=0),"Tax ignored (tax tracking off, or not allowed for this type)",IF(V66=K66&"","Same account on both sides",IF(AND(ISNUMBER(StartDate),C66<StartDate),"Date is before the accounting start date",IF(AND(D66<>"Adjustment",IFERROR(INDEX(coa_Pay,MATCH(K66&"",coa_Name,0)),"")<>"Yes"),"Paid From / Deposited To is not a payment account",""))))))))))) | Z66: =IF(AND(T66=0,X66=""),1,0) | AA66: =IF(Z66=1,IF(U66="In",L66,L66-W66),0) | AB66: =IF(Z66=1,IF(U66="In",L66-W66,L66),0) | AC66: =IF(AND(Z66=1,U66="Out"),W66,0) | AD66: =IF(AND(Z66=1,U66="In"),W66,0)
B67: TX-0061 | C67: 46078 | D67: Money In | E67: Product Sales | F67: Counter sales week 4 | I67: Cash | K67: Cash on Hand | L67: 55884.42 | M67: 5987.62 | O67: =IF(Z67=1,L67-W67,"") | P67: =IF(V67="","",IFERROR(INDEX(coa_Type,MATCH(V67,coa_Name,0)),"")) | Q67: =IF(Z67=1,IF(U67="In",K67&"",V67),"") | R67: =IF(Z67=1,IF(U67="In",V67,K67&""),"") | S67: =IF(X67<>"","⛔ "&X67&" — not posted",IF(Y67<>"","⚠ "&Y67,IF(Z67=1,"✓ OK",""))) | T67: =IF(AND(C67="",D67="",E67="",L67="",K67=""),1,0) | U67: =IFERROR(INDEX(tt_Dir,MATCH(D67,tt_Type,0)),"") | V67: =IF(D67="","",IFERROR(IF(INDEX(tt_Other,MATCH(D67,tt_Type,0))="",E67&"",INDEX(tt_Other,MATCH(D67,tt_Type,0))),"")) | W67: =IF(OR(TaxOn<>"Yes",NOT(ISNUMBER(M67))),0,IF(IFERROR(INDEX(tt_Tax,MATCH(D67,tt_Type,0)),"No")="Yes",M67,0)) | X67: =IF(T67=1,"",IF(C67="","Missing transaction date",IF(NOT(ISNUMBER(C67)),"Invalid date",IF(OR(C67<DATE(2000,1,1),C67>DATE(2099,12,31)),"Invalid date",IF(D67="","Select a type",IF(U67="","Unknown type: "&D67,IF(V67="","Select an account (Category)",IF(ISNA(MATCH(V67,coa_Name,0)),"Unknown account: "&V67,IF(K67="","Select Paid From / Deposited To",IF(ISNA(MATCH(K67,coa_Name,0)),"Unknown account: "&K67,IF(NOT(ISNUMBER(L67)),"Enter an amount",IF(L67=0,"Enter an amount",IF(ABS(W67)>ABS(L67),"Tax is larger than the amount",""))))))))))))) | Y67: =IF(OR(T67=1,X67<>""),"",IF(AND(B67<>"",COUNTIF(tx_ID,B67)>1),"Duplicate transaction ID",IF(AND(L67<0,D67<>"Adjustment"),"Negative amount — check this entry",IF(AND(D67="Customer Payment",G67=""),"Add the customer",IF(AND(D67="Customer Payment",OR(J67="",COUNTIF(ar_No,J67&"")=0)),"Invoice # in Reference not found on AR sheet",IF(AND(D67="Bill Payment",H67=""),"Add the vendor",IF(AND(D67="Bill Payment",OR(J67="",COUNTIFS(ap_No,J67&"",ap_Party,H67&"")=0)),"Bill # + vendor not found on AP sheet",IF(AND(ISNUMBER(M67),N(M67)<>0,W67=0),"Tax ignored (tax tracking off, or not allowed for this type)",IF(V67=K67&"","Same account on both sides",IF(AND(ISNUMBER(StartDate),C67<StartDate),"Date is before the accounting start date",IF(AND(D67<>"Adjustment",IFERROR(INDEX(coa_Pay,MATCH(K67&"",coa_Name,0)),"")<>"Yes"),"Paid From / Deposited To is not a payment account",""))))))))))) | Z67: =IF(AND(T67=0,X67=""),1,0) | AA67: =IF(Z67=1,IF(U67="In",L67,L67-W67),0) | AB67: =IF(Z67=1,IF(U67="In",L67-W67,L67),0) | AC67: =IF(AND(Z67=1,U67="Out"),W67,0) | AD67: =IF(AND(Z67=1,U67="In"),W67,0)
B68: TX-0062 | C68: 46078 | D68: Owner Draw | F68: Owner salary / personal draw | I68: Bank Transfer | K68: Bank Account | L68: 20000 | O68: =IF(Z68=1,L68-W68,"") | P68: =IF(V68="","",IFERROR(INDEX(coa_Type,MATCH(V68,coa_Name,0)),"")) | Q68: =IF(Z68=1,IF(U68="In",K68&"",V68),"") | R68: =IF(Z68=1,IF(U68="In",V68,K68&""),"") | S68: =IF(X68<>"","⛔ "&X68&" — not posted",IF(Y68<>"","⚠ "&Y68,IF(Z68=1,"✓ OK",""))) | T68: =IF(AND(C68="",D68="",E68="",L68="",K68=""),1,0) | U68: =IFERROR(INDEX(tt_Dir,MATCH(D68,tt_Type,0)),"") | V68: =IF(D68="","",IFERROR(IF(INDEX(tt_Other,MATCH(D68,tt_Type,0))="",E68&"",INDEX(tt_Other,MATCH(D68,tt_Type,0))),"")) | W68: =IF(OR(TaxOn<>"Yes",NOT(ISNUMBER(M68))),0,IF(IFERROR(INDEX(tt_Tax,MATCH(D68,tt_Type,0)),"No")="Yes",M68,0)) | X68: =IF(T68=1,"",IF(C68="","Missing transaction date",IF(NOT(ISNUMBER(C68)),"Invalid date",IF(OR(C68<DATE(2000,1,1),C68>DATE(2099,12,31)),"Invalid date",IF(D68="","Select a type",IF(U68="","Unknown type: "&D68,IF(V68="","Select an account (Category)",IF(ISNA(MATCH(V68,coa_Name,0)),"Unknown account: "&V68,IF(K68="","Select Paid From / Deposited To",IF(ISNA(MATCH(K68,coa_Name,0)),"Unknown account: "&K68,IF(NOT(ISNUMBER(L68)),"Enter an amount",IF(L68=0,"Enter an amount",IF(ABS(W68)>ABS(L68),"Tax is larger than the amount",""))))))))))))) | Y68: =IF(OR(T68=1,X68<>""),"",IF(AND(B68<>"",COUNTIF(tx_ID,B68)>1),"Duplicate transaction ID",IF(AND(L68<0,D68<>"Adjustment"),"Negative amount — check this entry",IF(AND(D68="Customer Payment",G68=""),"Add the customer",IF(AND(D68="Customer Payment",OR(J68="",COUNTIF(ar_No,J68&"")=0)),"Invoice # in Reference not found on AR sheet",IF(AND(D68="Bill Payment",H68=""),"Add the vendor",IF(AND(D68="Bill Payment",OR(J68="",COUNTIFS(ap_No,J68&"",ap_Party,H68&"")=0)),"Bill # + vendor not found on AP sheet",IF(AND(ISNUMBER(M68),N(M68)<>0,W68=0),"Tax ignored (tax tracking off, or not allowed for this type)",IF(V68=K68&"","Same account on both sides",IF(AND(ISNUMBER(StartDate),C68<StartDate),"Date is before the accounting start date",IF(AND(D68<>"Adjustment",IFERROR(INDEX(coa_Pay,MATCH(K68&"",coa_Name,0)),"")<>"Yes"),"Paid From / Deposited To is not a payment account",""))))))))))) | Z68: =IF(AND(T68=0,X68=""),1,0) | AA68: =IF(Z68=1,IF(U68="In",L68,L68-W68),0) | AB68: =IF(Z68=1,IF(U68="In",L68-W68,L68),0) | AC68: =IF(AND(Z68=1,U68="Out"),W68,0) | AD68: =IF(AND(Z68=1,U68="In"),W68,0)
B69: TX-0063 | C69: 46079 | D69: Money In | E69: Product Sales | F69: GCash / online orders week 4 | I69: E-Wallet | K69: E-Wallet / Online Payments | L69: 17317.78 | M69: 1855.48 | O69: =IF(Z69=1,L69-W69,"") | P69: =IF(V69="","",IFERROR(INDEX(coa_Type,MATCH(V69,coa_Name,0)),"")) | Q69: =IF(Z69=1,IF(U69="In",K69&"",V69),"") | R69: =IF(Z69=1,IF(U69="In",V69,K69&""),"") | S69: =IF(X69<>"","⛔ "&X69&" — not posted",IF(Y69<>"","⚠ "&Y69,IF(Z69=1,"✓ OK",""))) | T69: =IF(AND(C69="",D69="",E69="",L69="",K69=""),1,0) | U69: =IFERROR(INDEX(tt_Dir,MATCH(D69,tt_Type,0)),"") | V69: =IF(D69="","",IFERROR(IF(INDEX(tt_Other,MATCH(D69,tt_Type,0))="",E69&"",INDEX(tt_Other,MATCH(D69,tt_Type,0))),"")) | W69: =IF(OR(TaxOn<>"Yes",NOT(ISNUMBER(M69))),0,IF(IFERROR(INDEX(tt_Tax,MATCH(D69,tt_Type,0)),"No")="Yes",M69,0)) | X69: =IF(T69=1,"",IF(C69="","Missing transaction date",IF(NOT(ISNUMBER(C69)),"Invalid date",IF(OR(C69<DATE(2000,1,1),C69>DATE(2099,12,31)),"Invalid date",IF(D69="","Select a type",IF(U69="","Unknown type: "&D69,IF(V69="","Select an account (Category)",IF(ISNA(MATCH(V69,coa_Name,0)),"Unknown account: "&V69,IF(K69="","Select Paid From / Deposited To",IF(ISNA(MATCH(K69,coa_Name,0)),"Unknown account: "&K69,IF(NOT(ISNUMBER(L69)),"Enter an amount",IF(L69=0,"Enter an amount",IF(ABS(W69)>ABS(L69),"Tax is larger than the amount",""))))))))))))) | Y69: =IF(OR(T69=1,X69<>""),"",IF(AND(B69<>"",COUNTIF(tx_ID,B69)>1),"Duplicate transaction ID",IF(AND(L69<0,D69<>"Adjustment"),"Negative amount — check this entry",IF(AND(D69="Customer Payment",G69=""),"Add the customer",IF(AND(D69="Customer Payment",OR(J69="",COUNTIF(ar_No,J69&"")=0)),"Invoice # in Reference not found on AR sheet",IF(AND(D69="Bill Payment",H69=""),"Add the vendor",IF(AND(D69="Bill Payment",OR(J69="",COUNTIFS(ap_No,J69&"",ap_Party,H69&"")=0)),"Bill # + vendor not found on AP sheet",IF(AND(ISNUMBER(M69),N(M69)<>0,W69=0),"Tax ignored (tax tracking off, or not allowed for this type)",IF(V69=K69&"","Same account on both sides",IF(AND(ISNUMBER(StartDate),C69<StartDate),"Date is before the accounting start date",IF(AND(D69<>"Adjustment",IFERROR(INDEX(coa_Pay,MATCH(K69&"",coa_Name,0)),"")<>"Yes"),"Paid From / Deposited To is not a payment account",""))))))))))) | Z69: =IF(AND(T69=0,X69=""),1,0) | AA69: =IF(Z69=1,IF(U69="In",L69,L69-W69),0) | AB69: =IF(Z69=1,IF(U69="In",L69-W69,L69),0) | AC69: =IF(AND(Z69=1,U69="Out"),W69,0) | AD69: =IF(AND(Z69=1,U69="In"),W69,0)
B70: TX-0064 | C70: 46080 | D70: Transfer | E70: Bank Account | F70: Cash deposit to bank | I70: Cash | K70: Cash on Hand | L70: 47500 | O70: =IF(Z70=1,L70-W70,"") | P70: =IF(V70="","",IFERROR(INDEX(coa_Type,MATCH(V70,coa_Name,0)),"")) | Q70: =IF(Z70=1,IF(U70="In",K70&"",V70),"") | R70: =IF(Z70=1,IF(U70="In",V70,K70&""),"") | S70: =IF(X70<>"","⛔ "&X70&" — not posted",IF(Y70<>"","⚠ "&Y70,IF(Z70=1,"✓ OK",""))) | T70: =IF(AND(C70="",D70="",E70="",L70="",K70=""),1,0) | U70: =IFERROR(INDEX(tt_Dir,MATCH(D70,tt_Type,0)),"") | V70: =IF(D70="","",IFERROR(IF(INDEX(tt_Other,MATCH(D70,tt_Type,0))="",E70&"",INDEX(tt_Other,MATCH(D70,tt_Type,0))),"")) | W70: =IF(OR(TaxOn<>"Yes",NOT(ISNUMBER(M70))),0,IF(IFERROR(INDEX(tt_Tax,MATCH(D70,tt_Type,0)),"No")="Yes",M70,0)) | X70: =IF(T70=1,"",IF(C70="","Missing transaction date",IF(NOT(ISNUMBER(C70)),"Invalid date",IF(OR(C70<DATE(2000,1,1),C70>DATE(2099,12,31)),"Invalid date",IF(D70="","Select a type",IF(U70="","Unknown type: "&D70,IF(V70="","Select an account (Category)",IF(ISNA(MATCH(V70,coa_Name,0)),"Unknown account: "&V70,IF(K70="","Select Paid From / Deposited To",IF(ISNA(MATCH(K70,coa_Name,0)),"Unknown account: "&K70,IF(NOT(ISNUMBER(L70)),"Enter an amount",IF(L70=0,"Enter an amount",IF(ABS(W70)>ABS(L70),"Tax is larger than the amount",""))))))))))))) | Y70: =IF(OR(T70=1,X70<>""),"",IF(AND(B70<>"",COUNTIF(tx_ID,B70)>1),"Duplicate transaction ID",IF(AND(L70<0,D70<>"Adjustment"),"Negative amount — check this entry",IF(AND(D70="Customer Payment",G70=""),"Add the customer",IF(AND(D70="Customer Payment",OR(J70="",COUNTIF(ar_No,J70&"")=0)),"Invoice # in Reference not found on AR sheet",IF(AND(D70="Bill Payment",H70=""),"Add the vendor",IF(AND(D70="Bill Payment",OR(J70="",COUNTIFS(ap_No,J70&"",ap_Party,H70&"")=0)),"Bill # + vendor not found on AP sheet",IF(AND(ISNUMBER(M70),N(M70)<>0,W70=0),"Tax ignored (tax tracking off, or not allowed for this type)",IF(V70=K70&"","Same account on both sides",IF(AND(ISNUMBER(StartDate),C70<StartDate),"Date is before the accounting start date",IF(AND(D70<>"Adjustment",IFERROR(INDEX(coa_Pay,MATCH(K70&"",coa_Name,0)),"")<>"Yes"),"Paid From / Deposited To is not a payment account",""))))))))))) | Z70: =IF(AND(T70=0,X70=""),1,0) | AA70: =IF(Z70=1,IF(U70="In",L70,L70-W70),0) | AB70: =IF(Z70=1,IF(U70="In",L70-W70,L70),0) | AC70: =IF(AND(Z70=1,U70="Out"),W70,0) | AD70: =IF(AND(Z70=1,U70="In"),W70,0)
B71: TX-0065 | C71: 46080 | D71: Money Out | E71: Bank & Payment Fees | F71: Monthly bank charge | I71: Bank Transfer | K71: Bank Account | L71: 150 | O71: =IF(Z71=1,L71-W71,"") | P71: =IF(V71="","",IFERROR(INDEX(coa_Type,MATCH(V71,coa_Name,0)),"")) | Q71: =IF(Z71=1,IF(U71="In",K71&"",V71),"") | R71: =IF(Z71=1,IF(U71="In",V71,K71&""),"") | S71: =IF(X71<>"","⛔ "&X71&" — not posted",IF(Y71<>"","⚠ "&Y71,IF(Z71=1,"✓ OK",""))) | T71: =IF(AND(C71="",D71="",E71="",L71="",K71=""),1,0) | U71: =IFERROR(INDEX(tt_Dir,MATCH(D71,tt_Type,0)),"") | V71: =IF(D71="","",IFERROR(IF(INDEX(tt_Other,MATCH(D71,tt_Type,0))="",E71&"",INDEX(tt_Other,MATCH(D71,tt_Type,0))),"")) | W71: =IF(OR(TaxOn<>"Yes",NOT(ISNUMBER(M71))),0,IF(IFERROR(INDEX(tt_Tax,MATCH(D71,tt_Type,0)),"No")="Yes",M71,0)) | X71: =IF(T71=1,"",IF(C71="","Missing transaction date",IF(NOT(ISNUMBER(C71)),"Invalid date",IF(OR(C71<DATE(2000,1,1),C71>DATE(2099,12,31)),"Invalid date",IF(D71="","Select a type",IF(U71="","Unknown type: "&D71,IF(V71="","Select an account (Category)",IF(ISNA(MATCH(V71,coa_Name,0)),"Unknown account: "&V71,IF(K71="","Select Paid From / Deposited To",IF(ISNA(MATCH(K71,coa_Name,0)),"Unknown account: "&K71,IF(NOT(ISNUMBER(L71)),"Enter an amount",IF(L71=0,"Enter an amount",IF(ABS(W71)>ABS(L71),"Tax is larger than the amount",""))))))))))))) | Y71: =IF(OR(T71=1,X71<>""),"",IF(AND(B71<>"",COUNTIF(tx_ID,B71)>1),"Duplicate transaction ID",IF(AND(L71<0,D71<>"Adjustment"),"Negative amount — check this entry",IF(AND(D71="Customer Payment",G71=""),"Add the customer",IF(AND(D71="Customer Payment",OR(J71="",COUNTIF(ar_No,J71&"")=0)),"Invoice # in Reference not found on AR sheet",IF(AND(D71="Bill Payment",H71=""),"Add the vendor",IF(AND(D71="Bill Payment",OR(J71="",COUNTIFS(ap_No,J71&"",ap_Party,H71&"")=0)),"Bill # + vendor not found on AP sheet",IF(AND(ISNUMBER(M71),N(M71)<>0,W71=0),"Tax ignored (tax tracking off, or not allowed for this type)",IF(V71=K71&"","Same account on both sides",IF(AND(ISNUMBER(StartDate),C71<StartDate),"Date is before the accounting start date",IF(AND(D71<>"Adjustment",IFERROR(INDEX(coa_Pay,MATCH(K71&"",coa_Name,0)),"")<>"Yes"),"Paid From / Deposited To is not a payment account",""))))))))))) | Z71: =IF(AND(T71=0,X71=""),1,0) | AA71: =IF(Z71=1,IF(U71="In",L71,L71-W71),0) | AB71: =IF(Z71=1,IF(U71="In",L71-W71,L71),0) | AC71: =IF(AND(Z71=1,U71="Out"),W71,0) | AD71: =IF(AND(Z71=1,U71="In"),W71,0)
B72: TX-0066 | C72: 46081 | D72: Transfer | E72: Bank Account | F72: E-wallet cash-out to bank | I72: Online Payment | K72: E-Wallet / Online Payments | L72: 44200 | O72: =IF(Z72=1,L72-W72,"") | P72: =IF(V72="","",IFERROR(INDEX(coa_Type,MATCH(V72,coa_Name,0)),"")) | Q72: =IF(Z72=1,IF(U72="In",K72&"",V72),"") | R72: =IF(Z72=1,IF(U72="In",V72,K72&""),"") | S72: =IF(X72<>"","⛔ "&X72&" — not posted",IF(Y72<>"","⚠ "&Y72,IF(Z72=1,"✓ OK",""))) | T72: =IF(AND(C72="",D72="",E72="",L72="",K72=""),1,0) | U72: =IFERROR(INDEX(tt_Dir,MATCH(D72,tt_Type,0)),"") | V72: =IF(D72="","",IFERROR(IF(INDEX(tt_Other,MATCH(D72,tt_Type,0))="",E72&"",INDEX(tt_Other,MATCH(D72,tt_Type,0))),"")) | W72: =IF(OR(TaxOn<>"Yes",NOT(ISNUMBER(M72))),0,IF(IFERROR(INDEX(tt_Tax,MATCH(D72,tt_Type,0)),"No")="Yes",M72,0)) | X72: =IF(T72=1,"",IF(C72="","Missing transaction date",IF(NOT(ISNUMBER(C72)),"Invalid date",IF(OR(C72<DATE(2000,1,1),C72>DATE(2099,12,31)),"Invalid date",IF(D72="","Select a type",IF(U72="","Unknown type: "&D72,IF(V72="","Select an account (Category)",IF(ISNA(MATCH(V72,coa_Name,0)),"Unknown account: "&V72,IF(K72="","Select Paid From / Deposited To",IF(ISNA(MATCH(K72,coa_Name,0)),"Unknown account: "&K72,IF(NOT(ISNUMBER(L72)),"Enter an amount",IF(L72=0,"Enter an amount",IF(ABS(W72)>ABS(L72),"Tax is larger than the amount",""))))))))))))) | Y72: =IF(OR(T72=1,X72<>""),"",IF(AND(B72<>"",COUNTIF(tx_ID,B72)>1),"Duplicate transaction ID",IF(AND(L72<0,D72<>"Adjustment"),"Negative amount — check this entry",IF(AND(D72="Customer Payment",G72=""),"Add the customer",IF(AND(D72="Customer Payment",OR(J72="",COUNTIF(ar_No,J72&"")=0)),"Invoice # in Reference not found on AR sheet",IF(AND(D72="Bill Payment",H72=""),"Add the vendor",IF(AND(D72="Bill Payment",OR(J72="",COUNTIFS(ap_No,J72&"",ap_Party,H72&"")=0)),"Bill # + vendor not found on AP sheet",IF(AND(ISNUMBER(M72),N(M72)<>0,W72=0),"Tax ignored (tax tracking off, or not allowed for this type)",IF(V72=K72&"","Same account on both sides",IF(AND(ISNUMBER(StartDate),C72<StartDate),"Date is before the accounting start date",IF(AND(D72<>"Adjustment",IFERROR(INDEX(coa_Pay,MATCH(K72&"",coa_Name,0)),"")<>"Yes"),"Paid From / Deposited To is not a payment account",""))))))))))) | Z72: =IF(AND(T72=0,X72=""),1,0) | AA72: =IF(Z72=1,IF(U72="In",L72,L72-W72),0) | AB72: =IF(Z72=1,IF(U72="In",L72-W72,L72),0) | AC72: =IF(AND(Z72=1,U72="Out"),W72,0) | AD72: =IF(AND(Z72=1,U72="In"),W72,0)
B73: TX-0067 | C73: 46081 | D73: Money Out | E73: Direct Labor | F73: Bakers' salaries (16th-end) | I73: Bank Transfer | K73: Bank Account | L73: 38000 | O73: =IF(Z73=1,L73-W73,"") | P73: =IF(V73="","",IFERROR(INDEX(coa_Type,MATCH(V73,coa_Name,0)),"")) | Q73: =IF(Z73=1,IF(U73="In",K73&"",V73),"") | R73: =IF(Z73=1,IF(U73="In",V73,K73&""),"") | S73: =IF(X73<>"","⛔ "&X73&" — not posted",IF(Y73<>"","⚠ "&Y73,IF(Z73=1,"✓ OK",""))) | T73: =IF(AND(C73="",D73="",E73="",L73="",K73=""),1,0) | U73: =IFERROR(INDEX(tt_Dir,MATCH(D73,tt_Type,0)),"") | V73: =IF(D73="","",IFERROR(IF(INDEX(tt_Other,MATCH(D73,tt_Type,0))="",E73&"",INDEX(tt_Other,MATCH(D73,tt_Type,0))),"")) | W73: =IF(OR(TaxOn<>"Yes",NOT(ISNUMBER(M73))),0,IF(IFERROR(INDEX(tt_Tax,MATCH(D73,tt_Type,0)),"No")="Yes",M73,0)) | X73: =IF(T73=1,"",IF(C73="","Missing transaction date",IF(NOT(ISNUMBER(C73)),"Invalid date",IF(OR(C73<DATE(2000,1,1),C73>DATE(2099,12,31)),"Invalid date",IF(D73="","Select a type",IF(U73="","Unknown type: "&D73,IF(V73="","Select an account (Category)",IF(ISNA(MATCH(V73,coa_Name,0)),"Unknown account: "&V73,IF(K73="","Select Paid From / Deposited To",IF(ISNA(MATCH(K73,coa_Name,0)),"Unknown account: "&K73,IF(NOT(ISNUMBER(L73)),"Enter an amount",IF(L73=0,"Enter an amount",IF(ABS(W73)>ABS(L73),"Tax is larger than the amount",""))))))))))))) | Y73: =IF(OR(T73=1,X73<>""),"",IF(AND(B73<>"",COUNTIF(tx_ID,B73)>1),"Duplicate transaction ID",IF(AND(L73<0,D73<>"Adjustment"),"Negative amount — check this entry",IF(AND(D73="Customer Payment",G73=""),"Add the customer",IF(AND(D73="Customer Payment",OR(J73="",COUNTIF(ar_No,J73&"")=0)),"Invoice # in Reference not found on AR sheet",IF(AND(D73="Bill Payment",H73=""),"Add the vendor",IF(AND(D73="Bill Payment",OR(J73="",COUNTIFS(ap_No,J73&"",ap_Party,H73&"")=0)),"Bill # + vendor not found on AP sheet",IF(AND(ISNUMBER(M73),N(M73)<>0,W73=0),"Tax ignored (tax tracking off, or not allowed for this type)",IF(V73=K73&"","Same account on both sides",IF(AND(ISNUMBER(StartDate),C73<StartDate),"Date is before the accounting start date",IF(AND(D73<>"Adjustment",IFERROR(INDEX(coa_Pay,MATCH(K73&"",coa_Name,0)),"")<>"Yes"),"Paid From / Deposited To is not a payment account",""))))))))))) | Z73: =IF(AND(T73=0,X73=""),1,0) | AA73: =IF(Z73=1,IF(U73="In",L73,L73-W73),0) | AB73: =IF(Z73=1,IF(U73="In",L73-W73,L73),0) | AC73: =IF(AND(Z73=1,U73="Out"),W73,0) | AD73: =IF(AND(Z73=1,U73="In"),W73,0)
B74: TX-0068 | C74: 46081 | D74: Money Out | E74: Salaries & Wages | F74: Cashier salary (16th-end) | I74: Bank Transfer | K74: Bank Account | L74: 9000 | O74: =IF(Z74=1,L74-W74,"") | P74: =IF(V74="","",IFERROR(INDEX(coa_Type,MATCH(V74,coa_Name,0)),"")) | Q74: =IF(Z74=1,IF(U74="In",K74&"",V74),"") | R74: =IF(Z74=1,IF(U74="In",V74,K74&""),"") | S74: =IF(X74<>"","⛔ "&X74&" — not posted",IF(Y74<>"","⚠ "&Y74,IF(Z74=1,"✓ OK",""))) | T74: =IF(AND(C74="",D74="",E74="",L74="",K74=""),1,0) | U74: =IFERROR(INDEX(tt_Dir,MATCH(D74,tt_Type,0)),"") | V74: =IF(D74="","",IFERROR(IF(INDEX(tt_Other,MATCH(D74,tt_Type,0))="",E74&"",INDEX(tt_Other,MATCH(D74,tt_Type,0))),"")) | W74: =IF(OR(TaxOn<>"Yes",NOT(ISNUMBER(M74))),0,IF(IFERROR(INDEX(tt_Tax,MATCH(D74,tt_Type,0)),"No")="Yes",M74,0)) | X74: =IF(T74=1,"",IF(C74="","Missing transaction date",IF(NOT(ISNUMBER(C74)),"Invalid date",IF(OR(C74<DATE(2000,1,1),C74>DATE(2099,12,31)),"Invalid date",IF(D74="","Select a type",IF(U74="","Unknown type: "&D74,IF(V74="","Select an account (Category)",IF(ISNA(MATCH(V74,coa_Name,0)),"Unknown account: "&V74,IF(K74="","Select Paid From / Deposited To",IF(ISNA(MATCH(K74,coa_Name,0)),"Unknown account: "&K74,IF(NOT(ISNUMBER(L74)),"Enter an amount",IF(L74=0,"Enter an amount",IF(ABS(W74)>ABS(L74),"Tax is larger than the amount",""))))))))))))) | Y74: =IF(OR(T74=1,X74<>""),"",IF(AND(B74<>"",COUNTIF(tx_ID,B74)>1),"Duplicate transaction ID",IF(AND(L74<0,D74<>"Adjustment"),"Negative amount — check this entry",IF(AND(D74="Customer Payment",G74=""),"Add the customer",IF(AND(D74="Customer Payment",OR(J74="",COUNTIF(ar_No,J74&"")=0)),"Invoice # in Reference not found on AR sheet",IF(AND(D74="Bill Payment",H74=""),"Add the vendor",IF(AND(D74="Bill Payment",OR(J74="",COUNTIFS(ap_No,J74&"",ap_Party,H74&"")=0)),"Bill # + vendor not found on AP sheet",IF(AND(ISNUMBER(M74),N(M74)<>0,W74=0),"Tax ignored (tax tracking off, or not allowed for this type)",IF(V74=K74&"","Same account on both sides",IF(AND(ISNUMBER(StartDate),C74<StartDate),"Date is before the accounting start date",IF(AND(D74<>"Adjustment",IFERROR(INDEX(coa_Pay,MATCH(K74&"",coa_Name,0)),"")<>"Yes"),"Paid From / Deposited To is not a payment account",""))))))))))) | Z74: =IF(AND(T74=0,X74=""),1,0) | AA74: =IF(Z74=1,IF(U74="In",L74,L74-W74),0) | AB74: =IF(Z74=1,IF(U74="In",L74-W74,L74),0) | AC74: =IF(AND(Z74=1,U74="Out"),W74,0) | AD74: =IF(AND(Z74=1,U74="In"),W74,0)
B75: TX-0069 | C75: 46081 | D75: Adjustment | E75: Depreciation | F75: Monthly depreciation of equipment | K75: Accumulated Depreciation | L75: 3000 | O75: =IF(Z75=1,L75-W75,"") | P75: =IF(V75="","",IFERROR(INDEX(coa_Type,MATCH(V75,coa_Name,0)),"")) | Q75: =IF(Z75=1,IF(U75="In",K75&"",V75),"") | R75: =IF(Z75=1,IF(U75="In",V75,K75&""),"") | S75: =IF(X75<>"","⛔ "&X75&" — not posted",IF(Y75<>"","⚠ "&Y75,IF(Z75=1,"✓ OK",""))) | T75: =IF(AND(C75="",D75="",E75="",L75="",K75=""),1,0) | U75: =IFERROR(INDEX(tt_Dir,MATCH(D75,tt_Type,0)),"") | V75: =IF(D75="","",IFERROR(IF(INDEX(tt_Other,MATCH(D75,tt_Type,0))="",E75&"",INDEX(tt_Other,MATCH(D75,tt_Type,0))),"")) | W75: =IF(OR(TaxOn<>"Yes",NOT(ISNUMBER(M75))),0,IF(IFERROR(INDEX(tt_Tax,MATCH(D75,tt_Type,0)),"No")="Yes",M75,0)) | X75: =IF(T75=1,"",IF(C75="","Missing transaction date",IF(NOT(ISNUMBER(C75)),"Invalid date",IF(OR(C75<DATE(2000,1,1),C75>DATE(2099,12,31)),"Invalid date",IF(D75="","Select a type",IF(U75="","Unknown type: "&D75,IF(V75="","Select an account (Category)",IF(ISNA(MATCH(V75,coa_Name,0)),"Unknown account: "&V75,IF(K75="","Select Paid From / Deposited To",IF(ISNA(MATCH(K75,coa_Name,0)),"Unknown account: "&K75,IF(NOT(ISNUMBER(L75)),"Enter an amount",IF(L75=0,"Enter an amount",IF(ABS(W75)>ABS(L75),"Tax is larger than the amount",""))))))))))))) | Y75: =IF(OR(T75=1,X75<>""),"",IF(AND(B75<>"",COUNTIF(tx_ID,B75)>1),"Duplicate transaction ID",IF(AND(L75<0,D75<>"Adjustment"),"Negative amount — check this entry",IF(AND(D75="Customer Payment",G75=""),"Add the customer",IF(AND(D75="Customer Payment",OR(J75="",COUNTIF(ar_No,J75&"")=0)),"Invoice # in Reference not found on AR sheet",IF(AND(D75="Bill Payment",H75=""),"Add the vendor",IF(AND(D75="Bill Payment",OR(J75="",COUNTIFS(ap_No,J75&"",ap_Party,H75&"")=0)),"Bill # + vendor not found on AP sheet",IF(AND(ISNUMBER(M75),N(M75)<>0,W75=0),"Tax ignored (tax tracking off, or not allowed for this type)",IF(V75=K75&"","Same account on both sides",IF(AND(ISNUMBER(StartDate),C75<StartDate),"Date is before the accounting start date",IF(AND(D75<>"Adjustment",IFERROR(INDEX(coa_Pay,MATCH(K75&"",coa_Name,0)),"")<>"Yes"),"Paid From / Deposited To is not a payment account",""))))))))))) | Z75: =IF(AND(T75=0,X75=""),1,0) | AA75: =IF(Z75=1,IF(U75="In",L75,L75-W75),0) | AB75: =IF(Z75=1,IF(U75="In",L75-W75,L75),0) | AC75: =IF(AND(Z75=1,U75="Out"),W75,0) | AD75: =IF(AND(Z75=1,U75="In"),W75,0)
B76: TX-0070 | C76: 46082 | D76: Money Out | E76: Rent | F76: Shop rent | I76: Bank Transfer | J76: RENT-03 | K76: Bank Account | L76: 28000 | M76: 3000 | O76: =IF(Z76=1,L76-W76,"") | P76: =IF(V76="","",IFERROR(INDEX(coa_Type,MATCH(V76,coa_Name,0)),"")) | Q76: =IF(Z76=1,IF(U76="In",K76&"",V76),"") | R76: =IF(Z76=1,IF(U76="In",V76,K76&""),"") | S76: =IF(X76<>"","⛔ "&X76&" — not posted",IF(Y76<>"","⚠ "&Y76,IF(Z76=1,"✓ OK",""))) | T76: =IF(AND(C76="",D76="",E76="",L76="",K76=""),1,0) | U76: =IFERROR(INDEX(tt_Dir,MATCH(D76,tt_Type,0)),"") | V76: =IF(D76="","",IFERROR(IF(INDEX(tt_Other,MATCH(D76,tt_Type,0))="",E76&"",INDEX(tt_Other,MATCH(D76,tt_Type,0))),"")) | W76: =IF(OR(TaxOn<>"Yes",NOT(ISNUMBER(M76))),0,IF(IFERROR(INDEX(tt_Tax,MATCH(D76,tt_Type,0)),"No")="Yes",M76,0)) | X76: =IF(T76=1,"",IF(C76="","Missing transaction date",IF(NOT(ISNUMBER(C76)),"Invalid date",IF(OR(C76<DATE(2000,1,1),C76>DATE(2099,12,31)),"Invalid date",IF(D76="","Select a type",IF(U76="","Unknown type: "&D76,IF(V76="","Select an account (Category)",IF(ISNA(MATCH(V76,coa_Name,0)),"Unknown account: "&V76,IF(K76="","Select Paid From / Deposited To",IF(ISNA(MATCH(K76,coa_Name,0)),"Unknown account: "&K76,IF(NOT(ISNUMBER(L76)),"Enter an amount",IF(L76=0,"Enter an amount",IF(ABS(W76)>ABS(L76),"Tax is larger than the amount",""))))))))))))) | Y76: =IF(OR(T76=1,X76<>""),"",IF(AND(B76<>"",COUNTIF(tx_ID,B76)>1),"Duplicate transaction ID",IF(AND(L76<0,D76<>"Adjustment"),"Negative amount — check this entry",IF(AND(D76="Customer Payment",G76=""),"Add the customer",IF(AND(D76="Customer Payment",OR(J76="",COUNTIF(ar_No,J76&"")=0)),"Invoice # in Reference not found on AR sheet",IF(AND(D76="Bill Payment",H76=""),"Add the vendor",IF(AND(D76="Bill Payment",OR(J76="",COUNTIFS(ap_No,J76&"",ap_Party,H76&"")=0)),"Bill # + vendor not found on AP sheet",IF(AND(ISNUMBER(M76),N(M76)<>0,W76=0),"Tax ignored (tax tracking off, or not allowed for this type)",IF(V76=K76&"","Same account on both sides",IF(AND(ISNUMBER(StartDate),C76<StartDate),"Date is before the accounting start date",IF(AND(D76<>"Adjustment",IFERROR(INDEX(coa_Pay,MATCH(K76&"",coa_Name,0)),"")<>"Yes"),"Paid From / Deposited To is not a payment account",""))))))))))) | Z76: =IF(AND(T76=0,X76=""),1,0) | AA76: =IF(Z76=1,IF(U76="In",L76,L76-W76),0) | AB76: =IF(Z76=1,IF(U76="In",L76-W76,L76),0) | AC76: =IF(AND(Z76=1,U76="Out"),W76,0) | AD76: =IF(AND(Z76=1,U76="In"),W76,0)
B77: TX-0071 | C77: 46084 | D77: Bill Payment | F77: Supplier payment | H77: Fresh Dairy Co. | I77: Bank Transfer | J77: FR-021 | K77: Bank Account | L77: 15771.18 | O77: =IF(Z77=1,L77-W77,"") | P77: =IF(V77="","",IFERROR(INDEX(coa_Type,MATCH(V77,coa_Name,0)),"")) | Q77: =IF(Z77=1,IF(U77="In",K77&"",V77),"") | R77: =IF(Z77=1,IF(U77="In",V77,K77&""),"") | S77: =IF(X77<>"","⛔ "&X77&" — not posted",IF(Y77<>"","⚠ "&Y77,IF(Z77=1,"✓ OK",""))) | T77: =IF(AND(C77="",D77="",E77="",L77="",K77=""),1,0) | U77: =IFERROR(INDEX(tt_Dir,MATCH(D77,tt_Type,0)),"") | V77: =IF(D77="","",IFERROR(IF(INDEX(tt_Other,MATCH(D77,tt_Type,0))="",E77&"",INDEX(tt_Other,MATCH(D77,tt_Type,0))),"")) | W77: =IF(OR(TaxOn<>"Yes",NOT(ISNUMBER(M77))),0,IF(IFERROR(INDEX(tt_Tax,MATCH(D77,tt_Type,0)),"No")="Yes",M77,0)) | X77: =IF(T77=1,"",IF(C77="","Missing transaction date",IF(NOT(ISNUMBER(C77)),"Invalid date",IF(OR(C77<DATE(2000,1,1),C77>DATE(2099,12,31)),"Invalid date",IF(D77="","Select a type",IF(U77="","Unknown type: "&D77,IF(V77="","Select an account (Category)",IF(ISNA(MATCH(V77,coa_Name,0)),"Unknown account: "&V77,IF(K77="","Select Paid From / Deposited To",IF(ISNA(MATCH(K77,coa_Name,0)),"Unknown account: "&K77,IF(NOT(ISNUMBER(L77)),"Enter an amount",IF(L77=0,"Enter an amount",IF(ABS(W77)>ABS(L77),"Tax is larger than the amount",""))))))))))))) | Y77: =IF(OR(T77=1,X77<>""),"",IF(AND(B77<>"",COUNTIF(tx_ID,B77)>1),"Duplicate transaction ID",IF(AND(L77<0,D77<>"Adjustment"),"Negative amount — check this entry",IF(AND(D77="Customer Payment",G77=""),"Add the customer",IF(AND(D77="Customer Payment",OR(J77="",COUNTIF(ar_No,J77&"")=0)),"Invoice # in Reference not found on AR sheet",IF(AND(D77="Bill Payment",H77=""),"Add the vendor",IF(AND(D77="Bill Payment",OR(J77="",COUNTIFS(ap_No,J77&"",ap_Party,H77&"")=0)),"Bill # + vendor not found on AP sheet",IF(AND(ISNUMBER(M77),N(M77)<>0,W77=0),"Tax ignored (tax tracking off, or not allowed for this type)",IF(V77=K77&"","Same account on both sides",IF(AND(ISNUMBER(StartDate),C77<StartDate),"Date is before the accounting start date",IF(AND(D77<>"Adjustment",IFERROR(INDEX(coa_Pay,MATCH(K77&"",coa_Name,0)),"")<>"Yes"),"Paid From / Deposited To is not a payment account",""))))))))))) | Z77: =IF(AND(T77=0,X77=""),1,0) | AA77: =IF(Z77=1,IF(U77="In",L77,L77-W77),0) | AB77: =IF(Z77=1,IF(U77="In",L77-W77,L77),0) | AC77: =IF(AND(Z77=1,U77="Out"),W77,0) | AD77: =IF(AND(Z77=1,U77="In"),W77,0)
B78: TX-0072 | C78: 46085 | D78: Money In | E78: Product Sales | F78: Counter sales week 1 | I78: Cash | K78: Cash on Hand | L78: 54153.2 | M78: 5802.13 | O78: =IF(Z78=1,L78-W78,"") | P78: =IF(V78="","",IFERROR(INDEX(coa_Type,MATCH(V78,coa_Name,0)),"")) | Q78: =IF(Z78=1,IF(U78="In",K78&"",V78),"") | R78: =IF(Z78=1,IF(U78="In",V78,K78&""),"") | S78: =IF(X78<>"","⛔ "&X78&" — not posted",IF(Y78<>"","⚠ "&Y78,IF(Z78=1,"✓ OK",""))) | T78: =IF(AND(C78="",D78="",E78="",L78="",K78=""),1,0) | U78: =IFERROR(INDEX(tt_Dir,MATCH(D78,tt_Type,0)),"") | V78: =IF(D78="","",IFERROR(IF(INDEX(tt_Other,MATCH(D78,tt_Type,0))="",E78&"",INDEX(tt_Other,MATCH(D78,tt_Type,0))),"")) | W78: =IF(OR(TaxOn<>"Yes",NOT(ISNUMBER(M78))),0,IF(IFERROR(INDEX(tt_Tax,MATCH(D78,tt_Type,0)),"No")="Yes",M78,0)) | X78: =IF(T78=1,"",IF(C78="","Missing transaction date",IF(NOT(ISNUMBER(C78)),"Invalid date",IF(OR(C78<DATE(2000,1,1),C78>DATE(2099,12,31)),"Invalid date",IF(D78="","Select a type",IF(U78="","Unknown type: "&D78,IF(V78="","Select an account (Category)",IF(ISNA(MATCH(V78,coa_Name,0)),"Unknown account: "&V78,IF(K78="","Select Paid From / Deposited To",IF(ISNA(MATCH(K78,coa_Name,0)),"Unknown account: "&K78,IF(NOT(ISNUMBER(L78)),"Enter an amount",IF(L78=0,"Enter an amount",IF(ABS(W78)>ABS(L78),"Tax is larger than the amount",""))))))))))))) | Y78: =IF(OR(T78=1,X78<>""),"",IF(AND(B78<>"",COUNTIF(tx_ID,B78)>1),"Duplicate transaction ID",IF(AND(L78<0,D78<>"Adjustment"),"Negative amount — check this entry",IF(AND(D78="Customer Payment",G78=""),"Add the customer",IF(AND(D78="Customer Payment",OR(J78="",COUNTIF(ar_No,J78&"")=0)),"Invoice # in Reference not found on AR sheet",IF(AND(D78="Bill Payment",H78=""),"Add the vendor",IF(AND(D78="Bill Payment",OR(J78="",COUNTIFS(ap_No,J78&"",ap_Party,H78&"")=0)),"Bill # + vendor not found on AP sheet",IF(AND(ISNUMBER(M78),N(M78)<>0,W78=0),"Tax ignored (tax tracking off, or not allowed for this type)",IF(V78=K78&"","Same account on both sides",IF(AND(ISNUMBER(StartDate),C78<StartDate),"Date is before the accounting start date",IF(AND(D78<>"Adjustment",IFERROR(INDEX(coa_Pay,MATCH(K78&"",coa_Name,0)),"")<>"Yes"),"Paid From / Deposited To is not a payment account",""))))))))))) | Z78: =IF(AND(T78=0,X78=""),1,0) | AA78: =IF(Z78=1,IF(U78="In",L78,L78-W78),0) | AB78: =IF(Z78=1,IF(U78="In",L78-W78,L78),0) | AC78: =IF(AND(Z78=1,U78="Out"),W78,0) | AD78: =IF(AND(Z78=1,U78="In"),W78,0)
B79: TX-0073 | C79: 46086 | D79: Money In | E79: Product Sales | F79: GCash / online orders week 1 | I79: E-Wallet | K79: E-Wallet / Online Payments | L79: 22503.88 | M79: 2411.13 | O79: =IF(Z79=1,L79-W79,"") | P79: =IF(V79="","",IFERROR(INDEX(coa_Type,MATCH(V79,coa_Name,0)),"")) | Q79: =IF(Z79=1,IF(U79="In",K79&"",V79),"") | R79: =IF(Z79=1,IF(U79="In",V79,K79&""),"") | S79: =IF(X79<>"","⛔ "&X79&" — not posted",IF(Y79<>"","⚠ "&Y79,IF(Z79=1,"✓ OK",""))) | T79: =IF(AND(C79="",D79="",E79="",L79="",K79=""),1,0) | U79: =IFERROR(INDEX(tt_Dir,MATCH(D79,tt_Type,0)),"") | V79: =IF(D79="","",IFERROR(IF(INDEX(tt_Other,MATCH(D79,tt_Type,0))="",E79&"",INDEX(tt_Other,MATCH(D79,tt_Type,0))),"")) | W79: =IF(OR(TaxOn<>"Yes",NOT(ISNUMBER(M79))),0,IF(IFERROR(INDEX(tt_Tax,MATCH(D79,tt_Type,0)),"No")="Yes",M79,0)) | X79: =IF(T79=1,"",IF(C79="","Missing transaction date",IF(NOT(ISNUMBER(C79)),"Invalid date",IF(OR(C79<DATE(2000,1,1),C79>DATE(2099,12,31)),"Invalid date",IF(D79="","Select a type",IF(U79="","Unknown type: "&D79,IF(V79="","Select an account (Category)",IF(ISNA(MATCH(V79,coa_Name,0)),"Unknown account: "&V79,IF(K79="","Select Paid From / Deposited To",IF(ISNA(MATCH(K79,coa_Name,0)),"Unknown account: "&K79,IF(NOT(ISNUMBER(L79)),"Enter an amount",IF(L79=0,"Enter an amount",IF(ABS(W79)>ABS(L79),"Tax is larger than the amount",""))))))))))))) | Y79: =IF(OR(T79=1,X79<>""),"",IF(AND(B79<>"",COUNTIF(tx_ID,B79)>1),"Duplicate transaction ID",IF(AND(L79<0,D79<>"Adjustment"),"Negative amount — check this entry",IF(AND(D79="Customer Payment",G79=""),"Add the customer",IF(AND(D79="Customer Payment",OR(J79="",COUNTIF(ar_No,J79&"")=0)),"Invoice # in Reference not found on AR sheet",IF(AND(D79="Bill Payment",H79=""),"Add the vendor",IF(AND(D79="Bill Payment",OR(J79="",COUNTIFS(ap_No,J79&"",ap_Party,H79&"")=0)),"Bill # + vendor not found on AP sheet",IF(AND(ISNUMBER(M79),N(M79)<>0,W79=0),"Tax ignored (tax tracking off, or not allowed for this type)",IF(V79=K79&"","Same account on both sides",IF(AND(ISNUMBER(StartDate),C79<StartDate),"Date is before the accounting start date",IF(AND(D79<>"Adjustment",IFERROR(INDEX(coa_Pay,MATCH(K79&"",coa_Name,0)),"")<>"Yes"),"Paid From / Deposited To is not a payment account",""))))))))))) | Z79: =IF(AND(T79=0,X79=""),1,0) | AA79: =IF(Z79=1,IF(U79="In",L79,L79-W79),0) | AB79: =IF(Z79=1,IF(U79="In",L79-W79,L79),0) | AC79: =IF(AND(Z79=1,U79="Out"),W79,0) | AD79: =IF(AND(Z79=1,U79="In"),W79,0)
B80: TX-0074 | C80: 46086 | D80: Transfer | E80: Credit Card | F80: Credit card payment | I80: Bank Transfer | K80: Bank Account | L80: 7039.97 | O80: =IF(Z80=1,L80-W80,"") | P80: =IF(V80="","",IFERROR(INDEX(coa_Type,MATCH(V80,coa_Name,0)),"")) | Q80: =IF(Z80=1,IF(U80="In",K80&"",V80),"") | R80: =IF(Z80=1,IF(U80="In",V80,K80&""),"") | S80: =IF(X80<>"","⛔ "&X80&" — not posted",IF(Y80<>"","⚠ "&Y80,IF(Z80=1,"✓ OK",""))) | T80: =IF(AND(C80="",D80="",E80="",L80="",K80=""),1,0) | U80: =IFERROR(INDEX(tt_Dir,MATCH(D80,tt_Type,0)),"") | V80: =IF(D80="","",IFERROR(IF(INDEX(tt_Other,MATCH(D80,tt_Type,0))="",E80&"",INDEX(tt_Other,MATCH(D80,tt_Type,0))),"")) | W80: =IF(OR(TaxOn<>"Yes",NOT(ISNUMBER(M80))),0,IF(IFERROR(INDEX(tt_Tax,MATCH(D80,tt_Type,0)),"No")="Yes",M80,0)) | X80: =IF(T80=1,"",IF(C80="","Missing transaction date",IF(NOT(ISNUMBER(C80)),"Invalid date",IF(OR(C80<DATE(2000,1,1),C80>DATE(2099,12,31)),"Invalid date",IF(D80="","Select a type",IF(U80="","Unknown type: "&D80,IF(V80="","Select an account (Category)",IF(ISNA(MATCH(V80,coa_Name,0)),"Unknown account: "&V80,IF(K80="","Select Paid From / Deposited To",IF(ISNA(MATCH(K80,coa_Name,0)),"Unknown account: "&K80,IF(NOT(ISNUMBER(L80)),"Enter an amount",IF(L80=0,"Enter an amount",IF(ABS(W80)>ABS(L80),"Tax is larger than the amount",""))))))))))))) | Y80: =IF(OR(T80=1,X80<>""),"",IF(AND(B80<>"",COUNTIF(tx_ID,B80)>1),"Duplicate transaction ID",IF(AND(L80<0,D80<>"Adjustment"),"Negative amount — check this entry",IF(AND(D80="Customer Payment",G80=""),"Add the customer",IF(AND(D80="Customer Payment",OR(J80="",COUNTIF(ar_No,J80&"")=0)),"Invoice # in Reference not found on AR sheet",IF(AND(D80="Bill Payment",H80=""),"Add the vendor",IF(AND(D80="Bill Payment",OR(J80="",COUNTIFS(ap_No,J80&"",ap_Party,H80&"")=0)),"Bill # + vendor not found on AP sheet",IF(AND(ISNUMBER(M80),N(M80)<>0,W80=0),"Tax ignored (tax tracking off, or not allowed for this type)",IF(V80=K80&"","Same account on both sides",IF(AND(ISNUMBER(StartDate),C80<StartDate),"Date is before the accounting start date",IF(AND(D80<>"Adjustment",IFERROR(INDEX(coa_Pay,MATCH(K80&"",coa_Name,0)),"")<>"Yes"),"Paid From / Deposited To is not a payment account",""))))))))))) | Z80: =IF(AND(T80=0,X80=""),1,0) | AA80: =IF(Z80=1,IF(U80="In",L80,L80-W80),0) | AB80: =IF(Z80=1,IF(U80="In",L80-W80,L80),0) | AC80: =IF(AND(Z80=1,U80="Out"),W80,0) | AD80: =IF(AND(Z80=1,U80="In"),W80,0)
B81: TX-0075 | C81: 46087 | D81: Transfer | E81: Bank Account | F81: Cash deposit to bank | I81: Cash | K81: Cash on Hand | L81: 46000 | O81: =IF(Z81=1,L81-W81,"") | P81: =IF(V81="","",IFERROR(INDEX(coa_Type,MATCH(V81,coa_Name,0)),"")) | Q81: =IF(Z81=1,IF(U81="In",K81&"",V81),"") | R81: =IF(Z81=1,IF(U81="In",V81,K81&""),"") | S81: =IF(X81<>"","⛔ "&X81&" — not posted",IF(Y81<>"","⚠ "&Y81,IF(Z81=1,"✓ OK",""))) | T81: =IF(AND(C81="",D81="",E81="",L81="",K81=""),1,0) | U81: =IFERROR(INDEX(tt_Dir,MATCH(D81,tt_Type,0)),"") | V81: =IF(D81="","",IFERROR(IF(INDEX(tt_Other,MATCH(D81,tt_Type,0))="",E81&"",INDEX(tt_Other,MATCH(D81,tt_Type,0))),"")) | W81: =IF(OR(TaxOn<>"Yes",NOT(ISNUMBER(M81))),0,IF(IFERROR(INDEX(tt_Tax,MATCH(D81,tt_Type,0)),"No")="Yes",M81,0)) | X81: =IF(T81=1,"",IF(C81="","Missing transaction date",IF(NOT(ISNUMBER(C81)),"Invalid date",IF(OR(C81<DATE(2000,1,1),C81>DATE(2099,12,31)),"Invalid date",IF(D81="","Select a type",IF(U81="","Unknown type: "&D81,IF(V81="","Select an account (Category)",IF(ISNA(MATCH(V81,coa_Name,0)),"Unknown account: "&V81,IF(K81="","Select Paid From / Deposited To",IF(ISNA(MATCH(K81,coa_Name,0)),"Unknown account: "&K81,IF(NOT(ISNUMBER(L81)),"Enter an amount",IF(L81=0,"Enter an amount",IF(ABS(W81)>ABS(L81),"Tax is larger than the amount",""))))))))))))) | Y81: =IF(OR(T81=1,X81<>""),"",IF(AND(B81<>"",COUNTIF(tx_ID,B81)>1),"Duplicate transaction ID",IF(AND(L81<0,D81<>"Adjustment"),"Negative amount — check this entry",IF(AND(D81="Customer Payment",G81=""),"Add the customer",IF(AND(D81="Customer Payment",OR(J81="",COUNTIF(ar_No,J81&"")=0)),"Invoice # in Reference not found on AR sheet",IF(AND(D81="Bill Payment",H81=""),"Add the vendor",IF(AND(D81="Bill Payment",OR(J81="",COUNTIFS(ap_No,J81&"",ap_Party,H81&"")=0)),"Bill # + vendor not found on AP sheet",IF(AND(ISNUMBER(M81),N(M81)<>0,W81=0),"Tax ignored (tax tracking off, or not allowed for this type)",IF(V81=K81&"","Same account on both sides",IF(AND(ISNUMBER(StartDate),C81<StartDate),"Date is before the accounting start date",IF(AND(D81<>"Adjustment",IFERROR(INDEX(coa_Pay,MATCH(K81&"",coa_Name,0)),"")<>"Yes"),"Paid From / Deposited To is not a payment account",""))))))))))) | Z81: =IF(AND(T81=0,X81=""),1,0) | AA81: =IF(Z81=1,IF(U81="In",L81,L81-W81),0) | AB81: =IF(Z81=1,IF(U81="In",L81-W81,L81),0) | AC81: =IF(AND(Z81=1,U81="Out"),W81,0) | AD81: =IF(AND(Z81=1,U81="In"),W81,0)
B82: TX-0076 | C82: 46087 | D82: Money Out | E82: Other Direct Costs | F82: Boxes & paper bags (market) | I82: Cash | K82: Cash on Hand | L82: 4022.28 | M82: 430.96 | O82: =IF(Z82=1,L82-W82,"") | P82: =IF(V82="","",IFERROR(INDEX(coa_Type,MATCH(V82,coa_Name,0)),"")) | Q82: =IF(Z82=1,IF(U82="In",K82&"",V82),"") | R82: =IF(Z82=1,IF(U82="In",V82,K82&""),"") | S82: =IF(X82<>"","⛔ "&X82&" — not posted",IF(Y82<>"","⚠ "&Y82,IF(Z82=1,"✓ OK",""))) | T82: =IF(AND(C82="",D82="",E82="",L82="",K82=""),1,0) | U82: =IFERROR(INDEX(tt_Dir,MATCH(D82,tt_Type,0)),"") | V82: =IF(D82="","",IFERROR(IF(INDEX(tt_Other,MATCH(D82,tt_Type,0))="",E82&"",INDEX(tt_Other,MATCH(D82,tt_Type,0))),"")) | W82: =IF(OR(TaxOn<>"Yes",NOT(ISNUMBER(M82))),0,IF(IFERROR(INDEX(tt_Tax,MATCH(D82,tt_Type,0)),"No")="Yes",M82,0)) | X82: =IF(T82=1,"",IF(C82="","Missing transaction date",IF(NOT(ISNUMBER(C82)),"Invalid date",IF(OR(C82<DATE(2000,1,1),C82>DATE(2099,12,31)),"Invalid date",IF(D82="","Select a type",IF(U82="","Unknown type: "&D82,IF(V82="","Select an account (Category)",IF(ISNA(MATCH(V82,coa_Name,0)),"Unknown account: "&V82,IF(K82="","Select Paid From / Deposited To",IF(ISNA(MATCH(K82,coa_Name,0)),"Unknown account: "&K82,IF(NOT(ISNUMBER(L82)),"Enter an amount",IF(L82=0,"Enter an amount",IF(ABS(W82)>ABS(L82),"Tax is larger than the amount",""))))))))))))) | Y82: =IF(OR(T82=1,X82<>""),"",IF(AND(B82<>"",COUNTIF(tx_ID,B82)>1),"Duplicate transaction ID",IF(AND(L82<0,D82<>"Adjustment"),"Negative amount — check this entry",IF(AND(D82="Customer Payment",G82=""),"Add the customer",IF(AND(D82="Customer Payment",OR(J82="",COUNTIF(ar_No,J82&"")=0)),"Invoice # in Reference not found on AR sheet",IF(AND(D82="Bill Payment",H82=""),"Add the vendor",IF(AND(D82="Bill Payment",OR(J82="",COUNTIFS(ap_No,J82&"",ap_Party,H82&"")=0)),"Bill # + vendor not found on AP sheet",IF(AND(ISNUMBER(M82),N(M82)<>0,W82=0),"Tax ignored (tax tracking off, or not allowed for this type)",IF(V82=K82&"","Same account on both sides",IF(AND(ISNUMBER(StartDate),C82<StartDate),"Date is before the accounting start date",IF(AND(D82<>"Adjustment",IFERROR(INDEX(coa_Pay,MATCH(K82&"",coa_Name,0)),"")<>"Yes"),"Paid From / Deposited To is not a payment account",""))))))))))) | Z82: =IF(AND(T82=0,X82=""),1,0) | AA82: =IF(Z82=1,IF(U82="In",L82,L82-W82),0) | AB82: =IF(Z82=1,IF(U82="In",L82-W82,L82),0) | AC82: =IF(AND(Z82=1,U82="Out"),W82,0) | AD82: =IF(AND(Z82=1,U82="In"),W82,0)
